Workbook

Sheet Cover
A1: CASCADE OUTDOOR MANUFACTURING
A2: Corporate FP&A Budgeting & Forecasting Model
A4: Purpose
A5: Integrated financial planning model supporting budgeting, forecasting, scenario analysis, and management decision-making.
A7: Historical Period | B7: FY2023–FY2025
A8: Planning Period | B8: FY2026–FY2028
A10: Primary Tool | B10: Microsoft Excel for the Web
A11: Supporting Tool | B11: Power BI Desktop
A13: Model Status | B13: In Development
A15: Prepared for | B15: FP&A / Financial Business Intelligence Analysis

Sheet Control Panel
A1: Cascade Outdoor Manufacturing Control Panel
A3: Corporate FP&A Budgeting & Forecasting Model
A4: Company | B4: Cascade Outdoor Manufacturing
A5: Historical Start | B5: 44927
A6: Historical End | B6: 46022
A7: Forecast Start | B7: 46023
A8: Forecast End | B8: 47118
A10: Model QA Status | B10: ='Model QA'!D23 -> PASS
A11: Active Forecast Scenario | B11: ='Forecast Model'!B4 -> Base case
A12: Forecast Period | B12: 2026–2028
A13: 2028 Base Case Revenue | B13: ='Forecast Model'!E10 -> 6108131.1
A14: 2028 Base Case Operating Income | B14: ='Forecast Model'!E16 -> 1375445.1
A15: 2028 Base Case Free Cash Flow | B15: ='Cash Flow Plan'!E14 -> 1254249.1
A16: 2028 Ending Cash | B16: ='Cash Flow Plan'!E24 -> 4858967.8
A19: Management Forecast Summary
A21: Metric | B21: 2026 Forecast | C21: 2027 Forecast | D21: 2028 Forecast
A22: Revenue | B22: ='Forecast Model'!C10 -> 5247701.1 | C22: ='Forecast Model'!D10 -> 5661594 | D22: ='Forecast Model'!E10 -> 6108131.1
A23: Revenue Growth | B23: ='Forecast Model'!C11 -> 0.078871266 | C23: ='Forecast Model'!D11 -> 0.078871266 | D23: ='Forecast Model'!E11 -> 0.078871266
A24: Gross Profit | B24: ='Forecast Model'!C12 -> 2177796 | C24: ='Forecast Model'!D12 -> 2349561.5 | D24: ='Forecast Model'!E12 -> 2534874.4
A25: Gross Margin | B25: ='Forecast Model'!C13 -> 0.415 | C25: ='Forecast Model'!D13 -> 0.415 | D25: ='Forecast Model'!E13 -> 0.415
A26: Operating Expenses | B26: ='Forecast Model'!C14 -> -1051600.2 | C26: ='Forecast Model'!D14 -> -1104199.3 | D26: ='Forecast Model'!E14 -> -1159429.2
A27: Operating Income | B27: ='Forecast Model'!C16 -> 1126195.8 | C27: ='Forecast Model'!D16 -> 1245362.2 | D27: ='Forecast Model'!E16 -> 1375445.1
A28: Operating Margin | B28: ='Forecast Model'!C17 -> 0.21460745 | C28: ='Forecast Model'!D17 -> 0.21996671 | D28: ='Forecast Model'!E17 -> 0.22518265
A29: Net Income | B29: ='Forecast Model'!C18 -> 969654.55 | C29: ='Forecast Model'!D18 -> 1072256.9 | D29: ='Forecast Model'!E18 -> 1184258.3
A30: Free Cash Flow | B30: ='Cash Flow Plan'!C14 -> 863795.76 | C30: ='Cash Flow Plan'!D14 -> 1051842.2 | D30: ='Cash Flow Plan'!E14 -> 1254249.1
A31: Ending Cash | B31: ='Cash Flow Plan'!C24 -> 2552876.5 | C31: ='Cash Flow Plan'!D24 -> 3604718.7 | D31: ='Cash Flow Plan'!E24 -> 4858967.8
A32: Total Headcount | B32: ='Headcount Plan'!C12 -> 97 | C32: ='Headcount Plan'!D12 -> 102 | D32: ='Headcount Plan'!E12 -> 107
A33: Employment Cost | B33: ='Headcount Plan'!C71 -> 6171580.8 | C33: ='Headcount Plan'!D71 -> 6721122.7 | D33: ='Headcount Plan'!E71 -> 7301572.4
A34: Capital Expenditures | B34: ='CapEx Plan'!C12 -> 430500 | C34: ='CapEx Plan'!D12 -> 452025 | D34: ='CapEx Plan'!E12 -> 474626.25
A36: Three-Year Revenue CAGR | B36: =('Forecast Model'!E10/'Forecast Model'!B10)^(1/3)-1 -> 0.078871266
A37: Operating Margin Change | B37: ='Forecast Model'!E17-'Forecast Model'!B17 -> 0.01608173
A38: 2026–2028 Free Cash Flow Growth | B38: =('Cash Flow Plan'!E14/'Cash Flow Plan'!C14)^(1/2)-1 -> 0.20499813
A39: Management Reporting Status | B39: =IF(AND(B10="PASS",B11="Base case"),"READY","REVIEW") -> READY
A42: Forecast Driver Analysis
A44: Metric | B44: 2026 | C44: 2027 | D44: 2028 | E44: 2026–2028 Change
A45: Revenue | B45: ='Forecast Model'!C10 -> 5247701.1 | C45: ='Forecast Model'!D10 -> 5661594 | D45: ='Forecast Model'!E10 -> 6108131.1 | E45: =D45-B45 -> 860429.92
A46: Revenue Growth | B46: ='Forecast Model'!C11 -> 0.078871266 | C46: ='Forecast Model'!D11 -> 0.078871266 | D46: ='Forecast Model'!E11 -> 0.078871266 | E46: =D46-B46 -> 0
A47: Gross Margin | B47: ='Forecast Model'!C13 -> 0.415 | C47: ='Forecast Model'!D13 -> 0.415 | D47: ='Forecast Model'!E13 -> 0.415 | E47: =D47-B47 -> 0
A48: Operating Expenses | B48: ='Forecast Model'!C14 -> -1051600.2 | C48: ='Forecast Model'!D14 -> -1104199.3 | D48: ='Forecast Model'!E14 -> -1159429.2 | E48: =D48-B48 -> -107829.03
A49: Operating Income | B49: ='Forecast Model'!C16 -> 1126195.8 | C49: ='Forecast Model'!D16 -> 1245362.2 | D49: ='Forecast Model'!E16 -> 1375445.1 | E49: =D49-B49 -> 249249.38
A50: Operating Margin | B50: ='Forecast Model'!C17 -> 0.21460745 | C50: ='Forecast Model'!D17 -> 0.21996671 | D50: ='Forecast Model'!E17 -> 0.22518265 | E50: =D50-B50 -> 0.0105752
A51: Net Income | B51: ='Forecast Model'!C18 -> 969654.55 | C51: ='Forecast Model'!D18 -> 1072256.9 | D51: ='Forecast Model'!E18 -> 1184258.3 | E51: =D51-B51 -> 214603.72
A52: Free Cash Flow | B52: ='Cash Flow Plan'!C14 -> 863795.76 | C52: ='Cash Flow Plan'!D14 -> 1051842.2 | D52: ='Cash Flow Plan'!E14 -> 1254249.1 | E52: =D52-B52 -> 390453.38
A53: Ending Cash | B53: ='Cash Flow Plan'!C24 -> 2552876.5 | C53: ='Cash Flow Plan'!D24 -> 3604718.7 | D53: ='Cash Flow Plan'!E24 -> 4858967.8 | E53: =D53-B53 -> 2306091.4
A55: Revenue CAGR | B55: =('Forecast Model'!E10/'Forecast Model'!C10)^(1/2)-1 -> 0.078871266
A56: Operating Margin Expansion | B56: ='Forecast Model'!E17-'Forecast Model'!C17 -> 0.0105752
A57: Free Cash Flow CAGR | B57: =('Cash Flow Plan'!E14/'Cash Flow Plan'!C14)^(1/2)-1 -> 0.20499813
A58: Management Interpretation | B58: =IF(AND( 'Forecast Model'!E10>'Forecast Model'!C10, 'Forecast Model'!E17>='Forecast Model'!C17, 'Cash Flow Plan'!E14>'Cash Flow Plan'!C14), "Positive forecast trajectory", "Review forecast trajectory") -> Positive forecast trajectory
A61: Historical-to-Forecast Variance Analysis
A63: Metric | B63: 2025 Actual | C63: 2026 Forecast | D63: 2027 Forecast | E63: 2028 Forecast | F63: 2025–2028 Change
A64: Revenue | B64: ='Forecast Model'!B10 -> 4864066.1 | C64: ='Forecast Model'!C10 -> 5247701.1 | D64: ='Forecast Model'!D10 -> 5661594 | E64: ='Forecast Model'!E10 -> 6108131.1 | F64: =E64-B64 -> 1244065
A65: Revenue Growth | B65: ='Forecast Model'!B11 -> 0 | C65: ='Forecast Model'!C11 -> 0.078871266 | D65: ='Forecast Model'!D11 -> 0.078871266 | E65: ='Forecast Model'!E11 -> 0.078871266 | F65: =E65-B65 -> 0.078871266
A66: Gross Profit | B66: ='Forecast Model'!B12 -> 2018587.4 | C66: ='Forecast Model'!C12 -> 2177796 | D66: ='Forecast Model'!D12 -> 2349561.5 | E66: ='Forecast Model'!E12 -> 2534874.4 | F66: =E66-B66 -> 516286.96
A67: Gross Margin | B67: ='Forecast Model'!B13 -> 0.415 | C67: ='Forecast Model'!C13 -> 0.415 | D67: ='Forecast Model'!D13 -> 0.415 | E67: ='Forecast Model'!E13 -> 0.415 | F67: =E67-B67 -> 0
A68: Operating Expenses | B68: ='Forecast Model'!B14 -> -1001506.7 | C68: ='Forecast Model'!C14 -> -1051600.2 | D68: ='Forecast Model'!D14 -> -1104199.3 | E68: ='Forecast Model'!E14 -> -1159429.2 | F68: =E68-B68 -> -157922.51
A69: Operating Income | B69: ='Forecast Model'!B16 -> 1017080.7 | C69: ='Forecast Model'!C16 -> 1126195.8 | D69: ='Forecast Model'!D16 -> 1245362.2 | E69: ='Forecast Model'!E16 -> 1375445.1 | F69: =E69-B69 -> 358364.45
A70: Operating Margin | B70: ='Forecast Model'!B17 -> 0.20910092 | C70: ='Forecast Model'!C17 -> 0.21460745 | D70: ='Forecast Model'!D17 -> 0.21996671 | E70: ='Forecast Model'!E17 -> 0.22518265 | F70: =E70-B70 -> 0.01608173
A71: Net Income | B71: ='Forecast Model'!B18 -> 875531.89 | C71: ='Forecast Model'!C18 -> 969654.55 | D71: ='Forecast Model'!D18 -> 1072256.9 | E71: ='Forecast Model'!E18 -> 1184258.3 | F71: =E71-B71 -> 308726.38
A72: Free Cash Flow | B72: ='Cash Flow Plan'!B14 -> 689080.7 | C72: ='Cash Flow Plan'!C14 -> 863795.76 | D72: ='Cash Flow Plan'!D14 -> 1051842.2 | E72: ='Cash Flow Plan'!E14 -> 1254249.1 | F72: =E72-B72 -> 565168.45
A73: Ending Cash | C73: ='Cash Flow Plan'!C24 -> 2552876.5 | D73: ='Cash Flow Plan'!D24 -> 3604718.7 | E73: ='Cash Flow Plan'!E24 -> 4858967.8 | F73: =E73-B73 -> 4858967.8
A75: 2025–2028 Revenue Growth | B75: ='Forecast Model'!E10/'Forecast Model'!B10-1 -> 0.25576646
A76: 2025–2028 Operating Income Growth | B76: ='Forecast Model'!E16/'Forecast Model'!B16-1 -> 0.35234613
A77: 2025–2028 Net Income Growth | B77: ='Forecast Model'!E18/'Forecast Model'!B18-1 -> 0.3526158
A78: Operating Margin Expansion | B78: ='Forecast Model'!E17-'Forecast Model'!B17 -> 0.01608173
A79: Management Interpretation | B79: =IF(AND('Forecast Model'!E10>'Forecast Model'!B10,'Forecast Model'!E16>'Forecast Model'!B16,'Forecast Model'!E17>='Forecast Model'!B17),"Forecast indicates stronger scale and profitability","Review forecast profitability") -> Forecast indicates stronger scale and profitability
A81: Scenario Analysis
A82: Scenario | B82: 2028 Revenue | C82: 2028 Operating Income | D82: 2028 Free Cash Flow | E82: Revenue vs Base | F82: FCF vs Base
A83: Base Case | B83: ='Scenario Analysis'!B59 -> 6108131.1 | C83: ='Scenario Analysis'!B60 -> 2534874.4 | D83: ='Scenario Analysis'!B62 -> 2413678.4
A84: Best Case | B84: ='Scenario Analysis'!C59 -> 6631974.6 | C84: ='Scenario Analysis'!C60 -> 2818589.2 | D84: ='Scenario Analysis'!C62 -> 2697393.2 | E84: =B84-$B$83 -> 523843.58 | F84: =D84-$D$83 -> 283714.83
A85: Worst Case | B85: ='Scenario Analysis'!D59 -> 5612625.1 | C85: ='Scenario Analysis'!D60 -> 2273113.2 | D85: ='Scenario Analysis'!D62 -> 2151917.2 | E85: =B85-$B$83 -> -495505.99 | F85: =D85-$D$83 -> -261761.23
A87: Scenario Range Analysis
A89: Metric | B89: Best Case | C89: Worst Case | D89: Best-to-Worst-Range
A90: 2028 Revenue | B90: ='Scenario Analysis'!C59 -> 6631974.6 | C90: ='Scenario Analysis'!D59 -> 5612625.1 | D90: =B90-C90 -> 1019349.6
A91: 2028 Operating Income | B91: ='Scenario Analysis'!C60 -> 2818589.2 | C91: ='Scenario Analysis'!D60 -> 2273113.2 | D91: =B91-C91 -> 545476.06
A92: 2028 Free Cash Flow | B92: ='Scenario Analysis'!C62 -> 2697393.2 | C92: ='Scenario Analysis'!D62 -> 2151917.2 | D92: =B92-C92 -> 545476.06
A94: Management Interpretation | B94: Revenue Risk | C94: The 2028 revenue range demonstrates the sensitivity of long-term results to changes in the revenue growth assumption.
A96: Profitability Risk | B96: Gross margin and operating expense assumptions create additional upside or downside beyond revenue growth, resulting in a meaningful range of operating income outcomes.
A97: Cash Flow Risk | B97: Free cash flow remains positive across all scenarios, but weaker growth and margin performance reduce the cash available for reinvestment and other strategic uses.
A98: Management Focus | B98: Management should prioritize sustainable revenue growth, gross margin protection, and disciplined operating expense management to preserve forecast profitability and cash generation.
A100: Key Quantitative Takeaways
A101: 2028 Best-to-Worst Revenue Range | B101: ='Scenario Analysis'!C59-'Scenario Analysis'!D59 -> 1019349.6
A102: 2028 Best-to-Worst Free Cash Flow Range | B102: ='Scenario Analysis'!C62-'Scenario Analysis'!D62 -> 545476.06
A104: Model QA & Management Review
A106: QA Status | B106: ='Model QA'!D23 -> PASS
A107: Management Reporting Status | B107: =B39 -> READY
A108: Active Forecast Scenario | B108: =B11 -> Base case
A110: Validation Check | B110: Expected | C110: Actual | D110: Status
A111: 2025 Historical Revenue | B111: ='Model QA'!B5 -> 4864066 | C111: ='Model QA'!C5 -> 4864066.1 | D111: ='Model QA'!D5 -> PASS
A112: 2025 Historical Gross Profit | B112: ='Model QA'!B6 -> 2018587 | C112: ='Model QA'!C6 -> 2018587.4 | D112: ='Model QA'!D6 -> PASS
A113: 2025 Historical Operating Expenses | B113: ='Model QA'!B7 -> -1001507 | C113: ='Model QA'!C7 -> -1001506.7 | D113: ='Model QA'!D7 -> PASS
A114: 2025 Historical Operating Income | B114: ='Model QA'!B8 -> 1017081 | C114: ='Model QA'!C8 -> 1017080.7 | D114: ='Model QA'!D8 -> PASS
A116: Forecast Reconciliation
A117: 2026 Ending Cash | B117: ='Model QA'!B24 -> 2552876.5 | C117: ='Model QA'!C24 -> 2552876.5 | D117: ='Model QA'!D24 -> PASS
A118: 2027 Ending Cash | B118: ='Model QA'!B25 -> 3604718.7 | C118: ='Model QA'!C25 -> 3604718.7 | D118: ='Model QA'!D25 -> PASS
A119: 2028 Ending Cash | B119: ='Model QA'!B26 -> 4858967.8 | C119: ='Model QA'!C26 -> 4858967.8 | D119: ='Model QA'!D26 -> PASS
A120: 2026 CapEx | B120: ='Model QA'!B27 -> 430500 | C120: ='Model QA'!C27 -> 430500 | D120: ='Model QA'!D27 -> PASS
A121: 2027 CapEx | B121: ='Model QA'!B28 -> 452025 | C121: ='Model QA'!C28 -> 452025 | D121: ='Model QA'!D28 -> PASS
A122: 2028 CapEx | B122: ='Model QA'!B29 -> 474626.25 | C122: ='Model QA'!C29 -> 474626.25 | D122: ='Model QA'!D29 -> PASS
A124: 2026 Employment Cost | B124: ='Model QA'!B30 -> 6171580.8 | C124: ='Model QA'!C30 -> 6171580.8 | D124: ='Model QA'!D30 -> PASS
A125: 2027 Employment Cost | B125: ='Model QA'!B31 -> 6721122.7 | C125: ='Model QA'!C31 -> 6721122.7 | D125: ='Model QA'!D31 -> PASS
...

Sheet Accounts
A1: AccountKey | B1: AccountNumber | C1: AccountName | D1: FinancialStatement | E1: AccountCategory | F1: NormalBalance
A2: 1 | B2: 1000 | C2: Cash | D2: Balance Sheet | E2: Asset | F2: Debit
A3: 2 | B3: 1100 | C3: Accounts Receivable | D3: Balance Sheet | E3: Asset | F3: Debit
A4: 3 | B4: 1200 | C4: Inventory | D4: Balance Sheet | E4: Asset | F4: Debit
A5: 4 | B5: 1300 | C5: Prepaid Expenses | D5: Balance Sheet | E5: Asset | F5: Debit
A6: 5 | B6: 1500 | C6: Equipment | D6: Balance Sheet | E6: Asset | F6: Debit
A7: 6 | B7: 2000 | C7: Accounts Payable | D7: Balance Sheet | E7: Liability | F7: Credit
A8: 7 | B8: 2100 | C8: Accrued Expenses | D8: Balance Sheet | E8: Liability | F8: Credit
A9: 8 | B9: 2200 | C9: Long-Term Debt | D9: Balance Sheet | E9: Liability | F9: Credit
A10: 9 | B10: 3000 | C10: Retained Earnings | D10: Balance Sheet | E10: Equity | F10: Credit
A11: 10 | B11: 3100 | C11: Common Stock | D11: Balance Sheet | E11: Equity | F11: Credit
A12: 11 | B12: 4000 | C12: Product Revenue | D12: Income Statement | E12: Revenue | F12: Credit
A13: 12 | B13: 4010 | C13: Service Revenue | D13: Income Statement | E13: Revenue | F13: Credit
... A26: 25 | B26: 8200 | C26: Income Tax Expense | D26: Income Statement | E26: Tax Expense | F26: Debit

Sheet Business Units
A1: BusinessUnitKey | B1: BusinessUnitID | C1: BusinessUnitName
A2: 1 | B2: BUO1 | C2: Manufacturing
A3: 2 | B3: BUO2 | C3: Wholesale
A4: 3 | B4: BUO3 | C4: Retail
A5: 4 | B5: BUO4 | C5: E-Commerce

Sheet Calendar
A1: DateKey | B1: FullDate | C1: CalendarYear | D1: CalendarQuarter | E1: MonthNumber | F1: MonthName | G1: MonthYear | H1: FiscalYear
A2: 20230101 | B2: 44927 | C2: 2023 | D2: 1 | E2: 1 | F2: January | G2: Jan 2023 | H2: FY2023
A3: 20230102 | B3: 44928 | C3: 2023 | D3: 1 | E3: 1 | F3: January | G3: Jan 2023 | H3: FY2023
A4: 20230103 | B4: 44929 | C4: 2023 | D4: 1 | E4: 1 | F4: January | G4: Jan 2023 | H4: FY2023
A5: 20230104 | B5: 44930 | C5: 2023 | D5: 1 | E5: 1 | F5: January | G5: Jan 2023 | H5: FY2023
A6: 20230105 | B6: 44931 | C6: 2023 | D6: 1 | E6: 1 | F6: January | G6: Jan 2023 | H6: FY2023
A7: 20230106 | B7: 44932 | C7: 2023 | D7: 1 | E7: 1 | F7: January | G7: Jan 2023 | H7: FY2023
A8: 20230107 | B8: 44933 | C8: 2023 | D8: 1 | E8: 1 | F8: January | G8: Jan 2023 | H8: FY2023
A9: 20230108 | B9: 44934 | C9: 2023 | D9: 1 | E9: 1 | F9: January | G9: Jan 2023 | H9: FY2023
A10: 20230109 | B10: 44935 | C10: 2023 | D10: 1 | E10: 1 | F10: January | G10: Jan 2023 | H10: FY2023
A11: 20230110 | B11: 44936 | C11: 2023 | D11: 1 | E11: 1 | F11: January | G11: Jan 2023 | H11: FY2023
A12: 20230111 | B12: 44937 | C12: 2023 | D12: 1 | E12: 1 | F12: January | G12: Jan 2023 | H12: FY2023
A13: 20230112 | B13: 44938 | C13: 2023 | D13: 1 | E13: 1 | F13: January | G13: Jan 2023 | H13: FY2023
... A1097: 20251231 | B1097: 46022 | C1097: 2025 | D1097: 4 | E1097: 12 | F1097: December | G1097: Dec 2025 | H1097: FY2025

Sheet Departments
A1: DepartmentKey | B1: DepartmentID | C1: DepartmentName
A2: 1 | B2: D001 | C2: Executive
A3: 2 | B3: D002 | C3: Finance
A4: 3 | B4: D003 | C4: Human Resources
A5: 4 | B5: D004 | C5: Sales
A6: 5 | B6: D005 | C6: Marketing
A7: 6 | B7: D006 | C7: Operations
A8: 7 | B8: D007 | C8: Information Technology
A9: 8 | B9: D008 | C9: Customer Service

Sheet Financial Statements
A1: DateKey | B1: DepartmentKey | C1: BusinessUnitKey | D1: RegionKey | E1: AccountKey | F1: Scenario | G1: Amount | H1: FullDate | I1: AccountNumber | J1: AccountName | K1: FinancialStatement | L1: AccountCategory | M1: NormalBalance | N1: DepartmentName | O1: BusinessUnitName | P1: RegionName
A2: 20230101 | B2: 3 | C2: 1 | D2: 4 | E2: 13 | F2: Actual | G2: 24822.25 | H2: =_xlfn.XLOOKUP(tblFinancials[[#This Row],[DateKey]],tblCalendar[DateKey],tblCalendar[FullDate],"") -> 44927 | I2: =_xlfn.XLOOKUP(tblFinancials[[#This Row],[AccountKey]],tblAccounts[AccountKey],tblAccounts[AccountNumber],"") -> 4020 | J2: =_xlfn.XLOOKUP(tblFinancials[[#This Row],[AccountKey]],tblAccounts[AccountKey],tblAccounts[AccountName],"") -> Online Revenue | K2: =_xlfn.XLOOKUP(tblFinancials[[#This Row],[AccountKey]],tblAccounts[AccountKey],tblAccounts[FinancialStatement],"") -> Income Statement | L2: =_xlfn.XLOOKUP(tblFinancials[[#This Row],[AccountKey]],tblAccounts[AccountKey],tblAccounts[AccountCategory],"") -> Revenue | M2: =_xlfn.XLOOKUP(tblFinancials[[#This Row],[AccountKey]],tblAccounts[AccountKey],tblAccounts[NormalBalance],"") -> Credit | N2: =_xlfn.XLOOKUP(tblFinancials[[#This Row],[DepartmentKey]],tblDepartments[DepartmentKey],tblDepartments[DepartmentName],"") -> Human Resources | O2: =_xlfn.XLOOKUP(tblFinancials[[#This Row],[BusinessUnitKey]],tblBusinessUnits[BusinessUnitKey],tblBusinessUnits[BusinessUnitName],"") -> Manufacturing | P2: =_xlfn.XLOOKUP(tblFinancials[[#This Row],[RegionKey]],tblRegions[RegionKey],tblRegions[RegionName],"") -> East
A3: 20230101 | B3: 2 | C3: 1 | D3: 2 | E3: 13 | F3: Actual | G3: 24542.67 | H3: =_xlfn.XLOOKUP(tblFinancials[[#This Row],[DateKey]],tblCalendar[DateKey],tblCalendar[FullDate],"") -> 44927 | I3: =_xlfn.XLOOKUP(tblFinancials[[#This Row],[AccountKey]],tblAccounts[AccountKey],tblAccounts[AccountNumber],"") -> 4020 | J3: =_xlfn.XLOOKUP(tblFinancials[[#This Row],[AccountKey]],tblAccounts[AccountKey],tblAccounts[AccountName],"") -> Online Revenue | K3: =_xlfn.XLOOKUP(tblFinancials[[#This Row],[AccountKey]],tblAccounts[AccountKey],tblAccounts[FinancialStatement],"") -> Income Statement | L3: =_xlfn.XLOOKUP(tblFinancials[[#This Row],[AccountKey]],tblAccounts[AccountKey],tblAccounts[AccountCategory],"") -> Revenue | M3: =_xlfn.XLOOKUP(tblFinancials[[#This Row],[AccountKey]],tblAccounts[AccountKey],tblAccounts[NormalBalance],"") -> Credit | N3: =_xlfn.XLOOKUP(tblFinancials[[#This Row],[DepartmentKey]],tblDepartments[DepartmentKey],tblDepartments[DepartmentName],"") -> Finance | O3: =_xlfn.XLOOKUP(tblFinancials[[#This Row],[BusinessUnitKey]],tblBusinessUnits[BusinessUnitKey],tblBusinessUnits[BusinessUnitName],"") -> Manufacturing | P3: =_xlfn.XLOOKUP(tblFinancials[[#This Row],[RegionKey]],tblRegions[RegionKey],tblRegions[RegionName],"") -> Midwest
A4: 20230101 | B4: 4 | C4: 1 | D4: 1 | E4: 13 | F4: Actual | G4: 25107.18 | H4: =_xlfn.XLOOKUP(tblFinancials[[#This Row],[DateKey]],tblCalendar[DateKey],tblCalendar[FullDate],"") -> 44927 | I4: =_xlfn.XLOOKUP(tblFinancials[[#This Row],[AccountKey]],tblAccounts[AccountKey],tblAccounts[AccountNumber],"") -> 4020 | J4: =_xlfn.XLOOKUP(tblFinancials[[#This Row],[AccountKey]],tblAccounts[AccountKey],tblAccounts[AccountName],"") -> Online Revenue | K4: =_xlfn.XLOOKUP(tblFinancials[[#This Row],[AccountKey]],tblAccounts[AccountKey],tblAccounts[FinancialStatement],"") -> Income Statement | L4: =_xlfn.XLOOKUP(tblFinancials[[#This Row],[AccountKey]],tblAccounts[AccountKey],tblAccounts[AccountCategory],"") -> Revenue | M4: =_xlfn.XLOOKUP(tblFinancials[[#This Row],[AccountKey]],tblAccounts[AccountKey],tblAccounts[NormalBalance],"") -> Credit | N4: =_xlfn.XLOOKUP(tblFinancials[[#This Row],[DepartmentKey]],tblDepartments[DepartmentKey],tblDepartments[DepartmentName],"") -> Sales | O4: =_xlfn.XLOOKUP(tblFinancials[[#This Row],[BusinessUnitKey]],tblBusinessUnits[BusinessUnitKey],tblBusinessUnits[BusinessUnitName],"") -> Manufacturing | P4: =_xlfn.XLOOKUP(tblFinancials[[#This Row],[RegionKey]],tblRegions[RegionKey],tblRegions[RegionName],"") -> West
A5: 20230101 | B5: 3 | C5: 1 | D5: 1 | E5: 12 | F5: Actual | G5: 24660.76 | H5: =_xlfn.XLOOKUP(tblFinancials[[#This Row],[DateKey]],tblCalendar[DateKey],tblCalendar[FullDate],"") -> 44927 | I5: =_xlfn.XLOOKUP(tblFinancials[[#This Row],[AccountKey]],tblAccounts[AccountKey],tblAccounts[AccountNumber],"") -> 4010 | J5: =_xlfn.XLOOKUP(tblFinancials[[#This Row],[AccountKey]],tblAccounts[AccountKey],tblAccounts[AccountName],"") -> Service Revenue | K5: =_xlfn.XLOOKUP(tblFinancials[[#This Row],[AccountKey]],tblAccounts[AccountKey],tblAccounts[FinancialStatement],"") -> Income Statement | L5: =_xlfn.XLOOKUP(tblFinancials[[#This Row],[AccountKey]],tblAccounts[AccountKey],tblAccounts[AccountCategory],"") -> Revenue | M5: =_xlfn.XLOOKUP(tblFinancials[[#This Row],[AccountKey]],tblAccounts[AccountKey],tblAccounts[NormalBalance],"") -> Credit | N5: =_xlfn.XLOOKUP(tblFinancials[[#This Row],[DepartmentKey]],tblDepartments[DepartmentKey],tblDepartments[DepartmentName],"") -> Human Resources | O5: =_xlfn.XLOOKUP(tblFinancials[[#This Row],[BusinessUnitKey]],tblBusinessUnits[BusinessUnitKey],tblBusinessUnits[BusinessUnitName],"") -> Manufacturing | P5: =_xlfn.XLOOKUP(tblFinancials[[#This Row],[RegionKey]],tblRegions[RegionKey],tblRegions[RegionName],"") -> West
A6: 20230101 | B6: 8 | C6: 3 | D6: 1 | E6: 11 | F6: Actual | G6: 25016.45 | H6: =_xlfn.XLOOKUP(tblFinancials[[#This Row],[DateKey]],tblCalendar[DateKey],tblCalendar[FullDate],"") -> 44927 | I6: =_xlfn.XLOOKUP(tblFinancials[[#This Row],[AccountKey]],tblAccounts[AccountKey],tblAccounts[AccountNumber],"") -> 4000 | J6: =_xlfn.XLOOKUP(tblFinancials[[#This Row],[AccountKey]],tblAccounts[AccountKey],tblAccounts[AccountName],"") -> Product Revenue | K6: =_xlfn.XLOOKUP(tblFinancials[[#This Row],[AccountKey]],tblAccounts[AccountKey],tblAccounts[FinancialStatement],"") -> Income Statement | L6: =_xlfn.XLOOKUP(tblFinancials[[#This Row],[AccountKey]],tblAccounts[AccountKey],tblAccounts[AccountCategory],"") -> Revenue | M6: =_xlfn.XLOOKUP(tblFinancials[[#This Row],[AccountKey]],tblAccounts[AccountKey],tblAccounts[NormalBalance],"") -> Credit | N6: =_xlfn.XLOOKUP(tblFinancials[[#This Row],[DepartmentKey]],tblDepartments[DepartmentKey],tblDepartments[DepartmentName],"") -> Customer Service | O6: =_xlfn.XLOOKUP(tblFinancials[[#This Row],[BusinessUnitKey]],tblBusinessUnits[BusinessUnitKey],tblBusinessUnits[BusinessUnitName],"") -> Retail | P6: =_xlfn.XLOOKUP(tblFinancials[[#This Row],[RegionKey]],tblRegions[RegionKey],tblRegions[RegionName],"") -> West
A7: 20230101 | B7: 3 | C7: 3 | D7: 2 | E7: 13 | F7: Actual | G7: 25695.69 | H7: =_xlfn.XLOOKUP(tblFinancials[[#This Row],[DateKey]],tblCalendar[DateKey],tblCalendar[FullDate],"") -> 44927 | I7: =_xlfn.XLOOKUP(tblFinancials[[#This Row],[AccountKey]],tblAccounts[AccountKey],tblAccounts[AccountNumber],"") -> 4020 | J7: =_xlfn.XLOOKUP(tblFinancials[[#This Row],[AccountKey]],tblAccounts[AccountKey],tblAccounts[AccountName],"") -> Online Revenue | K7: =_xlfn.XLOOKUP(tblFinancials[[#This Row],[AccountKey]],tblAccounts[AccountKey],tblAccounts[FinancialStatement],"") -> Income Statement | L7: =_xlfn.XLOOKUP(tblFinancials[[#This Row],[AccountKey]],tblAccounts[AccountKey],tblAccounts[AccountCategory],"") -> Revenue | M7: =_xlfn.XLOOKUP(tblFinancials[[#This Row],[AccountKey]],tblAccounts[AccountKey],tblAccounts[NormalBalance],"") -> Credit | N7: =_xlfn.XLOOKUP(tblFinancials[[#This Row],[DepartmentKey]],tblDepartments[DepartmentKey],tblDepartments[DepartmentName],"") -> Human Resources | O7: =_xlfn.XLOOKUP(tblFinancials[[#This Row],[BusinessUnitKey]],tblBusinessUnits[BusinessUnitKey],tblBusinessUnits[BusinessUnitName],"") -> Retail | P7: =_xlfn.XLOOKUP(tblFinancials[[#This Row],[RegionKey]],tblRegions[RegionKey],tblRegions[RegionName],"") -> Midwest
A8: 20230101 | B8: 5 | C8: 2 | D8: 4 | E8: 13 | F8: Actual | G8: 26476.68 | H8: =_xlfn.XLOOKUP(tblFinancials[[#This Row],[DateKey]],tblCalendar[DateKey],tblCalendar[FullDate],"") -> 44927 | I8: =_xlfn.XLOOKUP(tblFinancials[[#This Row],[AccountKey]],tblAccounts[AccountKey],tblAccounts[AccountNumber],"") -> 4020 | J8: =_xlfn.XLOOKUP(tblFinancials[[#This Row],[AccountKey]],tblAccounts[AccountKey],tblAccounts[AccountName],"") -> Online Revenue | K8: =_xlfn.XLOOKUP(tblFinancials[[#This Row],[AccountKey]],tblAccounts[AccountKey],tblAccounts[FinancialStatement],"") -> Income Statement | L8: =_xlfn.XLOOKUP(tblFinancials[[#This Row],[AccountKey]],tblAccounts[AccountKey],tblAccounts[AccountCategory],"") -> Revenue | M8: =_xlfn.XLOOKUP(tblFinancials[[#This Row],[AccountKey]],tblAccounts[AccountKey],tblAccounts[NormalBalance],"") -> Credit | N8: =_xlfn.XLOOKUP(tblFinancials[[#This Row],[DepartmentKey]],tblDepartments[DepartmentKey],tblDepartments[DepartmentName],"") -> Marketing | O8: =_xlfn.XLOOKUP(tblFinancials[[#This Row],[BusinessUnitKey]],tblBusinessUnits[BusinessUnitKey],tblBusinessUnits[BusinessUnitName],"") -> Wholesale | P8: =_xlfn.XLOOKUP(tblFinancials[[#This Row],[RegionKey]],tblRegions[RegionKey],tblRegions[RegionName],"") -> East
A9: 20230101 | B9: 6 | C9: 4 | D9: 3 | E9: 11 | F9: Actual | G9: 24155.29 | H9: =_xlfn.XLOOKUP(tblFinancials[[#This Row],[DateKey]],tblCalendar[DateKey],tblCalendar[FullDate],"") -> 44927 | I9: =_xlfn.XLOOKUP(tblFinancials[[#This Row],[AccountKey]],tblAccounts[AccountKey],tblAccounts[AccountNumber],"") -> 4000 | J9: =_xlfn.XLOOKUP(tblFinancials[[#This Row],[AccountKey]],tblAccounts[AccountKey],tblAccounts[AccountName],"") -> Product Revenue | K9: =_xlfn.XLOOKUP(tblFinancials[[#This Row],[AccountKey]],tblAccounts[AccountKey],tblAccounts[FinancialStatement],"") -> Income Statement | L9: =_xlfn.XLOOKUP(tblFinancials[[#This Row],[AccountKey]],tblAccounts[AccountKey],tblAccounts[AccountCategory],"") -> Revenue | M9: =_xlfn.XLOOKUP(tblFinancials[[#This Row],[AccountKey]],tblAccounts[AccountKey],tblAccounts[NormalBalance],"") -> Credit | N9: =_xlfn.XLOOKUP(tblFinancials[[#This Row],[DepartmentKey]],tblDepartments[DepartmentKey],tblDepartments[DepartmentName],"") -> Operations | O9: =_xlfn.XLOOKUP(tblFinancials[[#This Row],[BusinessUnitKey]],tblBusinessUnits[BusinessUnitKey],tblBusinessUnits[BusinessUnitName],"") -> E-Commerce | P9: =_xlfn.XLOOKUP(tblFinancials[[#This Row],[RegionKey]],tblRegions[RegionKey],tblRegions[RegionName],"") -> South
A10: 20230101 | B10: 7 | C10: 3 | D10: 2 | E10: 11 | F10: Actual | G10: 24350.19 | H10: =_xlfn.XLOOKUP(tblFinancials[[#This Row],[DateKey]],tblCalendar[DateKey],tblCalendar[FullDate],"") -> 44927 | I10: =_xlfn.XLOOKUP(tblFinancials[[#This Row],[AccountKey]],tblAccounts[AccountKey],tblAccounts[AccountNumber],"") -> 4000 | J10: =_xlfn.XLOOKUP(tblFinancials[[#This Row],[AccountKey]],tblAccounts[AccountKey],tblAccounts[AccountName],"") -> Product Revenue | K10: =_xlfn.XLOOKUP(tblFinancials[[#This Row],[AccountKey]],tblAccounts[AccountKey],tblAccounts[FinancialStatement],"") -> Income Statement | L10: =_xlfn.XLOOKUP(tblFinancials[[#This Row],[AccountKey]],tblAccounts[AccountKey],tblAccounts[AccountCategory],"") -> Revenue | M10: =_xlfn.XLOOKUP(tblFinancials[[#This Row],[AccountKey]],tblAccounts[AccountKey],tblAccounts[NormalBalance],"") -> Credit | N10: =_xlfn.XLOOKUP(tblFinancials[[#This Row],[DepartmentKey]],tblDepartments[DepartmentKey],tblDepartments[DepartmentName],"") -> Information Technology | O10: =_xlfn.XLOOKUP(tblFinancials[[#This Row],[BusinessUnitKey]],tblBusinessUnits[BusinessUnitKey],tblBusinessUnits[BusinessUnitName],"") -> Retail | P10: =_xlfn.XLOOKUP(tblFinancials[[#This Row],[RegionKey]],tblRegions[RegionKey],tblRegions[RegionName],"") -> Midwest
A11: 20230101 | B11: 2 | C11: 4 | D11: 2 | E11: 11 | F11: Actual | G11: 26247.62 | H11: =_xlfn.XLOOKUP(tblFinancials[[#This Row],[DateKey]],tblCalendar[DateKey],tblCalendar[FullDate],"") -> 44927 | I11: =_xlfn.XLOOKUP(tblFinancials[[#This Row],[AccountKey]],tblAccounts[AccountKey],tblAccounts[AccountNumber],"") -> 4000 | J11: =_xlfn.XLOOKUP(tblFinancials[[#This Row],[AccountKey]],tblAccounts[AccountKey],tblAccounts[AccountName],"") -> Product Revenue | K11: =_xlfn.XLOOKUP(tblFinancials[[#This Row],[AccountKey]],tblAccounts[AccountKey],tblAccounts[FinancialStatement],"") -> Income Statement | L11: =_xlfn.XLOOKUP(tblFinancials[[#This Row],[AccountKey]],tblAccounts[AccountKey],tblAccounts[AccountCategory],"") -> Revenue | M11: =_xlfn.XLOOKUP(tblFinancials[[#This Row],[AccountKey]],tblAccounts[AccountKey],tblAccounts[NormalBalance],"") -> Credit | N11: =_xlfn.XLOOKUP(tblFinancials[[#This Row],[DepartmentKey]],tblDepartments[DepartmentKey],tblDepartments[DepartmentName],"") -> Finance | O11: =_xlfn.XLOOKUP(tblFinancials[[#This Row],[BusinessUnitKey]],tblBusinessUnits[BusinessUnitKey],tblBusinessUnits[BusinessUnitName],"") -> E-Commerce | P11: =_xlfn.XLOOKUP(tblFinancials[[#This Row],[RegionKey]],tblRegions[RegionKey],tblRegions[RegionName],"") -> Midwest
A12: 20230101 | B12: 6 | C12: 2 | D12: 2 | E12: 11 | F12: Actual | G12: 25929.8 | H12: =_xlfn.XLOOKUP(tblFinancials[[#This Row],[DateKey]],tblCalendar[DateKey],tblCalendar[FullDate],"") -> 44927 | I12: =_xlfn.XLOOKUP(tblFinancials[[#This Row],[AccountKey]],tblAccounts[AccountKey],tblAccounts[AccountNumber],"") -> 4000 | J12: =_xlfn.XLOOKUP(tblFinancials[[#This Row],[AccountKey]],tblAccounts[AccountKey],tblAccounts[AccountName],"") -> Product Revenue | K12: =_xlfn.XLOOKUP(tblFinancials[[#This Row],[AccountKey]],tblAccounts[AccountKey],tblAccounts[FinancialStatement],"") -> Income Statement | L12: =_xlfn.XLOOKUP(tblFinancials[[#This Row],[AccountKey]],tblAccounts[AccountKey],tblAccounts[AccountCategory],"") -> Revenue | M12: =_xlfn.XLOOKUP(tblFinancials[[#This Row],[AccountKey]],tblAccounts[AccountKey],tblAccounts[NormalBalance],"") -> Credit | N12: =_xlfn.XLOOKUP(tblFinancials[[#This Row],[DepartmentKey]],tblDepartments[DepartmentKey],tblDepartments[DepartmentName],"") -> Operations | O12: =_xlfn.XLOOKUP(tblFinancials[[#This Row],[BusinessUnitKey]],tblBusinessUnits[BusinessUnitKey],tblBusinessUnits[BusinessUnitName],"") -> Wholesale | P12: =_xlfn.XLOOKUP(tblFinancials[[#This Row],[RegionKey]],tblRegions[RegionKey],tblRegions[RegionName],"") -> Midwest
A13: 20230101 | B13: 2 | C13: 4 | D13: 1 | E13: 13 | F13: Actual | G13: 27088.81 | H13: =_xlfn.XLOOKUP(tblFinancials[[#This Row],[DateKey]],tblCalendar[DateKey],tblCalendar[FullDate],"") -> 44927 | I13: =_xlfn.XLOOKUP(tblFinancials[[#This Row],[AccountKey]],tblAccounts[AccountKey],tblAccounts[AccountNumber],"") -> 4020 | J13: =_xlfn.XLOOKUP(tblFinancials[[#This Row],[AccountKey]],tblAccounts[AccountKey],tblAccounts[AccountName],"") -> Online Revenue | K13: =_xlfn.XLOOKUP(tblFinancials[[#This Row],[AccountKey]],tblAccounts[AccountKey],tblAccounts[FinancialStatement],"") -> Income Statement | L13: =_xlfn.XLOOKUP(tblFinancials[[#This Row],[AccountKey]],tblAccounts[AccountKey],tblAccounts[AccountCategory],"") -> Revenue | M13: =_xlfn.XLOOKUP(tblFinancials[[#This Row],[AccountKey]],tblAccounts[AccountKey],tblAccounts[NormalBalance],"") -> Credit | N13: =_xlfn.XLOOKUP(tblFinancials[[#This Row],[DepartmentKey]],tblDepartments[DepartmentKey],tblDepartments[DepartmentName],"") -> Finance | O13: =_xlfn.XLOOKUP(tblFinancials[[#This Row],[BusinessUnitKey]],tblBusinessUnits[BusinessUnitKey],tblBusinessUnits[BusinessUnitName],"") -> E-Commerce | P13: =_xlfn.XLOOKUP(tblFinancials[[#This Row],[RegionKey]],tblRegions[RegionKey],tblRegions[RegionName],"") -> West
... A1297: 20251201 | B1297: 5 | C1297: 4 | D1297: 2 | E1297: 21 | F1297: Actual | G1297: -6874.77 | H1297: =_xlfn.XLOOKUP(tblFinancials[[#This Row],[DateKey]],tblCalendar[DateKey],tblCalendar[FullDate],"") -> 45992 | I1297: =_xlfn.XLOOKUP(tblFinancials[[#This Row],[AccountKey]],tblAccounts[AccountKey],tblAccounts[AccountNumber],"") -> 6600 | J1297: =_xlfn.XLOOKUP(tblFinancials[[#This Row],[AccountKey]],tblAccounts[AccountKey],tblAccounts[AccountName],"") -> Utilities Expense | K1297: =_xlfn.XLOOKUP(tblFinancials[[#This Row],[AccountKey]],tblAccounts[AccountKey],tblAccounts[FinancialStatement],"") -> Income Statement | L1297: =_xlfn.XLOOKUP(tblFinancials[[#This Row],[AccountKey]],tblAccounts[AccountKey],tblAccounts[AccountCategory],"") -> Operating Expense | M1297: =_xlfn.XLOOKUP(tblFinancials[[#This Row],[AccountKey]],tblAccounts[AccountKey],tblAccounts[NormalBalance],"") -> Debit | N1297: =_xlfn.XLOOKUP(tblFinancials[[#This Row],[DepartmentKey]],tblDepartments[DepartmentKey],tblDepartments[DepartmentName],"") -> Marketing | O1297: =_xlfn.XLOOKUP(tblFinancials[[#This Row],[BusinessUnitKey]],tblBusinessUnits[BusinessUnitKey],tblBusinessUnits[BusinessUnitName],"") -> E-Commerce | P1297: =_xlfn.XLOOKUP(tblFinancials[[#This Row],[RegionKey]],tblRegions[RegionKey],tblRegions[RegionName],"") -> Midwest

Sheet Regions
A1: RegionKey | B1: RegionID | C1: RegionName
A2: 1 | B2: R01 | C2: West
A3: 2 | B3: R02 | C3: Midwest
A4: 3 | B4: R03 | C4: South
A5: 4 | B5: R04 | C5: East

Sheet Historical Actuals
A1: CASCADE OUTDOOR MANUFACTURING
A2: Historical Income Statement
A4: Account | B4: 2023 | C4: 2024 | D4: 2025 | E4: 2024 YoY % | F4: 2025 YoY %
A5: Revenue
A6: Product Revenue | B6: =SUMIFS(tblFinancials[Amount],tblFinancials[AccountName],$A6,tblFinancials[FullDate],">="&DATE(B$4,1,1),tblFinancials[FullDate],"<="&DATE(B$4,12,31)) -> 1358696.8 | C6: =SUMIFS(tblFinancials[Amount],tblFinancials[AccountName],$A6,tblFinancials[FullDate],">="&DATE(C$4,1,1),tblFinancials[FullDate],"<="&DATE(C$4,12,31)) -> 1542816.8 | D6: =SUMIFS(tblFinancials[Amount],tblFinancials[AccountName],$A6,tblFinancials[FullDate],">="&DATE(D$4,1,1),tblFinancials[FullDate],"<="&DATE(D$4,12,31)) -> 1593911.6 | E6: =IFERROR(C6/B6-1,0) -> 0.13551221 | F6: =IFERROR(D6/C6-1,0) -> 0.033117892
A7: Service Revenue | B7: =SUMIFS(tblFinancials[Amount],tblFinancials[AccountName],$A7,tblFinancials[FullDate],">="&DATE(B$4,1,1),tblFinancials[FullDate],"<="&DATE(B$4,12,31)) -> 1487698.5 | C7: =SUMIFS(tblFinancials[Amount],tblFinancials[AccountName],$A7,tblFinancials[FullDate],">="&DATE(C$4,1,1),tblFinancials[FullDate],"<="&DATE(C$4,12,31)) -> 1468097.8 | D7: =SUMIFS(tblFinancials[Amount],tblFinancials[AccountName],$A7,tblFinancials[FullDate],">="&DATE(D$4,1,1),tblFinancials[FullDate],"<="&DATE(D$4,12,31)) -> 2075959.7 | E7: =IFERROR(C7/B7-1,0) -> -0.013175169 | F7: =IFERROR(D7/C7-1,0) -> 0.41404724
A8: Online Revenue | B8: =SUMIFS(tblFinancials[Amount],tblFinancials[AccountName],$A8,tblFinancials[FullDate],">="&DATE(B$4,1,1),tblFinancials[FullDate],"<="&DATE(B$4,12,31)) -> 1332487.7 | C8: =SUMIFS(tblFinancials[Amount],tblFinancials[AccountName],$A8,tblFinancials[FullDate],">="&DATE(C$4,1,1),tblFinancials[FullDate],"<="&DATE(C$4,12,31)) -> 1527404 | D8: =SUMIFS(tblFinancials[Amount],tblFinancials[AccountName],$A8,tblFinancials[FullDate],">="&DATE(D$4,1,1),tblFinancials[FullDate],"<="&DATE(D$4,12,31)) -> 1194194.8 | E8: =IFERROR(C8/B8-1,0) -> 0.14627999 | F8: =IFERROR(D8/C8-1,0) -> -0.21815396
A9: Total Revenue | B9: =SUM(B6:B8) -> 4178883 | C9: =SUM(C6:C8) -> 4538318.6 | D9: =SUM(D6:D8) -> 4864066.1 | E9: =IFERROR(C9/B9-1,0) -> 0.086012365 | F9: =IFERROR(D9/C9-1,0) -> 0.071777124
A12: Cost of Goods Sold | B12: =SUMIFS(tblFinancials[Amount],tblFinancials[AccountName],$A12,tblFinancials[FullDate],">="&DATE(B$4,1,1),tblFinancials[FullDate],"<="&DATE(B$4,12,31)) -> -2444646.6 | C12: =SUMIFS(tblFinancials[Amount],tblFinancials[AccountName],$A12,tblFinancials[FullDate],">="&DATE(C$4,1,1),tblFinancials[FullDate],"<="&DATE(C$4,12,31)) -> -2654916.4 | D12: =SUMIFS(tblFinancials[Amount],tblFinancials[AccountName],$A12,tblFinancials[FullDate],">="&DATE(D$4,1,1),tblFinancials[FullDate],"<="&DATE(D$4,12,31)) -> -2845478.7
A13: Gross Profit | B13: =B9+B12 -> 1734236.4 | C13: =C9+C12 -> 1883402.2 | D13: =D9+D12 -> 2018587.4 | E13: =IFERROR(C13/B13-1,0) -> 0.08601236 | F13: =IFERROR(D13/C13-1,0) -> 0.071777122
A14: Gross Margin % | B14: =IFERROR(B13/B9,0) -> 0.415 | C14: =IFERROR(C13/C9,0) -> 0.415 | D14: =IFERROR(D13/D9,0) -> 0.415
A16: Operating Expenses
A17: Salaries Expense | B17: =SUMIFS(tblFinancials[Amount],tblFinancials[AccountName],$A17,tblFinancials[FullDate],">="&DATE(B$4,1,1),tblFinancials[FullDate],"<="&DATE(B$4,12,31)) -> -52242.94 | C17: =SUMIFS(tblFinancials[Amount],tblFinancials[AccountName],$A17,tblFinancials[FullDate],">="&DATE(C$4,1,1),tblFinancials[FullDate],"<="&DATE(C$4,12,31)) -> -96375.75 | D17: =SUMIFS(tblFinancials[Amount],tblFinancials[AccountName],$A17,tblFinancials[FullDate],">="&DATE(D$4,1,1),tblFinancials[FullDate],"<="&DATE(D$4,12,31)) -> -114708.77
A18: Payroll Taxes | B18: =SUMIFS(tblFinancials[Amount],tblFinancials[AccountName],$A18,tblFinancials[FullDate],">="&DATE(B$4,1,1),tblFinancials[FullDate],"<="&DATE(B$4,12,31)) -> -80037.57 | C18: =SUMIFS(tblFinancials[Amount],tblFinancials[AccountName],$A18,tblFinancials[FullDate],">="&DATE(C$4,1,1),tblFinancials[FullDate],"<="&DATE(C$4,12,31)) -> -69239.39 | D18: =SUMIFS(tblFinancials[Amount],tblFinancials[AccountName],$A18,tblFinancials[FullDate],">="&DATE(D$4,1,1),tblFinancials[FullDate],"<="&DATE(D$4,12,31)) -> -121548.56
A19: Employee Benefits | B19: =SUMIFS(tblFinancials[Amount],tblFinancials[AccountName],$A19,tblFinancials[FullDate],">="&DATE(B$4,1,1),tblFinancials[FullDate],"<="&DATE(B$4,12,31)) -> -151449.31 | C19: =SUMIFS(tblFinancials[Amount],tblFinancials[AccountName],$A19,tblFinancials[FullDate],">="&DATE(C$4,1,1),tblFinancials[FullDate],"<="&DATE(C$4,12,31)) -> -76396.41 | D19: =SUMIFS(tblFinancials[Amount],tblFinancials[AccountName],$A19,tblFinancials[FullDate],">="&DATE(D$4,1,1),tblFinancials[FullDate],"<="&DATE(D$4,12,31)) -> -127470.29
A20: Marketing Expense | B20: =SUMIFS(tblFinancials[Amount],tblFinancials[AccountName],$A20,tblFinancials[FullDate],">="&DATE(B$4,1,1),tblFinancials[FullDate],"<="&DATE(B$4,12,31)) -> -98516.96 | C20: =SUMIFS(tblFinancials[Amount],tblFinancials[AccountName],$A20,tblFinancials[FullDate],">="&DATE(C$4,1,1),tblFinancials[FullDate],"<="&DATE(C$4,12,31)) -> -117550.9 | D20: =SUMIFS(tblFinancials[Amount],tblFinancials[AccountName],$A20,tblFinancials[FullDate],">="&DATE(D$4,1,1),tblFinancials[FullDate],"<="&DATE(D$4,12,31)) -> -134698.59
A21: Software Expense | B21: =SUMIFS(tblFinancials[Amount],tblFinancials[AccountName],$A21,tblFinancials[FullDate],">="&DATE(B$4,1,1),tblFinancials[FullDate],"<="&DATE(B$4,12,31)) -> -75424.46 | C21: =SUMIFS(tblFinancials[Amount],tblFinancials[AccountName],$A21,tblFinancials[FullDate],">="&DATE(C$4,1,1),tblFinancials[FullDate],"<="&DATE(C$4,12,31)) -> -92312.64 | D21: =SUMIFS(tblFinancials[Amount],tblFinancials[AccountName],$A21,tblFinancials[FullDate],">="&DATE(D$4,1,1),tblFinancials[FullDate],"<="&DATE(D$4,12,31)) -> -95296.73
A22: Rent Expense | B22: =SUMIFS(tblFinancials[Amount],tblFinancials[AccountName],$A22,tblFinancials[FullDate],">="&DATE(B$4,1,1),tblFinancials[FullDate],"<="&DATE(B$4,12,31)) -> -88551.8 | C22: =SUMIFS(tblFinancials[Amount],tblFinancials[AccountName],$A22,tblFinancials[FullDate],">="&DATE(C$4,1,1),tblFinancials[FullDate],"<="&DATE(C$4,12,31)) -> -83485.21 | D22: =SUMIFS(tblFinancials[Amount],tblFinancials[AccountName],$A22,tblFinancials[FullDate],">="&DATE(D$4,1,1),tblFinancials[FullDate],"<="&DATE(D$4,12,31)) -> -40564.25
A23: Utilities Expense | B23: =SUMIFS(tblFinancials[Amount],tblFinancials[AccountName],$A23,tblFinancials[FullDate],">="&DATE(B$4,1,1),tblFinancials[FullDate],"<="&DATE(B$4,12,31)) -> -92702.17 | C23: =SUMIFS(tblFinancials[Amount],tblFinancials[AccountName],$A23,tblFinancials[FullDate],">="&DATE(C$4,1,1),tblFinancials[FullDate],"<="&DATE(C$4,12,31)) -> -148036.79 | D23: =SUMIFS(tblFinancials[Amount],tblFinancials[AccountName],$A23,tblFinancials[FullDate],">="&DATE(D$4,1,1),tblFinancials[FullDate],"<="&DATE(D$4,12,31)) -> -106019.65
A24: Insurance Expense | B24: =SUMIFS(tblFinancials[Amount],tblFinancials[AccountName],$A24,tblFinancials[FullDate],">="&DATE(B$4,1,1),tblFinancials[FullDate],"<="&DATE(B$4,12,31)) -> -73253.14 | C24: =SUMIFS(tblFinancials[Amount],tblFinancials[AccountName],$A24,tblFinancials[FullDate],">="&DATE(C$4,1,1),tblFinancials[FullDate],"<="&DATE(C$4,12,31)) -> -103891.91 | D24: =SUMIFS(tblFinancials[Amount],tblFinancials[AccountName],$A24,tblFinancials[FullDate],">="&DATE(D$4,1,1),tblFinancials[FullDate],"<="&DATE(D$4,12,31)) -> -70498.07
A25: Travel Expense | B25: =SUMIFS(tblFinancials[Amount],tblFinancials[AccountName],$A25,tblFinancials[FullDate],">="&DATE(B$4,1,1),tblFinancials[FullDate],"<="&DATE(B$4,12,31)) -> -93867.94 | C25: =SUMIFS(tblFinancials[Amount],tblFinancials[AccountName],$A25,tblFinancials[FullDate],">="&DATE(C$4,1,1),tblFinancials[FullDate],"<="&DATE(C$4,12,31)) -> -58534.91 | D25: =SUMIFS(tblFinancials[Amount],tblFinancials[AccountName],$A25,tblFinancials[FullDate],">="&DATE(D$4,1,1),tblFinancials[FullDate],"<="&DATE(D$4,12,31)) -> -110065.08
A26: Professional Services | B26: =SUMIFS(tblFinancials[Amount],tblFinancials[AccountName],$A26,tblFinancials[FullDate],">="&DATE(B$4,1,1),tblFinancials[FullDate],"<="&DATE(B$4,12,31)) -> -102318.47 | C26: =SUMIFS(tblFinancials[Amount],tblFinancials[AccountName],$A26,tblFinancials[FullDate],">="&DATE(C$4,1,1),tblFinancials[FullDate],"<="&DATE(C$4,12,31)) -> -120394.77 | D26: =SUMIFS(tblFinancials[Amount],tblFinancials[AccountName],$A26,tblFinancials[FullDate],">="&DATE(D$4,1,1),tblFinancials[FullDate],"<="&DATE(D$4,12,31)) -> -80636.72
A27: Total Operating Expenses | B27: =SUM(B17:B26) -> -908364.76 | C27: =SUM(C17:C26) -> -966218.68 | D27: =SUM(D17:D26) -> -1001506.7 | E27: =IFERROR(C27/B27-1,0) -> 0.063690185 | F27: =IFERROR(D27/C27-1,0) -> 0.036521784
A29: Operating Income | B29: =B13+B27 -> 825871.69 | C29: =C13+C27 -> 917183.54 | D29: =D13+D27 -> 1017080.7 | E29: =IFERROR(C29/B29-1,0) -> 0.11056421 | F29: =IFERROR(D29/C29-1,0) -> 0.10891731
A30: Operating Margin % | B30: =IFERROR(B29/B9,0) -> 0.19762977 | C30: =IFERROR(C29/C9,0) -> 0.20209765 | D30: =IFERROR(D29/D9,0) -> 0.20910092
A32: Income Tax Expense | B32: =SUMIFS(tblFinancials[Amount],tblFinancials[AccountName],$A32,tblFinancials[FullDate],">="&DATE(B$4,1,1),tblFinancials[FullDate],"<="&DATE(B$4,12,31)) -> -73672.76 | C32: =SUMIFS(tblFinancials[Amount],tblFinancials[AccountName],$A32,tblFinancials[FullDate],">="&DATE(C$4,1,1),tblFinancials[FullDate],"<="&DATE(C$4,12,31)) -> -100286.18 | D32: =SUMIFS(tblFinancials[Amount],tblFinancials[AccountName],$A32,tblFinancials[FullDate],">="&DATE(D$4,1,1),tblFinancials[FullDate],"<="&DATE(D$4,12,31)) -> -141548.81
A33: Net Income | B33: =B29+B32 -> 752198.93 | C33: =C29+C32 -> 816897.36 | D33: =D29+D32 -> 875531.89 | E33: =IFERROR(C33/B33-1,0) -> 0.086012393 | F33: =IFERROR(D33/C33-1,0) -> 0.071777108
A34: Net Profit Margin % | B34: =IFERROR(B33/B9,0) -> 0.18 | C34: =IFERROR(C33/C9,0) -> 0.18 | D34: =IFERROR(D33/D9,0) -> 0.18
A36: Historical Model Checks
A37: Revenue Check | B37: =IF(ROUND(B9,2)=ROUND(SUMIFS(tblFinancials[Amount],tblFinancials[FinancialStatement],"Income Statement",tblFinancials[AccountCategory],"Revenue",tblFinancials[FullDate],">="&DATE(B$4,1,1),tblFinancials[FullDate],"<="&DATE(B$4,12,31)),2),"OK","CHECK") -> OK | C37: =IF(ROUND(C9,2)=ROUND(SUMIFS(tblFinancials[Amount],tblFinancials[FinancialStatement],"Income Statement",tblFinancials[AccountCategory],"Revenue",tblFinancials[FullDate],">="&DATE(C$4,1,1),tblFinancials[FullDate],"<="&DATE(C$4,12,31)),2),"OK","CHECK") -> OK | D37: =IF(ROUND(D9,2)=ROUND(SUMIFS(tblFinancials[Amount],tblFinancials[FinancialStatement],"Income Statement",tblFinancials[AccountCategory],"Revenue",tblFinancials[FullDate],">="&DATE(D$4,1,1),tblFinancials[FullDate],"<="&DATE(D$4,12,31)),2),"OK","CHECK") -> OK
A38: Gross Profit Check | B38: =IF(ROUND(B13,2)=ROUND(B9+B12,2),"OK","CHECK") -> OK | C38: =IF(ROUND(C13,2)=ROUND(C9+C12,2),"OK","CHECK") -> OK | D38: =IF(ROUND(D13,2)=ROUND(D9+D12,2),"OK","CHECK") -> OK
A39: Operating Income Check | B39: =IF(ROUND(B29,2)=ROUND(B13+B27,2),"OK","CHECK") -> OK | C39: =IF(ROUND(C29,2)=ROUND(C13+C27,2),"OK","CHECK") -> OK | D39: =IF(ROUND(D29,2)=ROUND(D13+D27,2),"OK","CHECK") -> OK
A40: Net Income Check | B40: =IF(ROUND(B33,2)=ROUND(B29+B32,2),"OK","CHECK") -> OK | C40: =IF(ROUND(C33,2)=ROUND(C29+C32,2),"OK","CHECK") -> OK | D40: =IF(ROUND(D33,2)=ROUND(D29+D32,2),"OK","CHECK") -> OK

Sheet Historical Trends
A1: CASCADE OUTDOOR MANUFACTURING
A2: Historical Financial Trends
A4: Metric | B4: 2023 | C4: 2024 | D4: 2025
A5: Revenue | B5: ='Historical Actuals'!B9 -> 4178883 | C5: ='Historical Actuals'!C9 -> 4538318.6 | D5: ='Historical Actuals'!D9 -> 4864066.1
A6: Revenue Growth | C6: ='Historical Actuals'!E9 -> 0.086012365 | D6: ='Historical Actuals'!F9 -> 0.071777124
A7: Gross Profit | B7: ='Historical Actuals'!B13 -> 1734236.4 | C7: ='Historical Actuals'!C13 -> 1883402.2 | D7: ='Historical Actuals'!D13 -> 2018587.4
A8: Gross Margin | B8: ='Historical Actuals'!B14 -> 0.415 | C8: ='Historical Actuals'!C14 -> 0.415 | D8: ='Historical Actuals'!D14 -> 0.415
A9: Operating Expenses | B9: ='Historical Actuals'!B27 -> -908364.76 | C9: ='Historical Actuals'!C27 -> -966218.68 | D9: ='Historical Actuals'!D27 -> -1001506.7
A10: Operating Expense Growth | C10: =IFERROR(C9/B9-1,0) -> 0.063690185 | D10: =IFERROR(D9/C9-1,0) -> 0.036521784
A11: Operating Income | C11: ='Historical Actuals'!C29 -> 917183.54 | D11: ='Historical Actuals'!D29 -> 1017080.7
A12: Operating Margin | B12: ='Historical Actuals'!B30 -> 0.19762977 | C12: ='Historical Actuals'!C30 -> 0.20209765 | D12: ='Historical Actuals'!D30 -> 0.20910092
A13: Net Income | B13: ='Historical Actuals'!B33 -> 752198.93 | C13: ='Historical Actuals'!C33 -> 816897.36 | D13: ='Historical Actuals'!D33 -> 875531.89
A14: Net Profit Margin | B14: ='Historical Actuals'!B34 -> 0.18 | C14: ='Historical Actuals'!C34 -> 0.18 | D14: ='Historical Actuals'!D34 -> 0.18
A16: Revenue Mix
A17: Product Revenue | B17: =IFERROR('Historical Actuals'!B6/'Historical Actuals'!B9,0) -> 0.32513396 | C17: =IFERROR('Historical Actuals'!C6/'Historical Actuals'!C9,0) -> 0.33995338 | D17: =IFERROR('Historical Actuals'!D6/'Historical Actuals'!D9,0) -> 0.32769119
A18: Service Revenue | B18: =IFERROR('Historical Actuals'!B7/'Historical Actuals'!B9,0) -> 0.35600387 | C18: =IFERROR('Historical Actuals'!C7/'Historical Actuals'!C9,0) -> 0.32348937 | D18: =IFERROR('Historical Actuals'!D7/'Historical Actuals'!D9,0) -> 0.42679512
A19: Online Revenue | B19: =IFERROR('Historical Actuals'!B8/'Historical Actuals'!B9,0) -> 0.31886218 | C19: =IFERROR('Historical Actuals'!C8/'Historical Actuals'!C9,0) -> 0.33655725 | D19: =IFERROR('Historical Actuals'!D8/'Historical Actuals'!D9,0) -> 0.24551369
A21: Revenue Growth by Type
A22: Product Revenue Growth | C22: =IFERROR('Historical Actuals'!C6/'Historical Actuals'!B6-1,0) -> 0.13551221 | D22: =IFERROR('Historical Actuals'!D6/'Historical Actuals'!C6-1,0) -> 0.033117892
A23: Service Revenue Growth | C23: =IFERROR('Historical Actuals'!C7/'Historical Actuals'!B7-1,0) -> -0.013175169 | D23: =IFERROR('Historical Actuals'!D7/'Historical Actuals'!C7-1,0) -> 0.41404724
A24: Online Revenue Growth | C24: =IFERROR('Historical Actuals'!C8/'Historical Actuals'!B8-1,0) -> 0.14627999 | D24: =IFERROR('Historical Actuals'!D8/'Historical Actuals'!C8-1,0) -> -0.21815396
A27: Historical Management KPIs
A28: Revenue CAGR (2023–2025) | B28: =IFERROR(('Historical Actuals'!D9/'Historical Actuals'!B9)^(1/2)-1,0) -> 0.078871266
A29: Gross Margin Change | B29: ='Historical Actuals'!D14-'Historical Actuals'!B14 -> -2.7772899e-09
A30: Operating Margin Change | B30: ='Historical Actuals'!D30-'Historical Actuals'!B30 -> 0.011471151
A31: Net Margin Change | B31: ='Historical Actuals'!D34-'Historical Actuals'!B34 -> 1.9798045e-09

Sheet Revenue Analysis
A1: CASCADE OUTDOOR MANUFACTURING
A2: Historical Revenue Analysis
A4: Business Unit | B4: BusinessUnitKey | C4: 2023 | D4: 2024 | E4: 2025 | F4: 2024 YoY % | G4: 2025 YoY %
A5: Manufacturing | B5: 1 | C5: =SUMIFS(tblFinancials[Amount],tblFinancials[BusinessUnitKey],$B5,tblFinancials[AccountCategory],"Revenue",tblFinancials[FullDate],">="&DATE(C$4,1,1),tblFinancials[FullDate],"<="&DATE(C$4,12,31)) -> 912415.04 | D5: =SUMIFS(tblFinancials[Amount],tblFinancials[BusinessUnitKey],$B5,tblFinancials[AccountCategory],"Revenue",tblFinancials[FullDate],">="&DATE(D$4,1,1),tblFinancials[FullDate],"<="&DATE(D$4,12,31)) -> 967524.1 | E5: =SUMIFS(tblFinancials[Amount],tblFinancials[BusinessUnitKey],$B5,tblFinancials[AccountCategory],"Revenue",tblFinancials[FullDate],">="&DATE(E$4,1,1),tblFinancials[FullDate],"<="&DATE(E$4,12,31)) -> 1231127.4 | F5: =IFERROR(D5/C5-1,0) -> 0.060399114 | G5: =IFERROR(E5/D5-1,0) -> 0.27245138
A6: Wholesale | B6: 2 | C6: =SUMIFS(tblFinancials[Amount],tblFinancials[BusinessUnitKey],$B6,tblFinancials[AccountCategory],"Revenue",tblFinancials[FullDate],">="&DATE(C$4,1,1),tblFinancials[FullDate],"<="&DATE(C$4,12,31)) -> 963235.69 | D6: =SUMIFS(tblFinancials[Amount],tblFinancials[BusinessUnitKey],$B6,tblFinancials[AccountCategory],"Revenue",tblFinancials[FullDate],">="&DATE(D$4,1,1),tblFinancials[FullDate],"<="&DATE(D$4,12,31)) -> 1306632.9 | E6: =SUMIFS(tblFinancials[Amount],tblFinancials[BusinessUnitKey],$B6,tblFinancials[AccountCategory],"Revenue",tblFinancials[FullDate],">="&DATE(E$4,1,1),tblFinancials[FullDate],"<="&DATE(E$4,12,31)) -> 1181754.6 | F6: =IFERROR(D6/C6-1,0) -> 0.35650378 | G6: =IFERROR(E6/D6-1,0) -> -0.095572586
A7: Retail | B7: 3 | C7: =SUMIFS(tblFinancials[Amount],tblFinancials[BusinessUnitKey],$B7,tblFinancials[AccountCategory],"Revenue",tblFinancials[FullDate],">="&DATE(C$4,1,1),tblFinancials[FullDate],"<="&DATE(C$4,12,31)) -> 1174289.1 | D7: =SUMIFS(tblFinancials[Amount],tblFinancials[BusinessUnitKey],$B7,tblFinancials[AccountCategory],"Revenue",tblFinancials[FullDate],">="&DATE(D$4,1,1),tblFinancials[FullDate],"<="&DATE(D$4,12,31)) -> 1000351.3 | E7: =SUMIFS(tblFinancials[Amount],tblFinancials[BusinessUnitKey],$B7,tblFinancials[AccountCategory],"Revenue",tblFinancials[FullDate],">="&DATE(E$4,1,1),tblFinancials[FullDate],"<="&DATE(E$4,12,31)) -> 1420953.4 | F7: =IFERROR(D7/C7-1,0) -> -0.14812182 | G7: =IFERROR(E7/D7-1,0) -> 0.42045448
A8: E-Commerce | B8: 4 | C8: =SUMIFS(tblFinancials[Amount],tblFinancials[BusinessUnitKey],$B8,tblFinancials[AccountCategory],"Revenue",tblFinancials[FullDate],">="&DATE(C$4,1,1),tblFinancials[FullDate],"<="&DATE(C$4,12,31)) -> 1128943.2 | D8: =SUMIFS(tblFinancials[Amount],tblFinancials[BusinessUnitKey],$B8,tblFinancials[AccountCategory],"Revenue",tblFinancials[FullDate],">="&DATE(D$4,1,1),tblFinancials[FullDate],"<="&DATE(D$4,12,31)) -> 1263810.4 | E8: =SUMIFS(tblFinancials[Amount],tblFinancials[BusinessUnitKey],$B8,tblFinancials[AccountCategory],"Revenue",tblFinancials[FullDate],">="&DATE(E$4,1,1),tblFinancials[FullDate],"<="&DATE(E$4,12,31)) -> 1030230.7 | F8: =IFERROR(D8/C8-1,0) -> 0.11946326 | G8: =IFERROR(E8/D8-1,0) -> -0.18482179
A9: Total Revenue | C9: =SUM(C5:C8) -> 4178883 | D9: =SUM(D5:D8) -> 4538318.6 | E9: =SUM(E5:E8) -> 4864066.1 | F9: =IFERROR(D9/C9-1,0) -> 0.086012365 | G9: =IFERROR(E9/D9-1,0) -> 0.071777124
A12: Revenue by Region
A13: Region | B13: RegionKey | C13: 2023 | D13: 2024 | E13: 2025 | F13: 2024 YoY % | G13: 2025 YoY %
A14: West | B14: 1 | C14: =SUMIFS(tblFinancials[Amount],tblFinancials[RegionKey],$B14,tblFinancials[AccountCategory],"Revenue",tblFinancials[FullDate],">="&DATE(C$13,1,1),tblFinancials[FullDate],"<="&DATE(C$13,12,31)) -> 1171392.6 | D14: =SUMIFS(tblFinancials[Amount],tblFinancials[RegionKey],$B14,tblFinancials[AccountCategory],"Revenue",tblFinancials[FullDate],">="&DATE(D$13,1,1),tblFinancials[FullDate],"<="&DATE(D$13,12,31)) -> 1209083 | E14: =SUMIFS(tblFinancials[Amount],tblFinancials[RegionKey],$B14,tblFinancials[AccountCategory],"Revenue",tblFinancials[FullDate],">="&DATE(E$13,1,1),tblFinancials[FullDate],"<="&DATE(E$13,12,31)) -> 957037.82 | F14: =IFERROR(D14/C14-1,0) -> 0.032175693 | G14: =IFERROR(E14/D14-1,0) -> -0.20845978
A15: Midwest | B15: 2 | C15: =SUMIFS(tblFinancials[Amount],tblFinancials[RegionKey],$B15,tblFinancials[AccountCategory],"Revenue",tblFinancials[FullDate],">="&DATE(C$13,1,1),tblFinancials[FullDate],"<="&DATE(C$13,12,31)) -> 1022730.7 | D15: =SUMIFS(tblFinancials[Amount],tblFinancials[RegionKey],$B15,tblFinancials[AccountCategory],"Revenue",tblFinancials[FullDate],">="&DATE(D$13,1,1),tblFinancials[FullDate],"<="&DATE(D$13,12,31)) -> 1101158.3 | E15: =SUMIFS(tblFinancials[Amount],tblFinancials[RegionKey],$B15,tblFinancials[AccountCategory],"Revenue",tblFinancials[FullDate],">="&DATE(E$13,1,1),tblFinancials[FullDate],"<="&DATE(E$13,12,31)) -> 1202957.2 | F15: =IFERROR(D15/C15-1,0) -> 0.07668458 | G15: =IFERROR(E15/D15-1,0) -> 0.092447088
A16: South | B16: 3 | C16: =SUMIFS(tblFinancials[Amount],tblFinancials[RegionKey],$B16,tblFinancials[AccountCategory],"Revenue",tblFinancials[FullDate],">="&DATE(C$13,1,1),tblFinancials[FullDate],"<="&DATE(C$13,12,31)) -> 999109.27 | D16: =SUMIFS(tblFinancials[Amount],tblFinancials[RegionKey],$B16,tblFinancials[AccountCategory],"Revenue",tblFinancials[FullDate],">="&DATE(D$13,1,1),tblFinancials[FullDate],"<="&DATE(D$13,12,31)) -> 1249050.2 | E16: =SUMIFS(tblFinancials[Amount],tblFinancials[RegionKey],$B16,tblFinancials[AccountCategory],"Revenue",tblFinancials[FullDate],">="&DATE(E$13,1,1),tblFinancials[FullDate],"<="&DATE(E$13,12,31)) -> 1490814 | F16: =IFERROR(D16/C16-1,0) -> 0.25016371 | G16: =IFERROR(E16/D16-1,0) -> 0.19355818
A17: East | B17: 4 | C17: =SUMIFS(tblFinancials[Amount],tblFinancials[RegionKey],$B17,tblFinancials[AccountCategory],"Revenue",tblFinancials[FullDate],">="&DATE(C$13,1,1),tblFinancials[FullDate],"<="&DATE(C$13,12,31)) -> 985650.47 | D17: =SUMIFS(tblFinancials[Amount],tblFinancials[RegionKey],$B17,tblFinancials[AccountCategory],"Revenue",tblFinancials[FullDate],">="&DATE(D$13,1,1),tblFinancials[FullDate],"<="&DATE(D$13,12,31)) -> 979027.16 | E17: =SUMIFS(tblFinancials[Amount],tblFinancials[RegionKey],$B17,tblFinancials[AccountCategory],"Revenue",tblFinancials[FullDate],">="&DATE(E$13,1,1),tblFinancials[FullDate],"<="&DATE(E$13,12,31)) -> 1213257 | F17: =IFERROR(D17/C17-1,0) -> -0.006719735 | G17: =IFERROR(E17/D17-1,0) -> 0.23924758
A18: Total Revenue | C18: =SUM(C14:C17) -> 4178883 | D18: =SUM(D14:D17) -> 4538318.6 | E18: =SUM(E14:E17) -> 4864066.1 | F18: =IFERROR(D18/C18-1,0) -> 0.086012365 | G18: =IFERROR(E18/D18-1,0) -> 0.071777124

Sheet Expense Analysis
A1: CASCADE OUTDOOR MANUFACTURING
A2: Historical Operating Expense Analysis
A4: Department | B4: DepartmentKey | C4: 2023 | D4: 2024 | E4: 2025 | F4: 2024 YoY % | G4: 2025 YoY % | H4: 2025 Expense Mix
A5: Executive | B5: 1 | C5: =SUMIFS(tblFinancials[Amount],tblFinancials[DepartmentKey],$B5,tblFinancials[AccountCategory],"Operating Expense",tblFinancials[FullDate],">="&DATE(C$4,1,1),tblFinancials[FullDate],"<="&DATE(C$4,12,31)) -> -89157.2 | D5: =SUMIFS(tblFinancials[Amount],tblFinancials[DepartmentKey],$B5,tblFinancials[AccountCategory],"Operating Expense",tblFinancials[FullDate],">="&DATE(D$4,1,1),tblFinancials[FullDate],"<="&DATE(D$4,12,31)) -> -140491.59 | E5: =SUMIFS(tblFinancials[Amount],tblFinancials[DepartmentKey],$B5,tblFinancials[AccountCategory],"Operating Expense",tblFinancials[FullDate],">="&DATE(E$4,1,1),tblFinancials[FullDate],"<="&DATE(E$4,12,31)) -> -134456.64 | F5: =IFERROR(D5/C5-1,0) -> 0.57577391 | G5: =IFERROR(E5/D5-1,0) -> -0.042955952 | H5: =IFERROR(E5/E13,0) -> 0.13425436
A6: Finance | B6: 2 | C6: =SUMIFS(tblFinancials[Amount],tblFinancials[DepartmentKey],$B6,tblFinancials[AccountCategory],"Operating Expense",tblFinancials[FullDate],">="&DATE(C$4,1,1),tblFinancials[FullDate],"<="&DATE(C$4,12,31)) -> -63275.71 | D6: =SUMIFS(tblFinancials[Amount],tblFinancials[DepartmentKey],$B6,tblFinancials[AccountCategory],"Operating Expense",tblFinancials[FullDate],">="&DATE(D$4,1,1),tblFinancials[FullDate],"<="&DATE(D$4,12,31)) -> -75718.71 | E6: =SUMIFS(tblFinancials[Amount],tblFinancials[DepartmentKey],$B6,tblFinancials[AccountCategory],"Operating Expense",tblFinancials[FullDate],">="&DATE(E$4,1,1),tblFinancials[FullDate],"<="&DATE(E$4,12,31)) -> -109025.24 | F6: =IFERROR(D6/C6-1,0) -> 0.19664734 | G6: =IFERROR(E6/D6-1,0) -> 0.43987186 | H6: =IFERROR(E6/E13,0) -> 0.10886122
A7: Human Resources | B7: 3 | C7: =SUMIFS(tblFinancials[Amount],tblFinancials[DepartmentKey],$B7,tblFinancials[AccountCategory],"Operating Expense",tblFinancials[FullDate],">="&DATE(C$4,1,1),tblFinancials[FullDate],"<="&DATE(C$4,12,31)) -> -80840.44 | D7: =SUMIFS(tblFinancials[Amount],tblFinancials[DepartmentKey],$B7,tblFinancials[AccountCategory],"Operating Expense",tblFinancials[FullDate],">="&DATE(D$4,1,1),tblFinancials[FullDate],"<="&DATE(D$4,12,31)) -> -100158.82 | E7: =SUMIFS(tblFinancials[Amount],tblFinancials[DepartmentKey],$B7,tblFinancials[AccountCategory],"Operating Expense",tblFinancials[FullDate],">="&DATE(E$4,1,1),tblFinancials[FullDate],"<="&DATE(E$4,12,31)) -> -174194.12 | F7: =IFERROR(D7/C7-1,0) -> 0.23896926 | G7: =IFERROR(E7/D7-1,0) -> 0.73917904 | H7: =IFERROR(E7/E13,0) -> 0.17393205
A8: Sales | B8: 4 | C8: =SUMIFS(tblFinancials[Amount],tblFinancials[DepartmentKey],$B8,tblFinancials[AccountCategory],"Operating Expense",tblFinancials[FullDate],">="&DATE(C$4,1,1),tblFinancials[FullDate],"<="&DATE(C$4,12,31)) -> -125819.73 | D8: =SUMIFS(tblFinancials[Amount],tblFinancials[DepartmentKey],$B8,tblFinancials[AccountCategory],"Operating Expense",tblFinancials[FullDate],">="&DATE(D$4,1,1),tblFinancials[FullDate],"<="&DATE(D$4,12,31)) -> -123310.94 | E8: =SUMIFS(tblFinancials[Amount],tblFinancials[DepartmentKey],$B8,tblFinancials[AccountCategory],"Operating Expense",tblFinancials[FullDate],">="&DATE(E$4,1,1),tblFinancials[FullDate],"<="&DATE(E$4,12,31)) -> -151909.95 | F8: =IFERROR(D8/C8-1,0) -> -0.01993956 | G8: =IFERROR(E8/D8-1,0) -> 0.23192598 | H8: =IFERROR(E8/E13,0) -> 0.15168141
A9: Marketing | B9: 5 | C9: =SUMIFS(tblFinancials[Amount],tblFinancials[DepartmentKey],$B9,tblFinancials[AccountCategory],"Operating Expense",tblFinancials[FullDate],">="&DATE(C$4,1,1),tblFinancials[FullDate],"<="&DATE(C$4,12,31)) -> -109322.91 | D9: =SUMIFS(tblFinancials[Amount],tblFinancials[DepartmentKey],$B9,tblFinancials[AccountCategory],"Operating Expense",tblFinancials[FullDate],">="&DATE(D$4,1,1),tblFinancials[FullDate],"<="&DATE(D$4,12,31)) -> -108724.82 | E9: =SUMIFS(tblFinancials[Amount],tblFinancials[DepartmentKey],$B9,tblFinancials[AccountCategory],"Operating Expense",tblFinancials[FullDate],">="&DATE(E$4,1,1),tblFinancials[FullDate],"<="&DATE(E$4,12,31)) -> -81967.01 | F9: =IFERROR(D9/C9-1,0) -> -0.0054708569 | G9: =IFERROR(E9/D9-1,0) -> -0.24610581 | H9: =IFERROR(E9/E13,0) -> 0.081843695
A10: Operations | B10: 6 | C10: =SUMIFS(tblFinancials[Amount],tblFinancials[DepartmentKey],$B10,tblFinancials[AccountCategory],"Operating Expense",tblFinancials[FullDate],">="&DATE(C$4,1,1),tblFinancials[FullDate],"<="&DATE(C$4,12,31)) -> -157597.56 | D10: =SUMIFS(tblFinancials[Amount],tblFinancials[DepartmentKey],$B10,tblFinancials[AccountCategory],"Operating Expense",tblFinancials[FullDate],">="&DATE(D$4,1,1),tblFinancials[FullDate],"<="&DATE(D$4,12,31)) -> -146199.04 | E10: =SUMIFS(tblFinancials[Amount],tblFinancials[DepartmentKey],$B10,tblFinancials[AccountCategory],"Operating Expense",tblFinancials[FullDate],">="&DATE(E$4,1,1),tblFinancials[FullDate],"<="&DATE(E$4,12,31)) -> -113383.66 | F10: =IFERROR(D10/C10-1,0) -> -0.072326754 | G10: =IFERROR(E10/D10-1,0) -> -0.22445688 | H10: =IFERROR(E10/E13,0) -> 0.11321308
A11: Informaton Technology | B11: 7 | C11: =SUMIFS(tblFinancials[Amount],tblFinancials[DepartmentKey],$B11,tblFinancials[AccountCategory],"Operating Expense",tblFinancials[FullDate],">="&DATE(C$4,1,1),tblFinancials[FullDate],"<="&DATE(C$4,12,31)) -> -186606.9 | D11: =SUMIFS(tblFinancials[Amount],tblFinancials[DepartmentKey],$B11,tblFinancials[AccountCategory],"Operating Expense",tblFinancials[FullDate],">="&DATE(D$4,1,1),tblFinancials[FullDate],"<="&DATE(D$4,12,31)) -> -143596.91 | E11: =SUMIFS(tblFinancials[Amount],tblFinancials[DepartmentKey],$B11,tblFinancials[AccountCategory],"Operating Expense",tblFinancials[FullDate],">="&DATE(E$4,1,1),tblFinancials[FullDate],"<="&DATE(E$4,12,31)) -> -122610.08 | F11: =IFERROR(D11/C11-1,0) -> -0.23048446 | G11: =IFERROR(E11/D11-1,0) -> -0.14615099 | H11: =IFERROR(E11/E13,0) -> 0.12242562
A12: Customer Service | B12: 8 | C12: =SUMIFS(tblFinancials[Amount],tblFinancials[DepartmentKey],$B12,tblFinancials[AccountCategory],"Operating Expense",tblFinancials[FullDate],">="&DATE(C$4,1,1),tblFinancials[FullDate],"<="&DATE(C$4,12,31)) -> -95744.31 | D12: =SUMIFS(tblFinancials[Amount],tblFinancials[DepartmentKey],$B12,tblFinancials[AccountCategory],"Operating Expense",tblFinancials[FullDate],">="&DATE(D$4,1,1),tblFinancials[FullDate],"<="&DATE(D$4,12,31)) -> -128017.85 | E12: =SUMIFS(tblFinancials[Amount],tblFinancials[DepartmentKey],$B12,tblFinancials[AccountCategory],"Operating Expense",tblFinancials[FullDate],">="&DATE(E$4,1,1),tblFinancials[FullDate],"<="&DATE(E$4,12,31)) -> -113960.01 | F12: =IFERROR(D12/C12-1,0) -> 0.3370805 | G12: =IFERROR(E12/D12-1,0) -> -0.10981156 | H12: =IFERROR(E12/E13,0) -> 0.11378856
A13: Total Operating Expenses | C13: =SUM(C5:C12) -> -908364.76 | D13: =SUM(D5:D12) -> -966218.68 | E13: =SUM(E5:E12) -> -1001506.7 | H13: =SUM(H5:H12) -> 1

Sheet Monthly Analysis
A1: CASCADE OUTDOOR MANUFACTURING
A2: Historical Monthly Financial Analysis
A4: Month | B4: 2023 Revenue | C4: 2024 Revenue | D4: 2025 Revenue | E4: 2024 YoY % | F4: 2025 YoY % | G4: 2025 Revenue Mix | H4: Month Number | J4: Revenue Seasonality Summary
A5: January | B5: =SUMIFS(tblFinancials[Amount],tblFinancials[AccountCategory],"Revenue",tblFinancials[FullDate],">="&DATE(2023,$H5,1),tblFinancials[FullDate],"<"&EDATE(DATE(2023,$H5,1),1)) -> 304093.39 | C5: =SUMIFS(tblFinancials[Amount],tblFinancials[AccountCategory],"Revenue",tblFinancials[FullDate],">="&DATE(2024,$H5,1),tblFinancials[FullDate],"<"&EDATE(DATE(2024,$H5,1),1)) -> 331735.32 | D5: =SUMIFS(tblFinancials[Amount],tblFinancials[AccountCategory],"Revenue",tblFinancials[FullDate],">="&DATE(2025,$H5,1),tblFinancials[FullDate],"<"&EDATE(DATE(2025,$H5,1),1)) -> 353732.04 | E5: =IFERROR(C5/B5-1,0) -> 0.090899477 | F5: =IFERROR(D5/C5-1,0) -> 0.066308043 | G5: =IFERROR(D5/$D$17,0) -> 0.072723527 | H5: 1
A6: February | B6: =SUMIFS(tblFinancials[Amount],tblFinancials[AccountCategory],"Revenue",tblFinancials[FullDate],">="&DATE(2023,$H6,1),tblFinancials[FullDate],"<"&EDATE(DATE(2023,$H6,1),1)) -> 291128.88 | C6: =SUMIFS(tblFinancials[Amount],tblFinancials[AccountCategory],"Revenue",tblFinancials[FullDate],">="&DATE(2024,$H6,1),tblFinancials[FullDate],"<"&EDATE(DATE(2024,$H6,1),1)) -> 317057.67 | D6: =SUMIFS(tblFinancials[Amount],tblFinancials[AccountCategory],"Revenue",tblFinancials[FullDate],">="&DATE(2025,$H6,1),tblFinancials[FullDate],"<"&EDATE(DATE(2025,$H6,1),1)) -> 339053.14 | E6: =IFERROR(C6/B6-1,0) -> 0.089062926 | F6: =IFERROR(D6/C6-1,0) -> 0.06937372 | G6: =IFERROR(D6/$D$17,0) -> 0.069705702 | H6: 2 | J6: Month | K6: 2023 Mix | L6: 2024 Mix | M6: 2025 Mix | N6: 3-Year Average
A7: March | B7: =SUMIFS(tblFinancials[Amount],tblFinancials[AccountCategory],"Revenue",tblFinancials[FullDate],">="&DATE(2023,$H7,1),tblFinancials[FullDate],"<"&EDATE(DATE(2023,$H7,1),1)) -> 317411.6 | C7: =SUMIFS(tblFinancials[Amount],tblFinancials[AccountCategory],"Revenue",tblFinancials[FullDate],">="&DATE(2024,$H7,1),tblFinancials[FullDate],"<"&EDATE(DATE(2024,$H7,1),1)) -> 348594.04 | D7: =SUMIFS(tblFinancials[Amount],tblFinancials[AccountCategory],"Revenue",tblFinancials[FullDate],">="&DATE(2025,$H7,1),tblFinancials[FullDate],"<"&EDATE(DATE(2025,$H7,1),1)) -> 373615.06 | E7: =IFERROR(C7/B7-1,0) -> 0.098239762 | F7: =IFERROR(D7/C7-1,0) -> 0.071776959 | G7: =IFERROR(D7/$D$17,0) -> 0.076811263 | H7: 3 | J7: January | K7: =IFERROR(B5/$B$17,0) -> 0.07276906 | L7: =IFERROR(C5/$C$17,0) -> 0.073096525 | M7: =IFERROR(D5/$D$17,0) -> 0.072723527 | N7: =AVERAGE(K7:M7) -> 0.072863037
A8: April | B8: =SUMIFS(tblFinancials[Amount],tblFinancials[AccountCategory],"Revenue",tblFinancials[FullDate],">="&DATE(2023,$H8,1),tblFinancials[FullDate],"<"&EDATE(DATE(2023,$H8,1),1)) -> 340870.26 | C8: =SUMIFS(tblFinancials[Amount],tblFinancials[AccountCategory],"Revenue",tblFinancials[FullDate],">="&DATE(2024,$H8,1),tblFinancials[FullDate],"<"&EDATE(DATE(2024,$H8,1),1)) -> 377158.19 | D8: =SUMIFS(tblFinancials[Amount],tblFinancials[AccountCategory],"Revenue",tblFinancials[FullDate],">="&DATE(2025,$H8,1),tblFinancials[FullDate],"<"&EDATE(DATE(2025,$H8,1),1)) -> 398451.02 | E8: =IFERROR(C8/B8-1,0) -> 0.10645672 | F8: =IFERROR(D8/C8-1,0) -> 0.056455966 | G8: =IFERROR(D8/$D$17,0) -> 0.081917271 | H8: 4 | J8: February | K8: =IFERROR(B6/$B$17,0) -> 0.069666674 | L8: =IFERROR(C6/$C$17,0) -> 0.069862364 | M8: =IFERROR(D6/$D$17,0) -> 0.069705702 | N8: =AVERAGE(K8:M8) -> 0.069744913
A9: May | B9: 357855.3 | C9: =SUMIFS(tblFinancials[Amount],tblFinancials[AccountCategory],"Revenue",tblFinancials[FullDate],">="&DATE(2024,$H9,1),tblFinancials[FullDate],"<"&EDATE(DATE(2024,$H9,1),1)) -> 390508.44 | D9: =SUMIFS(tblFinancials[Amount],tblFinancials[AccountCategory],"Revenue",tblFinancials[FullDate],">="&DATE(2025,$H9,1),tblFinancials[FullDate],"<"&EDATE(DATE(2025,$H9,1),1)) -> 419822.65 | E9: =IFERROR(C9/B9-1,0) -> 0.091246769 | F9: =IFERROR(D9/C9-1,0) -> 0.075066777 | G9: =IFERROR(D9/$D$17,0) -> 0.08631105 | H9: 5 | J9: March | K9: =IFERROR(B7/$B$17,0) -> 0.075956086 | L9: =IFERROR(C7/$C$17,0) -> 0.076811275 | M9: =IFERROR(D7/$D$17,0) -> 0.076811263 | N9: =AVERAGE(K9:M9) -> 0.076526208
A10: June | B10: =SUMIFS(tblFinancials[Amount],tblFinancials[AccountCategory],"Revenue",tblFinancials[FullDate],">="&DATE(2023,$H10,1),tblFinancials[FullDate],"<"&EDATE(DATE(2023,$H10,1),1)) -> 372565.38 | C10: =SUMIFS(tblFinancials[Amount],tblFinancials[AccountCategory],"Revenue",tblFinancials[FullDate],">="&DATE(2024,$H10,1),tblFinancials[FullDate],"<"&EDATE(DATE(2024,$H10,1),1)) -> 402140.43 | D10: =SUMIFS(tblFinancials[Amount],tblFinancials[AccountCategory],"Revenue",tblFinancials[FullDate],">="&DATE(2025,$H10,1),tblFinancials[FullDate],"<"&EDATE(DATE(2025,$H10,1),1)) -> 426140.54 | E10: =IFERROR(C10/B10-1,0) -> 0.079382174 | F10: =IFERROR(D10/C10-1,0) -> 0.059680918 | G10: =IFERROR(D10/$D$17,0) -> 0.08760994 | H10: 6 | J10: April | K10: =IFERROR(B8/$B$17,0) -> 0.081569706 | L10: =IFERROR(C8/$C$17,0) -> 0.083105269 | M10: =IFERROR(D8/$D$17,0) -> 0.081917271 | N10: =AVERAGE(K10:M10) -> 0.082197415
A11: July | B11: =SUMIFS(tblFinancials[Amount],tblFinancials[AccountCategory],"Revenue",tblFinancials[FullDate],">="&DATE(2023,$H11,1),tblFinancials[FullDate],"<"&EDATE(DATE(2023,$H11,1),1)) -> 373124.78 | C11: =SUMIFS(tblFinancials[Amount],tblFinancials[AccountCategory],"Revenue",tblFinancials[FullDate],">="&DATE(2024,$H11,1),tblFinancials[FullDate],"<"&EDATE(DATE(2024,$H11,1),1)) -> 403427.72 | D11: =SUMIFS(tblFinancials[Amount],tblFinancials[AccountCategory],"Revenue",tblFinancials[FullDate],">="&DATE(2025,$H11,1),tblFinancials[FullDate],"<"&EDATE(DATE(2025,$H11,1),1)) -> 441078.15 | E11: =IFERROR(C11/B11-1,0) -> 0.081213957 | F11: =IFERROR(D11/C11-1,0) -> 0.093326334 | G11: =IFERROR(D11/$D$17,0) -> 0.090680953 | H11: 7 | J11: May | K11: =IFERROR(B9/$B$17,0) -> 0.085634199 | L11: =IFERROR(C9/$C$17,0) -> 0.086046942 | M11: =IFERROR(D9/$D$17,0) -> 0.08631105 | N11: =AVERAGE(K11:M11) -> 0.085997397
A12: August | B12: =SUMIFS(tblFinancials[Amount],tblFinancials[AccountCategory],"Revenue",tblFinancials[FullDate],">="&DATE(2023,$H12,1),tblFinancials[FullDate],"<"&EDATE(DATE(2023,$H12,1),1)) -> 367454.45 | C12: =SUMIFS(tblFinancials[Amount],tblFinancials[AccountCategory],"Revenue",tblFinancials[FullDate],">="&DATE(2024,$H12,1),tblFinancials[FullDate],"<"&EDATE(DATE(2024,$H12,1),1)) -> 394584.98 | D12: =SUMIFS(tblFinancials[Amount],tblFinancials[AccountCategory],"Revenue",tblFinancials[FullDate],">="&DATE(2025,$H12,1),tblFinancials[FullDate],"<"&EDATE(DATE(2025,$H12,1),1)) -> 423481.68 | E12: =IFERROR(C12/B12-1,0) -> 0.073833723 | F12: =IFERROR(D12/C12-1,0) -> 0.073233147 | G12: =IFERROR(D12/$D$17,0) -> 0.087063307 | H12: 8 | J12: June | K12: =IFERROR(B10/$B$17,0) -> 0.089154298 | L12: =IFERROR(C10/$C$17,0) -> 0.088610004 | M12: =IFERROR(D10/$D$17,0) -> 0.08760994 | N12: =AVERAGE(K12:M12) -> 0.08845808
A13: September | B13: =SUMIFS(tblFinancials[Amount],tblFinancials[AccountCategory],"Revenue",tblFinancials[FullDate],">="&DATE(2023,$H13,1),tblFinancials[FullDate],"<"&EDATE(DATE(2023,$H13,1),1)) -> 336103.24 | C13: =SUMIFS(tblFinancials[Amount],tblFinancials[AccountCategory],"Revenue",tblFinancials[FullDate],">="&DATE(2024,$H13,1),tblFinancials[FullDate],"<"&EDATE(DATE(2024,$H13,1),1)) -> 362264.52 | D13: =SUMIFS(tblFinancials[Amount],tblFinancials[AccountCategory],"Revenue",tblFinancials[FullDate],">="&DATE(2025,$H13,1),tblFinancials[FullDate],"<"&EDATE(DATE(2025,$H13,1),1)) -> 393858.51 | E13: =IFERROR(C13/B13-1,0) -> 0.077837036 | F13: =IFERROR(D13/C13-1,0) -> 0.087212488 | G13: =IFERROR(D13/$D$17,0) -> 0.0809731 | H13: 9 | J13: July | K13: =IFERROR(B11/$B$17,0) -> 0.089288161 | L13: =IFERROR(C11/$C$17,0) -> 0.088893653 | M13: =IFERROR(D11/$D$17,0) -> 0.090680953 | N13: =AVERAGE(K13:M13) -> 0.089620922
A14: October | B14: =SUMIFS(tblFinancials[Amount],tblFinancials[AccountCategory],"Revenue",tblFinancials[FullDate],">="&DATE(2023,$H14,1),tblFinancials[FullDate],"<"&EDATE(DATE(2023,$H14,1),1)) -> 345417.85 | C14: =SUMIFS(tblFinancials[Amount],tblFinancials[AccountCategory],"Revenue",tblFinancials[FullDate],">="&DATE(2024,$H14,1),tblFinancials[FullDate],"<"&EDATE(DATE(2024,$H14,1),1)) -> 375033.89 | D14: =SUMIFS(tblFinancials[Amount],tblFinancials[AccountCategory],"Revenue",tblFinancials[FullDate],">="&DATE(2025,$H14,1),tblFinancials[FullDate],"<"&EDATE(DATE(2025,$H14,1),1)) -> 397717.38 | E14: =IFERROR(C14/B14-1,0) -> 0.08573975 | F14: =IFERROR(D14/C14-1,0) -> 0.060483841 | G14: =IFERROR(D14/$D$17,0) -> 0.081766442 | H14: 10 | J14: August | K14: =IFERROR(B12/$B$17,0) -> 0.08793126 | L14: =IFERROR(C12/$C$17,0) -> 0.086945191 | M14: =IFERROR(D12/$D$17,0) -> 0.087063307 | N14: =AVERAGE(K14:M14) -> 0.087313253
A15: November | B15: =SUMIFS(tblFinancials[Amount],tblFinancials[AccountCategory],"Revenue",tblFinancials[FullDate],">="&DATE(2023,$H15,1),tblFinancials[FullDate],"<"&EDATE(DATE(2023,$H15,1),1)) -> 368643.5 | C15: =SUMIFS(tblFinancials[Amount],tblFinancials[AccountCategory],"Revenue",tblFinancials[FullDate],">="&DATE(2024,$H15,1),tblFinancials[FullDate],"<"&EDATE(DATE(2024,$H15,1),1)) -> 402221.04 | D15: =SUMIFS(tblFinancials[Amount],tblFinancials[AccountCategory],"Revenue",tblFinancials[FullDate],">="&DATE(2025,$H15,1),tblFinancials[FullDate],"<"&EDATE(DATE(2025,$H15,1),1)) -> 428684 | E15: =IFERROR(C15/B15-1,0) -> 0.091084042 | F15: =IFERROR(D15/C15-1,0) -> 0.065792083 | G15: =IFERROR(D15/$D$17,0) -> 0.088132849 | H15: 11 | J15: September | K15: =IFERROR(B13/$B$17,0) -> 0.080428966 | L15: =IFERROR(C13/$C$17,0) -> 0.079823509 | M15: =IFERROR(D13/$D$17,0) -> 0.0809731 | N15: =AVERAGE(K15:M15) -> 0.080408525
A16: December | B16: =SUMIFS(tblFinancials[Amount],tblFinancials[AccountCategory],"Revenue",tblFinancials[FullDate],">="&DATE(2023,$H16,1),tblFinancials[FullDate],"<"&EDATE(DATE(2023,$H16,1),1)) -> 404214.39 | C16: =SUMIFS(tblFinancials[Amount],tblFinancials[AccountCategory],"Revenue",tblFinancials[FullDate],">="&DATE(2024,$H16,1),tblFinancials[FullDate],"<"&EDATE(DATE(2024,$H16,1),1)) -> 433592.39 | D16: =SUMIFS(tblFinancials[Amount],tblFinancials[AccountCategory],"Revenue",tblFinancials[FullDate],">="&DATE(2025,$H16,1),tblFinancials[FullDate],"<"&EDATE(DATE(2025,$H16,1),1)) -> 468431.92 | E16: =IFERROR(C16/B16-1,0) -> 0.072679253 | F16: =IFERROR(D16/C16-1,0) -> 0.08035088 | G16: =IFERROR(D16/$D$17,0) -> 0.096304596 | H16: 12 | J16: October | K16: =IFERROR(B14/$B$17,0) -> 0.082657937 | L16: =IFERROR(C14/$C$17,0) -> 0.082637188 | M16: =IFERROR(D14/$D$17,0) -> 0.081766442 | N16: =AVERAGE(K16:M16) -> 0.082353856
A17: Total Revenue | B17: =SUM(B5:B16) -> 4178883 | C17: =SUM(C5:C16) -> 4538318.6 | D17: =SUM(D5:D16) -> 4864066.1 | E17: =IFERROR(C17/B17-1,0) -> 0.086012365 | F17: =IFERROR(D17/C17-1,0) -> 0.071777124 | G17: =SUM(G5:G16) -> 1 | J17: November | K17: =IFERROR(B15/$B$17,0) -> 0.088215798 | L17: =IFERROR(C15/$C$17,0) -> 0.088627766 | M17: =IFERROR(D15/$D$17,0) -> 0.088132849 | N17: =AVERAGE(K17:M17) -> 0.088325471
J18: December | K18: =IFERROR(B16/$B$17,0) -> 0.096727855 | L18: =IFERROR(C16/$C$17,0) -> 0.095540315 | M18: =IFERROR(D16/$D$17,0) -> 0.096304596 | N18: =AVERAGE(K18:M18) -> 0.096190922
J19: Total | K19: =SUM(K7:K18) -> 1 | L19: =SUM(L7:L18) -> 1 | M19: =SUM(M7:M18) -> 1 | N19: =SUM(N7:N18) -> 1
A20: Historical Monthly Operating Expense Analysis
A22: Month | B22: 2023 Operating Expenses | C22: 2024 Operating Expenses | D22: 2025 Operating Expenses | E22: 2024 YoY % | F22: 2025 YoY % | G22: 2025 Expense Mix | H22: Month Number
A23: January | B23: =SUMIFS(tblFinancials[Amount],tblFinancials[AccountCategory],"Operating Expense",tblFinancials[FullDate],">="&DATE(2023,$H23,1),tblFinancials[FullDate],"<"&EDATE(DATE(2023,$H23,1),1)) -> -55903.95 | C23: =SUMIFS(tblFinancials[Amount],tblFinancials[AccountCategory],"Operating Expense",tblFinancials[FullDate],">="&DATE(2024,$H23,1),tblFinancials[FullDate],"<"&EDATE(DATE(2024,$H23,1),1)) -> -77957.8 | D23: =SUMIFS(tblFinancials[Amount],tblFinancials[AccountCategory],"Operating Expense",tblFinancials[FullDate],">="&DATE(2025,$H23,1),tblFinancials[FullDate],"<"&EDATE(DATE(2025,$H23,1),1)) -> -75351.81 | E23: =IFERROR(C23/B23-1,0) -> 0.39449538 | F23: =IFERROR(D23/C23-1,0) -> -0.033428214 | G23: =IFERROR(D23/$D$35,0) -> 0.075238447 | H23: 1
A24: February | B24: =SUMIFS(tblFinancials[Amount],tblFinancials[AccountCategory],"Operating Expense",tblFinancials[FullDate],">="&DATE(2023,$H24,1),tblFinancials[FullDate],"<"&EDATE(DATE(2023,$H24,1),1)) -> -63338.21 | C24: =SUMIFS(tblFinancials[Amount],tblFinancials[AccountCategory],"Operating Expense",tblFinancials[FullDate],">="&DATE(2024,$H24,1),tblFinancials[FullDate],"<"&EDATE(DATE(2024,$H24,1),1)) -> -68175.87 | D24: =SUMIFS(tblFinancials[Amount],tblFinancials[AccountCategory],"Operating Expense",tblFinancials[FullDate],">="&DATE(2025,$H24,1),tblFinancials[FullDate],"<"&EDATE(DATE(2025,$H24,1),1)) -> -79677.49 | E24: =IFERROR(C24/B24-1,0) -> 0.076378224 | F24: =IFERROR(D24/C24-1,0) -> 0.16870514 | G24: =IFERROR(D24/$D$35,0) -> 0.07955762 | H24: 2
A25: March | B25: =SUMIFS(tblFinancials[Amount],tblFinancials[AccountCategory],"Operating Expense",tblFinancials[FullDate],">="&DATE(2023,$H25,1),tblFinancials[FullDate],"<"&EDATE(DATE(2023,$H25,1),1)) -> -74591.73 | C25: =SUMIFS(tblFinancials[Amount],tblFinancials[AccountCategory],"Operating Expense",tblFinancials[FullDate],">="&DATE(2024,$H25,1),tblFinancials[FullDate],"<"&EDATE(DATE(2024,$H25,1),1)) -> -75429.02 | D25: =SUMIFS(tblFinancials[Amount],tblFinancials[AccountCategory],"Operating Expense",tblFinancials[FullDate],">="&DATE(2025,$H25,1),tblFinancials[FullDate],"<"&EDATE(DATE(2025,$H25,1),1)) -> -73359.69 | E25: =IFERROR(C25/B25-1,0) -> 0.011224971 | F25: =IFERROR(D25/C25-1,0) -> -0.027434136 | G25: =IFERROR(D25/$D$35,0) -> 0.073249325 | H25: 3
A26: April | B26: =SUMIFS(tblFinancials[Amount],tblFinancials[AccountCategory],"Operating Expense",tblFinancials[FullDate],">="&DATE(2023,$H26,1),tblFinancials[FullDate],"<"&EDATE(DATE(2023,$H26,1),1)) -> -80104.51 | C26: =SUMIFS(tblFinancials[Amount],tblFinancials[AccountCategory],"Operating Expense",tblFinancials[FullDate],">="&DATE(2024,$H26,1),tblFinancials[FullDate],"<"&EDATE(DATE(2024,$H26,1),1)) -> -75612.31 | D26: =SUMIFS(tblFinancials[Amount],tblFinancials[AccountCategory],"Operating Expense",tblFinancials[FullDate],">="&DATE(2025,$H26,1),tblFinancials[FullDate],"<"&EDATE(DATE(2025,$H26,1),1)) -> -79739.4 | E26: =IFERROR(C26/B26-1,0) -> -0.056079239 | F26: =IFERROR(D26/C26-1,0) -> 0.05458225 | G26: =IFERROR(D26/$D$35,0) -> 0.079619437 | H26: 4
A27: May | B27: =SUMIFS(tblFinancials[Amount],tblFinancials[AccountCategory],"Operating Expense",tblFinancials[FullDate],">="&DATE(2023,$H27,1),tblFinancials[FullDate],"<"&EDATE(DATE(2023,$H27,1),1)) -> -76041.62 | C27: =SUMIFS(tblFinancials[Amount],tblFinancials[AccountCategory],"Operating Expense",tblFinancials[FullDate],">="&DATE(2024,$H27,1),tblFinancials[FullDate],"<"&EDATE(DATE(2024,$H27,1),1)) -> -91769.48 | D27: =SUMIFS(tblFinancials[Amount],tblFinancials[AccountCategory],"Operating Expense",tblFinancials[FullDate],">="&DATE(2025,$H27,1),tblFinancials[FullDate],"<"&EDATE(DATE(2025,$H27,1),1)) -> -83741.15 | E27: =IFERROR(C27/B27-1,0) -> 0.20683226 | F27: =IFERROR(D27/C27-1,0) -> -0.08748366 | G27: =IFERROR(D27/$D$35,0) -> 0.083615166 | H27: 5
A28: June | B28: =SUMIFS(tblFinancials[Amount],tblFinancials[AccountCategory],"Operating Expense",tblFinancials[FullDate],">="&DATE(2023,$H28,1),tblFinancials[FullDate],"<"&EDATE(DATE(2023,$H28,1),1)) -> -71489.31 | C28: =SUMIFS(tblFinancials[Amount],tblFinancials[AccountCategory],"Operating Expense",tblFinancials[FullDate],">="&DATE(2024,$H28,1),tblFinancials[FullDate],"<"&EDATE(DATE(2024,$H28,1),1)) -> -78241.81 | D28: =SUMIFS(tblFinancials[Amount],tblFinancials[AccountCategory],"Operating Expense",tblFinancials[FullDate],">="&DATE(2025,$H28,1),tblFinancials[FullDate],"<"&EDATE(DATE(2025,$H28,1),1)) -> -74795.32 | E28: =IFERROR(C28/B28-1,0) -> 0.094454681 | F28: =IFERROR(D28/C28-1,0) -> -0.044049211 | G28: =IFERROR(D28/$D$35,0) -> 0.074682795 | H28: 6
A29: July | B29: =SUMIFS(tblFinancials[Amount],tblFinancials[AccountCategory],"Operating Expense",tblFinancials[FullDate],">="&DATE(2023,$H29,1),tblFinancials[FullDate],"<"&EDATE(DATE(2023,$H29,1),1)) -> -87684.32 | C29: =SUMIFS(tblFinancials[Amount],tblFinancials[AccountCategory],"Operating Expense",tblFinancials[FullDate],">="&DATE(2024,$H29,1),tblFinancials[FullDate],"<"&EDATE(DATE(2024,$H29,1),1)) -> -85817.01 | D29: =SUMIFS(tblFinancials[Amount],tblFinancials[AccountCategory],"Operating Expense",tblFinancials[FullDate],">="&DATE(2025,$H29,1),tblFinancials[FullDate],"<"&EDATE(DATE(2025,$H29,1),1)) -> -86599.96 | E29: =IFERROR(C29/B29-1,0) -> -0.021295826 | F29: =IFERROR(D29/C29-1,0) -> 0.0091234826 | G29: =IFERROR(D29/$D$35,0) -> 0.086469675 | H29: 7
A30: August | B30: =SUMIFS(tblFinancials[Amount],tblFinancials[AccountCategory],"Operating Expense",tblFinancials[FullDate],">="&DATE(2023,$H30,1),tblFinancials[FullDate],"<"&EDATE(DATE(2023,$H30,1),1)) -> -78455.09 | C30: =SUMIFS(tblFinancials[Amount],tblFinancials[AccountCategory],"Operating Expense",tblFinancials[FullDate],">="&DATE(2024,$H30,1),tblFinancials[FullDate],"<"&EDATE(DATE(2024,$H30,1),1)) -> -76229.61 | D30: =SUMIFS(tblFinancials[Amount],tblFinancials[AccountCategory],"Operating Expense",tblFinancials[FullDate],">="&DATE(2025,$H30,1),tblFinancials[FullDate],"<"&EDATE(DATE(2025,$H30,1),1)) -> -99518.19 | E30: =IFERROR(C30/B30-1,0) -> -0.028366292 | F30: =IFERROR(D30/C30-1,0) -> 0.3055057 | G30: =IFERROR(D30/$D$35,0) -> 0.099368471 | H30: 8
A31: September | B31: =SUMIFS(tblFinancials[Amount],tblFinancials[AccountCategory],"Operating Expense",tblFinancials[FullDate],">="&DATE(2023,$H31,1),tblFinancials[FullDate],"<"&EDATE(DATE(2023,$H31,1),1)) -> -78984.26 | C31: =SUMIFS(tblFinancials[Amount],tblFinancials[AccountCategory],"Operating Expense",tblFinancials[FullDate],">="&DATE(2024,$H31,1),tblFinancials[FullDate],"<"&EDATE(DATE(2024,$H31,1),1)) -> -85132.16 | D31: =SUMIFS(tblFinancials[Amount],tblFinancials[AccountCategory],"Operating Expense",tblFinancials[FullDate],">="&DATE(2025,$H31,1),tblFinancials[FullDate],"<"&EDATE(DATE(2025,$H31,1),1)) -> -69656.83 | E31: =IFERROR(C31/B31-1,0) -> 0.077837027 | F31: =IFERROR(D31/C31-1,0) -> -0.18178007 | G31: =IFERROR(D31/$D$35,0) -> 0.069552035 | H31: 9
A32: October | B32: =SUMIFS(tblFinancials[Amount],tblFinancials[AccountCategory],"Operating Expense",tblFinancials[FullDate],">="&DATE(2023,$H32,1),tblFinancials[FullDate],"<"&EDATE(DATE(2023,$H32,1),1)) -> -75202.1 | C32: =SUMIFS(tblFinancials[Amount],tblFinancials[AccountCategory],"Operating Expense",tblFinancials[FullDate],">="&DATE(2024,$H32,1),tblFinancials[FullDate],"<"&EDATE(DATE(2024,$H32,1),1)) -> -80637.54 | D32: =SUMIFS(tblFinancials[Amount],tblFinancials[AccountCategory],"Operating Expense",tblFinancials[FullDate],">="&DATE(2025,$H32,1),tblFinancials[FullDate],"<"&EDATE(DATE(2025,$H32,1),1)) -> -68244.63 | E32: =IFERROR(C32/B32-1,0) -> 0.072277769 | F32: =IFERROR(D32/C32-1,0) -> -0.15368661 | G32: =IFERROR(D32/$D$35,0) -> 0.06814196 | H32: 10
A33: November | B33: =SUMIFS(tblFinancials[Amount],tblFinancials[AccountCategory],"Operating Expense",tblFinancials[FullDate],">="&DATE(2023,$H33,1),tblFinancials[FullDate],"<"&EDATE(DATE(2023,$H33,1),1)) -> -79646.17 | C33: =SUMIFS(tblFinancials[Amount],tblFinancials[AccountCategory],"Operating Expense",tblFinancials[FullDate],">="&DATE(2024,$H33,1),tblFinancials[FullDate],"<"&EDATE(DATE(2024,$H33,1),1)) -> -94521.94 | D33: =SUMIFS(tblFinancials[Amount],tblFinancials[AccountCategory],"Operating Expense",tblFinancials[FullDate],">="&DATE(2025,$H33,1),tblFinancials[FullDate],"<"&EDATE(DATE(2025,$H33,1),1)) -> -100740.74 | E33: =IFERROR(C33/B33-1,0) -> 0.1867732 | F33: =IFERROR(D33/C33-1,0) -> 0.065792132 | G33: =IFERROR(D33/$D$35,0) -> 0.10058918 | H33: 11
A34: December | B34: =SUMIFS(tblFinancials[Amount],tblFinancials[AccountCategory],"Operating Expense",tblFinancials[FullDate],">="&DATE(2023,$H34,1),tblFinancials[FullDate],"<"&EDATE(DATE(2023,$H34,1),1)) -> -86923.49 | C34: =SUMIFS(tblFinancials[Amount],tblFinancials[AccountCategory],"Operating Expense",tblFinancials[FullDate],">="&DATE(2024,$H34,1),tblFinancials[FullDate],"<"&EDATE(DATE(2024,$H34,1),1)) -> -76694.13 | D34: =SUMIFS(tblFinancials[Amount],tblFinancials[AccountCategory],"Operating Expense",tblFinancials[FullDate],">="&DATE(2025,$H34,1),tblFinancials[FullDate],"<"&EDATE(DATE(2025,$H34,1),1)) -> -110081.5 | E34: =IFERROR(C34/B34-1,0) -> -0.11768234 | F34: =IFERROR(D34/C34-1,0) -> 0.43533149 | G34: =IFERROR(D34/$D$35,0) -> 0.10991589 | H34: 12
A35: Total Operating Expenses | B35: =SUM(B23:B34) -> -908364.76 | C35: =SUM(C23:C34) -> -966218.68 | D35: =SUM(D23:D34) -> -1001506.7 | G35: =SUM(G23:G34) -> 1
A38: Monthly Operating Income Analysis
A40: Month | B40: 2023 Operating Income | C40: 2024 Operating Income | D40: 2025 Operating Income
A41: January | B41: =SUMIFS(tblFinancials[Amount],tblFinancials[AccountCategory],"Revenue",tblFinancials[FullDate],">="&DATE(2023,$H23,1),tblFinancials[FullDate],"<"&EDATE(DATE(2023,$H23,1),1))+SUMIFS(tblFinancials[Amount],tblFinancials[AccountCategory],"Cost of Sales",tblFinancials[FullDate],">="&DATE(2023,$H23,1),tblFinancials[FullDate],"<"&EDATE(DATE(2023,$H23,1),1))+SUMIFS(tblFinancials[Amount],tblFinancials[AccountCategory],"Operating Expense",tblFinancials[FullDate],">="&DATE(2023,$H23,1),tblFinancials[FullDate],"<"&EDATE(DATE(2023,$H23,1),1)) -> 70294.8 | C41: =SUMIFS(tblFinancials[Amount],tblFinancials[AccountCategory],"Revenue",tblFinancials[FullDate],">="&DATE(2024,$H23,1),tblFinancials[FullDate],"<"&EDATE(DATE(2024,$H23,1),1))+SUMIFS(tblFinancials[Amount],tblFinancials[AccountCategory],"Cost of Sales",tblFinancials[FullDate],">="&DATE(2024,$H23,1),tblFinancials[FullDate],"<"&EDATE(DATE(2024,$H23,1),1))+SUMIFS(tblFinancials[Amount],tblFinancials[AccountCategory],"Operating Expense",tblFinancials[FullDate],">="&DATE(2024,$H23,1),tblFinancials[FullDate],"<"&EDATE(DATE(2024,$H23,1),1)) -> 59712.36 | D41: =SUMIFS(tblFinancials[Amount],tblFinancials[AccountCategory],"Revenue",tblFinancials[FullDate],">="&DATE(2025,$H23,1),tblFinancials[FullDate],"<"&EDATE(DATE(2025,$H23,1),1))+SUMIFS(tblFinancials[Amount],tblFinancials[AccountCategory],"Cost of Sales",tblFinancials[FullDate],">="&DATE(2025,$H23,1),tblFinancials[FullDate],"<"&EDATE(DATE(2025,$H23,1),1))+SUMIFS(tblFinancials[Amount],tblFinancials[AccountCategory],"Operating Expense",tblFinancials[FullDate],">="&DATE(2025,$H23,1),tblFinancials[FullDate],"<"&EDATE(DATE(2025,$H23,1),1)) -> 71446.99
A42: February | B42: =SUMIFS(tblFinancials[Amount],tblFinancials[AccountCategory],"Revenue",tblFinancials[FullDate],">="&DATE(2023,$H24,1),tblFinancials[FullDate],"<"&EDATE(DATE(2023,$H24,1),1))+SUMIFS(tblFinancials[Amount],tblFinancials[AccountCategory],"Cost of Sales",tblFinancials[FullDate],">="&DATE(2023,$H24,1),tblFinancials[FullDate],"<"&EDATE(DATE(2023,$H24,1),1))+SUMIFS(tblFinancials[Amount],tblFinancials[AccountCategory],"Operating Expense",tblFinancials[FullDate],">="&DATE(2023,$H24,1),tblFinancials[FullDate],"<"&EDATE(DATE(2023,$H24,1),1)) -> 57480.28 | C42: =SUMIFS(tblFinancials[Amount],tblFinancials[AccountCategory],"Revenue",tblFinancials[FullDate],">="&DATE(2024,$H24,1),tblFinancials[FullDate],"<"&EDATE(DATE(2024,$H24,1),1))+SUMIFS(tblFinancials[Amount],tblFinancials[AccountCategory],"Cost of Sales",tblFinancials[FullDate],">="&DATE(2024,$H24,1),tblFinancials[FullDate],"<"&EDATE(DATE(2024,$H24,1),1))+SUMIFS(tblFinancials[Amount],tblFinancials[AccountCategory],"Operating Expense",tblFinancials[FullDate],">="&DATE(2024,$H24,1),tblFinancials[FullDate],"<"&EDATE(DATE(2024,$H24,1),1)) -> 63403.06 | D42: =SUMIFS(tblFinancials[Amount],tblFinancials[AccountCategory],"Revenue",tblFinancials[FullDate],">="&DATE(2025,$H24,1),tblFinancials[FullDate],"<"&EDATE(DATE(2025,$H24,1),1))+SUMIFS(tblFinancials[Amount],tblFinancials[AccountCategory],"Cost of Sales",tblFinancials[FullDate],">="&DATE(2025,$H24,1),tblFinancials[FullDate],"<"&EDATE(DATE(2025,$H24,1),1))+SUMIFS(tblFinancials[Amount],tblFinancials[AccountCategory],"Operating Expense",tblFinancials[FullDate],">="&DATE(2025,$H24,1),tblFinancials[FullDate],"<"&EDATE(DATE(2025,$H24,1),1)) -> 61029.56
A43: March | B43: =SUMIFS(tblFinancials[Amount],tblFinancials[AccountCategory],"Revenue",tblFinancials[FullDate],">="&DATE(2023,$H25,1),tblFinancials[FullDate],"<"&EDATE(DATE(2023,$H25,1),1))+SUMIFS(tblFinancials[Amount],tblFinancials[AccountCategory],"Cost of Sales",tblFinancials[FullDate],">="&DATE(2023,$H25,1),tblFinancials[FullDate],"<"&EDATE(DATE(2023,$H25,1),1))+SUMIFS(tblFinancials[Amount],tblFinancials[AccountCategory],"Operating Expense",tblFinancials[FullDate],">="&DATE(2023,$H25,1),tblFinancials[FullDate],"<"&EDATE(DATE(2023,$H25,1),1)) -> 57134.09 | C43: =SUMIFS(tblFinancials[Amount],tblFinancials[AccountCategory],"Revenue",tblFinancials[FullDate],">="&DATE(2024,$H25,1),tblFinancials[FullDate],"<"&EDATE(DATE(2024,$H25,1),1))+SUMIFS(tblFinancials[Amount],tblFinancials[AccountCategory],"Cost of Sales",tblFinancials[FullDate],">="&DATE(2024,$H25,1),tblFinancials[FullDate],"<"&EDATE(DATE(2024,$H25,1),1))+SUMIFS(tblFinancials[Amount],tblFinancials[AccountCategory],"Operating Expense",tblFinancials[FullDate],">="&DATE(2024,$H25,1),tblFinancials[FullDate],"<"&EDATE(DATE(2024,$H25,1),1)) -> 69237.5 | D43: =SUMIFS(tblFinancials[Amount],tblFinancials[AccountCategory],"Revenue",tblFinancials[FullDate],">="&DATE(2025,$H25,1),tblFinancials[FullDate],"<"&EDATE(DATE(2025,$H25,1),1))+SUMIFS(tblFinancials[Amount],tblFinancials[AccountCategory],"Cost of Sales",tblFinancials[FullDate],">="&DATE(2025,$H25,1),tblFinancials[FullDate],"<"&EDATE(DATE(2025,$H25,1),1))+SUMIFS(tblFinancials[Amount],tblFinancials[AccountCategory],"Operating Expense",tblFinancials[FullDate],">="&DATE(2025,$H25,1),tblFinancials[FullDate],"<"&EDATE(DATE(2025,$H25,1),1)) -> 81690.56
A44: April | B44: =SUMIFS(tblFinancials[Amount],tblFinancials[AccountCategory],"Revenue",tblFinancials[FullDate],">="&DATE(2023,$H26,1),tblFinancials[FullDate],"<"&EDATE(DATE(2023,$H26,1),1))+SUMIFS(tblFinancials[Amount],tblFinancials[AccountCategory],"Cost of Sales",tblFinancials[FullDate],">="&DATE(2023,$H26,1),tblFinancials[FullDate],"<"&EDATE(DATE(2023,$H26,1),1))+SUMIFS(tblFinancials[Amount],tblFinancials[AccountCategory],"Operating Expense",tblFinancials[FullDate],">="&DATE(2023,$H26,1),tblFinancials[FullDate],"<"&EDATE(DATE(2023,$H26,1),1)) -> 61356.65 | C44: =SUMIFS(tblFinancials[Amount],tblFinancials[AccountCategory],"Revenue",tblFinancials[FullDate],">="&DATE(2024,$H26,1),tblFinancials[FullDate],"<"&EDATE(DATE(2024,$H26,1),1))+SUMIFS(tblFinancials[Amount],tblFinancials[AccountCategory],"Cost of Sales",tblFinancials[FullDate],">="&DATE(2024,$H26,1),tblFinancials[FullDate],"<"&EDATE(DATE(2024,$H26,1),1))+SUMIFS(tblFinancials[Amount],tblFinancials[AccountCategory],"Operating Expense",tblFinancials[FullDate],">="&DATE(2024,$H26,1),tblFinancials[FullDate],"<"&EDATE(DATE(2024,$H26,1),1)) -> 80908.34 | D44: =SUMIFS(tblFinancials[Amount],tblFinancials[AccountCategory],"Revenue",tblFinancials[FullDate],">="&DATE(2025,$H26,1),tblFinancials[FullDate],"<"&EDATE(DATE(2025,$H26,1),1))+SUMIFS(tblFinancials[Amount],tblFinancials[AccountCategory],"Cost of Sales",tblFinancials[FullDate],">="&DATE(2025,$H26,1),tblFinancials[FullDate],"<"&EDATE(DATE(2025,$H26,1),1))+SUMIFS(tblFinancials[Amount],tblFinancials[AccountCategory],"Operating Expense",tblFinancials[FullDate],">="&DATE(2025,$H26,1),tblFinancials[FullDate],"<"&EDATE(DATE(2025,$H26,1),1)) -> 85617.77
A45: May | B45: =SUMIFS(tblFinancials[Amount],tblFinancials[AccountCategory],"Revenue",tblFinancials[FullDate],">="&DATE(2023,$H27,1),tblFinancials[FullDate],"<"&EDATE(DATE(2023,$H27,1),1))+SUMIFS(tblFinancials[Amount],tblFinancials[AccountCategory],"Cost of Sales",tblFinancials[FullDate],">="&DATE(2023,$H27,1),tblFinancials[FullDate],"<"&EDATE(DATE(2023,$H27,1),1))+SUMIFS(tblFinancials[Amount],tblFinancials[AccountCategory],"Operating Expense",tblFinancials[FullDate],">="&DATE(2023,$H27,1),tblFinancials[FullDate],"<"&EDATE(DATE(2023,$H27,1),1)) -> 72468.33 | C45: =SUMIFS(tblFinancials[Amount],tblFinancials[AccountCategory],"Revenue",tblFinancials[FullDate],">="&DATE(2024,$H27,1),tblFinancials[FullDate],"<"&EDATE(DATE(2024,$H27,1),1))+SUMIFS(tblFinancials[Amount],tblFinancials[AccountCategory],"Cost of Sales",tblFinancials[FullDate],">="&DATE(2024,$H27,1),tblFinancials[FullDate],"<"&EDATE(DATE(2024,$H27,1),1))+SUMIFS(tblFinancials[Amount],tblFinancials[AccountCategory],"Operating Expense",tblFinancials[FullDate],">="&DATE(2024,$H27,1),tblFinancials[FullDate],"<"&EDATE(DATE(2024,$H27,1),1)) -> 70291.52 | D45: =SUMIFS(tblFinancials[Amount],tblFinancials[AccountCategory],"Revenue",tblFinancials[FullDate],">="&DATE(2025,$H27,1),tblFinancials[FullDate],"<"&EDATE(DATE(2025,$H27,1),1))+SUMIFS(tblFinancials[Amount],tblFinancials[AccountCategory],"Cost of Sales",tblFinancials[FullDate],">="&DATE(2025,$H27,1),tblFinancials[FullDate],"<"&EDATE(DATE(2025,$H27,1),1))+SUMIFS(tblFinancials[Amount],tblFinancials[AccountCategory],"Operating Expense",tblFinancials[FullDate],">="&DATE(2025,$H27,1),tblFinancials[FullDate],"<"&EDATE(DATE(2025,$H27,1),1)) -> 90485.25
A46: June | B46: =SUMIFS(tblFinancials[Amount],tblFinancials[AccountCategory],"Revenue",tblFinancials[FullDate],">="&DATE(2023,$H28,1),tblFinancials[FullDate],"<"&EDATE(DATE(2023,$H28,1),1))+SUMIFS(tblFinancials[Amount],tblFinancials[AccountCategory],"Cost of Sales",tblFinancials[FullDate],">="&DATE(2023,$H28,1),tblFinancials[FullDate],"<"&EDATE(DATE(2023,$H28,1),1))+SUMIFS(tblFinancials[Amount],tblFinancials[AccountCategory],"Operating Expense",tblFinancials[FullDate],">="&DATE(2023,$H28,1),tblFinancials[FullDate],"<"&EDATE(DATE(2023,$H28,1),1)) -> 83125.32 | C46: =SUMIFS(tblFinancials[Amount],tblFinancials[AccountCategory],"Revenue",tblFinancials[FullDate],">="&DATE(2024,$H28,1),tblFinancials[FullDate],"<"&EDATE(DATE(2024,$H28,1),1))+SUMIFS(tblFinancials[Amount],tblFinancials[AccountCategory],"Cost of Sales",tblFinancials[FullDate],">="&DATE(2024,$H28,1),tblFinancials[FullDate],"<"&EDATE(DATE(2024,$H28,1),1))+SUMIFS(tblFinancials[Amount],tblFinancials[AccountCategory],"Operating Expense",tblFinancials[FullDate],">="&DATE(2024,$H28,1),tblFinancials[FullDate],"<"&EDATE(DATE(2024,$H28,1),1)) -> 88646.47 | D46: =SUMIFS(tblFinancials[Amount],tblFinancials[AccountCategory],"Revenue",tblFinancials[FullDate],">="&DATE(2025,$H28,1),tblFinancials[FullDate],"<"&EDATE(DATE(2025,$H28,1),1))+SUMIFS(tblFinancials[Amount],tblFinancials[AccountCategory],"Cost of Sales",tblFinancials[FullDate],">="&DATE(2025,$H28,1),tblFinancials[FullDate],"<"&EDATE(DATE(2025,$H28,1),1))+SUMIFS(tblFinancials[Amount],tblFinancials[AccountCategory],"Operating Expense",tblFinancials[FullDate],">="&DATE(2025,$H28,1),tblFinancials[FullDate],"<"&EDATE(DATE(2025,$H28,1),1)) -> 102053
A47: July | B47: =SUMIFS(tblFinancials[Amount],tblFinancials[AccountCategory],"Revenue",tblFinancials[FullDate],">="&DATE(2023,$H29,1),tblFinancials[FullDate],"<"&EDATE(DATE(2023,$H29,1),1))+SUMIFS(tblFinancials[Amount],tblFinancials[AccountCategory],"Cost of Sales",tblFinancials[FullDate],">="&DATE(2023,$H29,1),tblFinancials[FullDate],"<"&EDATE(DATE(2023,$H29,1),1))+SUMIFS(tblFinancials[Amount],tblFinancials[AccountCategory],"Operating Expense",tblFinancials[FullDate],">="&DATE(2023,$H29,1),tblFinancials[FullDate],"<"&EDATE(DATE(2023,$H29,1),1)) -> 67162.46 | C47: =SUMIFS(tblFinancials[Amount],tblFinancials[AccountCategory],"Revenue",tblFinancials[FullDate],">="&DATE(2024,$H29,1),tblFinancials[FullDate],"<"&EDATE(DATE(2024,$H29,1),1))+SUMIFS(tblFinancials[Amount],tblFinancials[AccountCategory],"Cost of Sales",tblFinancials[FullDate],">="&DATE(2024,$H29,1),tblFinancials[FullDate],"<"&EDATE(DATE(2024,$H29,1),1))+SUMIFS(tblFinancials[Amount],tblFinancials[AccountCategory],"Operating Expense",tblFinancials[FullDate],">="&DATE(2024,$H29,1),tblFinancials[FullDate],"<"&EDATE(DATE(2024,$H29,1),1)) -> 81605.49 | D47: =SUMIFS(tblFinancials[Amount],tblFinancials[AccountCategory],"Revenue",tblFinancials[FullDate],">="&DATE(2025,$H29,1),tblFinancials[FullDate],"<"&EDATE(DATE(2025,$H29,1),1))+SUMIFS(tblFinancials[Amount],tblFinancials[AccountCategory],"Cost of Sales",tblFinancials[FullDate],">="&DATE(2025,$H29,1),tblFinancials[FullDate],"<"&EDATE(DATE(2025,$H29,1),1))+SUMIFS(tblFinancials[Amount],tblFinancials[AccountCategory],"Operating Expense",tblFinancials[FullDate],">="&DATE(2025,$H29,1),tblFinancials[FullDate],"<"&EDATE(DATE(2025,$H29,1),1)) -> 96447.47
A48: August | B48: =SUMIFS(tblFinancials[Amount],tblFinancials[AccountCategory],"Revenue",tblFinancials[FullDate],">="&DATE(2023,$H30,1),tblFinancials[FullDate],"<"&EDATE(DATE(2023,$H30,1),1))+SUMIFS(tblFinancials[Amount],tblFinancials[AccountCategory],"Cost of Sales",tblFinancials[FullDate],">="&DATE(2023,$H30,1),tblFinancials[FullDate],"<"&EDATE(DATE(2023,$H30,1),1))+SUMIFS(tblFinancials[Amount],tblFinancials[AccountCategory],"Operating Expense",tblFinancials[FullDate],">="&DATE(2023,$H30,1),tblFinancials[FullDate],"<"&EDATE(DATE(2023,$H30,1),1)) -> 74038.51 | C48: =SUMIFS(tblFinancials[Amount],tblFinancials[AccountCategory],"Revenue",tblFinancials[FullDate],">="&DATE(2024,$H30,1),tblFinancials[FullDate],"<"&EDATE(DATE(2024,$H30,1),1))+SUMIFS(tblFinancials[Amount],tblFinancials[AccountCategory],"Cost of Sales",tblFinancials[FullDate],">="&DATE(2024,$H30,1),tblFinancials[FullDate],"<"&EDATE(DATE(2024,$H30,1),1))+SUMIFS(tblFinancials[Amount],tblFinancials[AccountCategory],"Operating Expense",tblFinancials[FullDate],">="&DATE(2024,$H30,1),tblFinancials[FullDate],"<"&EDATE(DATE(2024,$H30,1),1)) -> 87523.16 | D48: =SUMIFS(tblFinancials[Amount],tblFinancials[AccountCategory],"Revenue",tblFinancials[FullDate],">="&DATE(2025,$H30,1),tblFinancials[FullDate],"<"&EDATE(DATE(2025,$H30,1),1))+SUMIFS(tblFinancials[Amount],tblFinancials[AccountCategory],"Cost of Sales",tblFinancials[FullDate],">="&DATE(2025,$H30,1),tblFinancials[FullDate],"<"&EDATE(DATE(2025,$H30,1),1))+SUMIFS(tblFinancials[Amount],tblFinancials[AccountCategory],"Operating Expense",tblFinancials[FullDate],">="&DATE(2025,$H30,1),tblFinancials[FullDate],"<"&EDATE(DATE(2025,$H30,1),1)) -> 76226.71
A49: September | B49: =SUMIFS(tblFinancials[Amount],tblFinancials[AccountCategory],"Revenue",tblFinancials[FullDate],">="&DATE(2023,$H31,1),tblFinancials[FullDate],"<"&EDATE(DATE(2023,$H31,1),1))+SUMIFS(tblFinancials[Amount],tblFinancials[AccountCategory],"Cost of Sales",tblFinancials[FullDate],">="&DATE(2023,$H31,1),tblFinancials[FullDate],"<"&EDATE(DATE(2023,$H31,1),1))+SUMIFS(tblFinancials[Amount],tblFinancials[AccountCategory],"Operating Expense",tblFinancials[FullDate],">="&DATE(2023,$H31,1),tblFinancials[FullDate],"<"&EDATE(DATE(2023,$H31,1),1)) -> 60498.58 | C49: =SUMIFS(tblFinancials[Amount],tblFinancials[AccountCategory],"Revenue",tblFinancials[FullDate],">="&DATE(2024,$H31,1),tblFinancials[FullDate],"<"&EDATE(DATE(2024,$H31,1),1))+SUMIFS(tblFinancials[Amount],tblFinancials[AccountCategory],"Cost of Sales",tblFinancials[FullDate],">="&DATE(2024,$H31,1),tblFinancials[FullDate],"<"&EDATE(DATE(2024,$H31,1),1))+SUMIFS(tblFinancials[Amount],tblFinancials[AccountCategory],"Operating Expense",tblFinancials[FullDate],">="&DATE(2024,$H31,1),tblFinancials[FullDate],"<"&EDATE(DATE(2024,$H31,1),1)) -> 65207.61 | D49: =SUMIFS(tblFinancials[Amount],tblFinancials[AccountCategory],"Revenue",tblFinancials[FullDate],">="&DATE(2025,$H31,1),tblFinancials[FullDate],"<"&EDATE(DATE(2025,$H31,1),1))+SUMIFS(tblFinancials[Amount],tblFinancials[AccountCategory],"Cost of Sales",tblFinancials[FullDate],">="&DATE(2025,$H31,1),tblFinancials[FullDate],"<"&EDATE(DATE(2025,$H31,1),1))+SUMIFS(tblFinancials[Amount],tblFinancials[AccountCategory],"Operating Expense",tblFinancials[FullDate],">="&DATE(2025,$H31,1),tblFinancials[FullDate],"<"&EDATE(DATE(2025,$H31,1),1)) -> 93794.45
A50: October | B50: =SUMIFS(tblFinancials[Amount],tblFinancials[AccountCategory],"Revenue",tblFinancials[FullDate],">="&DATE(2023,$H32,1),tblFinancials[FullDate],"<"&EDATE(DATE(2023,$H32,1),1))+SUMIFS(tblFinancials[Amount],tblFinancials[AccountCategory],"Cost of Sales",tblFinancials[FullDate],">="&DATE(2023,$H32,1),tblFinancials[FullDate],"<"&EDATE(DATE(2023,$H32,1),1))+SUMIFS(tblFinancials[Amount],tblFinancials[AccountCategory],"Operating Expense",tblFinancials[FullDate],">="&DATE(2023,$H32,1),tblFinancials[FullDate],"<"&EDATE(DATE(2023,$H32,1),1)) -> 68146.31 | C50: =SUMIFS(tblFinancials[Amount],tblFinancials[AccountCategory],"Revenue",tblFinancials[FullDate],">="&DATE(2024,$H32,1),tblFinancials[FullDate],"<"&EDATE(DATE(2024,$H32,1),1))+SUMIFS(tblFinancials[Amount],tblFinancials[AccountCategory],"Cost of Sales",tblFinancials[FullDate],">="&DATE(2024,$H32,1),tblFinancials[FullDate],"<"&EDATE(DATE(2024,$H32,1),1))+SUMIFS(tblFinancials[Amount],tblFinancials[AccountCategory],"Operating Expense",tblFinancials[FullDate],">="&DATE(2024,$H32,1),tblFinancials[FullDate],"<"&EDATE(DATE(2024,$H32,1),1)) -> 75001.53 | D50: =SUMIFS(tblFinancials[Amount],tblFinancials[AccountCategory],"Revenue",tblFinancials[FullDate],">="&DATE(2025,$H32,1),tblFinancials[FullDate],"<"&EDATE(DATE(2025,$H32,1),1))+SUMIFS(tblFinancials[Amount],tblFinancials[AccountCategory],"Cost of Sales",tblFinancials[FullDate],">="&DATE(2025,$H32,1),tblFinancials[FullDate],"<"&EDATE(DATE(2025,$H32,1),1))+SUMIFS(tblFinancials[Amount],tblFinancials[AccountCategory],"Operating Expense",tblFinancials[FullDate],">="&DATE(2025,$H32,1),tblFinancials[FullDate],"<"&EDATE(DATE(2025,$H32,1),1)) -> 96808.08
A51: November | B51: =SUMIFS(tblFinancials[Amount],tblFinancials[AccountCategory],"Revenue",tblFinancials[FullDate],">="&DATE(2023,$H33,1),tblFinancials[FullDate],"<"&EDATE(DATE(2023,$H33,1),1))+SUMIFS(tblFinancials[Amount],tblFinancials[AccountCategory],"Cost of Sales",tblFinancials[FullDate],">="&DATE(2023,$H33,1),tblFinancials[FullDate],"<"&EDATE(DATE(2023,$H33,1),1))+SUMIFS(tblFinancials[Amount],tblFinancials[AccountCategory],"Operating Expense",tblFinancials[FullDate],">="&DATE(2023,$H33,1),tblFinancials[FullDate],"<"&EDATE(DATE(2023,$H33,1),1)) -> 73340.88 | C51: =SUMIFS(tblFinancials[Amount],tblFinancials[AccountCategory],"Revenue",tblFinancials[FullDate],">="&DATE(2024,$H33,1),tblFinancials[FullDate],"<"&EDATE(DATE(2024,$H33,1),1))+SUMIFS(tblFinancials[Amount],tblFinancials[AccountCategory],"Cost of Sales",tblFinancials[FullDate],">="&DATE(2024,$H33,1),tblFinancials[FullDate],"<"&EDATE(DATE(2024,$H33,1),1))+SUMIFS(tblFinancials[Amount],tblFinancials[AccountCategory],"Operating Expense",tblFinancials[FullDate],">="&DATE(2024,$H33,1),tblFinancials[FullDate],"<"&EDATE(DATE(2024,$H33,1),1)) -> 72399.79 | D51: =SUMIFS(tblFinancials[Amount],tblFinancials[AccountCategory],"Revenue",tblFinancials[FullDate],">="&DATE(2025,$H33,1),tblFinancials[FullDate],"<"&EDATE(DATE(2025,$H33,1),1))+SUMIFS(tblFinancials[Amount],tblFinancials[AccountCategory],"Cost of Sales",tblFinancials[FullDate],">="&DATE(2025,$H33,1),tblFinancials[FullDate],"<"&EDATE(DATE(2025,$H33,1),1))+SUMIFS(tblFinancials[Amount],tblFinancials[AccountCategory],"Operating Expense",tblFinancials[FullDate],">="&DATE(2025,$H33,1),tblFinancials[FullDate],"<"&EDATE(DATE(2025,$H33,1),1)) -> 77163.12
A52: December | B52: =SUMIFS(tblFinancials[Amount],tblFinancials[AccountCategory],"Revenue",tblFinancials[FullDate],">="&DATE(2023,$H34,1),tblFinancials[FullDate],"<"&EDATE(DATE(2023,$H34,1),1))+SUMIFS(tblFinancials[Amount],tblFinancials[AccountCategory],"Cost of Sales",tblFinancials[FullDate],">="&DATE(2023,$H34,1),tblFinancials[FullDate],"<"&EDATE(DATE(2023,$H34,1),1))+SUMIFS(tblFinancials[Amount],tblFinancials[AccountCategory],"Operating Expense",tblFinancials[FullDate],">="&DATE(2023,$H34,1),tblFinancials[FullDate],"<"&EDATE(DATE(2023,$H34,1),1)) -> 80825.48 | C52: =SUMIFS(tblFinancials[Amount],tblFinancials[AccountCategory],"Revenue",tblFinancials[FullDate],">="&DATE(2024,$H34,1),tblFinancials[FullDate],"<"&EDATE(DATE(2024,$H34,1),1))+SUMIFS(tblFinancials[Amount],tblFinancials[AccountCategory],"Cost of Sales",tblFinancials[FullDate],">="&DATE(2024,$H34,1),tblFinancials[FullDate],"<"&EDATE(DATE(2024,$H34,1),1))+SUMIFS(tblFinancials[Amount],tblFinancials[AccountCategory],"Operating Expense",tblFinancials[FullDate],">="&DATE(2024,$H34,1),tblFinancials[FullDate],"<"&EDATE(DATE(2024,$H34,1),1)) -> 103246.71 | D52: =SUMIFS(tblFinancials[Amount],tblFinancials[AccountCategory],"Revenue",tblFinancials[FullDate],">="&DATE(2025,$H34,1),tblFinancials[FullDate],"<"&EDATE(DATE(2025,$H34,1),1))+SUMIFS(tblFinancials[Amount],tblFinancials[AccountCategory],"Cost of Sales",tblFinancials[FullDate],">="&DATE(2025,$H34,1),tblFinancials[FullDate],"<"&EDATE(DATE(2025,$H34,1),1))+SUMIFS(tblFinancials[Amount],tblFinancials[AccountCategory],"Operating Expense",tblFinancials[FullDate],">="&DATE(2025,$H34,1),tblFinancials[FullDate],"<"&EDATE(DATE(2025,$H34,1),1)) -> 84317.74
A53: Total Operating Income | B53: =SUM(B41:B52) -> 825871.69 | C53: =SUM(C41:C52) -> 917183.54 | D53: =SUM(D41:D52) -> 1017080.7

Sheet Assumptions
A1: CASCADE OUTDOOR MANUFACTURING
A2: FP&A Forecast Assumptions
A4: Assumption | B4: Historical | C4: Base Case | D4: Best Case | E4: Worst Case | F4: Source / Rationale
A6: Revenue Growth
A7: Revenue Growth Rate | B7: =(('Historical Trends'!D5/'Historical Trends'!B5)^(1/2))-1 -> 0.078871266 | C7: =B7 -> 0.078871266 | D7: =C7+3% -> 0.10887127 | E7: =C7-3% -> 0.048871266 | F7: 2023–2025 historical revenue CAGR; scenario range represents ±3 percentage points.
A9: Gross Margin
A10: Gross Margin % | B10: ='Historical Trends'!D8 -> 0.415 | C10: =B10 -> 0.415 | D10: =C10+1% -> 0.425 | E10: =C10-1% -> 0.405 | F10: Historical gross margin has remained approximately 41.5%; scenarios flex margin by ±1 percentage point.
A12: Operating Expenses
A13: Operating Expense Growth | B13: =ABS(('Historical Trends'!D9/'Historical Trends'!B9)^(1/2)-1) -> 0.050018118 | C13: =B13 -> 0.050018118 | D13: =C13-2% -> 0.030018118 | E13: =C13+2% -> 0.070018118 | F13: 2023–2025 historical operating expense CAGR; Best Case assumes stronger cost control, Worst Case assumes higher expense growth.
A15: Operating Profitability
A16: Operating Margin % | B16: ='Historical Trends'!D12 -> 0.20910092 | C16: =B16 -> 0.20910092 | D16: =C16+1.5% -> 0.22410092 | E16: =C16-1.5% -> 0.19410092 | F16: 2025 historical operating margin; scenarios reflect potential operating leverage or pressure.
A18: Revenue Mix
A19: Product Revenue Mix | B19: ='Historical Trends'!D17 -> 0.32769119 | C19: =B19 -> 0.32769119 | D19: =B19-2% -> 0.30769119 | E19: =B19+2% -> 0.34769119
A20: Service Revenue Mix | B20: ='Historical Trends'!D18 -> 0.42679512 | C20: =B20 -> 0.42679512 | D20: =B20 -> 0.42679512 | E20: =B20 -> 0.42679512
A21: Online Revenue Mix | B21: ='Historical Trends'!D19 -> 0.24551369 | C21: =B21 -> 0.24551369 | D21: =B21+2% -> 0.26551369 | E21: =B21-2% -> 0.22551369
A22: Revenue Mix Check | B22: =SUM(B19:B21) -> 1 | C22: =SUM(C19:C21) -> 1 | D22: =SUM(D19:D21) -> 1 | E22: =SUM(E19:E21) -> 1
A24: Monthly Revenue Seasonality
A25: Month | B25: 2023 | C25: 2024 | D25: 2025 | E25: 3-Year Average
A26: January | B26: ='Monthly Analysis'!K7 -> 0.07276906 | C26: ='Monthly Analysis'!L7 -> 0.073096525 | D26: ='Monthly Analysis'!M7 -> 0.072723527 | E26: ='Monthly Analysis'!N7 -> 0.072863037
A27: February | B27: ='Monthly Analysis'!K8 -> 0.069666674 | C27: ='Monthly Analysis'!L8 -> 0.069862364 | D27: ='Monthly Analysis'!M8 -> 0.069705702 | E27: ='Monthly Analysis'!N8 -> 0.069744913
A28: March | B28: ='Monthly Analysis'!K9 -> 0.075956086 | C28: ='Monthly Analysis'!L9 -> 0.076811275 | D28: ='Monthly Analysis'!M9 -> 0.076811263 | E28: ='Monthly Analysis'!N9 -> 0.076526208
A29: April | B29: ='Monthly Analysis'!K10 -> 0.081569706 | C29: ='Monthly Analysis'!L10 -> 0.083105269 | D29: ='Monthly Analysis'!M10 -> 0.081917271 | E29: ='Monthly Analysis'!N10 -> 0.082197415
A30: May | B30: ='Monthly Analysis'!K11 -> 0.085634199 | C30: ='Monthly Analysis'!L11 -> 0.086046942 | D30: ='Monthly Analysis'!M11 -> 0.08631105 | E30: ='Monthly Analysis'!N11 -> 0.085997397
A31: June | B31: ='Monthly Analysis'!K12 -> 0.089154298 | C31: ='Monthly Analysis'!L12 -> 0.088610004 | D31: ='Monthly Analysis'!M12 -> 0.08760994 | E31: ='Monthly Analysis'!N12 -> 0.08845808
A32: July | B32: ='Monthly Analysis'!K13 -> 0.089288161 | C32: ='Monthly Analysis'!L13 -> 0.088893653 | D32: ='Monthly Analysis'!M13 -> 0.090680953 | E32: ='Monthly Analysis'!N13 -> 0.089620922
A33: August | B33: ='Monthly Analysis'!K14 -> 0.08793126 | C33: ='Monthly Analysis'!L14 -> 0.086945191 | D33: ='Monthly Analysis'!M14 -> 0.087063307 | E33: ='Monthly Analysis'!N14 -> 0.087313253
A34: September | B34: ='Monthly Analysis'!K15 -> 0.080428966 | C34: ='Monthly Analysis'!L15 -> 0.079823509 | D34: ='Monthly Analysis'!M15 -> 0.0809731 | E34: ='Monthly Analysis'!N15 -> 0.080408525
A35: October | B35: ='Monthly Analysis'!K16 -> 0.082657937 | C35: ='Monthly Analysis'!L16 -> 0.082637188 | D35: ='Monthly Analysis'!M16 -> 0.081766442 | E35: ='Monthly Analysis'!N16 -> 0.082353856
A36: November | B36: ='Monthly Analysis'!K17 -> 0.088215798 | C36: ='Monthly Analysis'!L17 -> 0.088627766 | D36: ='Monthly Analysis'!M17 -> 0.088132849 | E36: ='Monthly Analysis'!N17 -> 0.088325471
A37: December | B37: ='Monthly Analysis'!K18 -> 0.096727855 | C37: ='Monthly Analysis'!L18 -> 0.095540315 | D37: ='Monthly Analysis'!M18 -> 0.096304596 | E37: ='Monthly Analysis'!N18 -> 0.096190922
A38: Total | B38: =SUM(B26:B37) -> 1 | C38: =SUM(C26:C37) -> 1 | D38: =SUM(D26:D37) -> 1 | E38: =SUM(E26:E37) -> 1
A41: Modeling Notes
A42: Revenue growth is based on the historical 2023–2025 revenue CAGR.
A43: Gross margin is based on the historical 2025 gross margin.
A44: Operating expense growth is based on the historical 2023–2025 operating expense CAGR.
A45: Operating margin assumptions reflect the historical 2025 operating margin and scenario flexibility.
A46: Revenue mix is based on the 2025 historical revenue mix.
A47: Monthly revenue seasonality is based on the three-year historical average.
A48: Best and Worst Case scenarios are management planning assumptions and are not historical results.
A51: Income Tax Rate | B51: 0.139 | C51: 0.139 | D51: 0.139 | E51: 0.139 | F51: 2025 effective tax rate; held constant across forecast scenarios for initial model.

Sheet Forecast Calendar
A1: CASCADE OUTDOOR MANUFACTURING
A2: Forecast Calendar
A4: Date | B4: Year | C4: Month Number | D4: Month | E4: Quarter | F4: Forecast Year
A5: =DATE(2026,1,1) -> 46023 | B5: =YEAR(A5) -> 2026 | C5: =MONTH(A5) -> 1 | D5: =TEXT(A5,"mmmm") -> January | E5: ="Q"&ROUNDUP(MONTH(A5)/3,0) -> Q1 | F5: ="FY"&YEAR(A5) -> FY2026
A6: =EDATE(A5,1) -> 46054 | B6: =YEAR(A6) -> 2026 | C6: =MONTH(A6) -> 2 | D6: =TEXT(A6,"mmmm") -> February | E6: ="Q"&ROUNDUP(MONTH(A6)/3,0) -> Q1 | F6: ="FY"&YEAR(A6) -> FY2026
A7: =EDATE(A6,1) -> 46082 | B7: =YEAR(A7) -> 2026 | C7: =MONTH(A7) -> 3 | D7: =TEXT(A7,"mmmm") -> March | E7: ="Q"&ROUNDUP(MONTH(A7)/3,0) -> Q1 | F7: ="FY"&YEAR(A7) -> FY2026
A8: =EDATE(A7,1) -> 46113 | B8: =YEAR(A8) -> 2026 | C8: =MONTH(A8) -> 4 | D8: =TEXT(A8,"mmmm") -> April | E8: ="Q"&ROUNDUP(MONTH(A8)/3,0) -> Q2 | F8: ="FY"&YEAR(A8) -> FY2026
A9: =EDATE(A8,1) -> 46143 | B9: =YEAR(A9) -> 2026 | C9: =MONTH(A9) -> 5 | D9: =TEXT(A9,"mmmm") -> May | E9: ="Q"&ROUNDUP(MONTH(A9)/3,0) -> Q2 | F9: ="FY"&YEAR(A9) -> FY2026
A10: =EDATE(A9,1) -> 46174 | B10: =YEAR(A10) -> 2026 | C10: =MONTH(A10) -> 6 | D10: =TEXT(A10,"mmmm") -> June | E10: ="Q"&ROUNDUP(MONTH(A10)/3,0) -> Q2 | F10: ="FY"&YEAR(A10) -> FY2026
A11: =EDATE(A10,1) -> 46204 | B11: =YEAR(A11) -> 2026 | C11: =MONTH(A11) -> 7 | D11: =TEXT(A11,"mmmm") -> July | E11: ="Q"&ROUNDUP(MONTH(A11)/3,0) -> Q3 | F11: ="FY"&YEAR(A11) -> FY2026
A12: =EDATE(A11,1) -> 46235 | B12: =YEAR(A12) -> 2026 | C12: =MONTH(A12) -> 8 | D12: =TEXT(A12,"mmmm") -> August | E12: ="Q"&ROUNDUP(MONTH(A12)/3,0) -> Q3 | F12: ="FY"&YEAR(A12) -> FY2026
A13: =EDATE(A12,1) -> 46266 | B13: =YEAR(A13) -> 2026 | C13: =MONTH(A13) -> 9 | D13: =TEXT(A13,"mmmm") -> September | E13: ="Q"&ROUNDUP(MONTH(A13)/3,0) -> Q3 | F13: ="FY"&YEAR(A13) -> FY2026
A14: =EDATE(A13,1) -> 46296 | B14: =YEAR(A14) -> 2026 | C14: =MONTH(A14) -> 10 | D14: =TEXT(A14,"mmmm") -> October | E14: ="Q"&ROUNDUP(MONTH(A14)/3,0) -> Q4 | F14: ="FY"&YEAR(A14) -> FY2026
A15: =EDATE(A14,1) -> 46327 | B15: =YEAR(A15) -> 2026 | C15: =MONTH(A15) -> 11 | D15: =TEXT(A15,"mmmm") -> November | E15: ="Q"&ROUNDUP(MONTH(A15)/3,0) -> Q4 | F15: ="FY"&YEAR(A15) -> FY2026
A16: =EDATE(A15,1) -> 46357 | B16: =YEAR(A16) -> 2026 | C16: =MONTH(A16) -> 12 | D16: =TEXT(A16,"mmmm") -> December | E16: ="Q"&ROUNDUP(MONTH(A16)/3,0) -> Q4 | F16: ="FY"&YEAR(A16) -> FY2026
A17: =EDATE(A16,1) -> 46388 | B17: =YEAR(A17) -> 2027 | C17: =MONTH(A17) -> 1 | D17: =TEXT(A17,"mmmm") -> January | E17: ="Q"&ROUNDUP(MONTH(A17)/3,0) -> Q1 | F17: ="FY"&YEAR(A17) -> FY2027
... A40: =EDATE(A39,1) -> 47088 | B40: =YEAR(A40) -> 2028 | C40: =MONTH(A40) -> 12 | D40: =TEXT(A40,"mmmm") -> December | E40: ="Q"&ROUNDUP(MONTH(A40)/3,0) -> Q4 | F40: ="FY"&YEAR(A40) -> FY2028

Sheet Forecast Model
A1: CASCADE OUTDOOR MANUFACTURING
A2: Corporate FP&A Budgeting & Forecasting Model
A4: Forecast Scenario | B4: Base case
A7: Forecast Summary
A9: Metric | B9: 2025 Actual | C9: 2026 Forecast | D9: 2027 Forecast | E9: 2028 Forecast
A10: Revenue | B10: ='Historical Trends'!D5 -> 4864066.1 | C10: =B10*(1+C11) -> 5247701.1 | D10: =C10*(1+D11) -> 5661594 | E10: =D10*(1+E11) -> 6108131.1
A11: Revenue Growth | C11: =Assumptions!C7 -> 0.078871266 | D11: =C11 -> 0.078871266 | E11: =D11 -> 0.078871266
A12: Gross Profit | B12: ='Historical Trends'!D7 -> 2018587.4 | C12: =C10*C13 -> 2177796 | D12: =D10*D13 -> 2349561.5 | E12: =E10*E13 -> 2534874.4
A13: Gross Margin | B13: ='Historical Trends'!D8 -> 0.415 | C13: =Assumptions!C10 -> 0.415 | D13: =C13 -> 0.415 | E13: =D13 -> 0.415
A14: Operating Expenses | B14: ='Historical Trends'!D9 -> -1001506.7 | C14: =B14*(1+C15) -> -1051600.2 | D14: =C14*(1+D15) -> -1104199.3 | E14: =D14*(1+E15) -> -1159429.2
A15: Operating Expense Growth | C15: =Assumptions!C13 -> 0.050018118 | D15: =C15 -> 0.050018118 | E15: =D15 -> 0.050018118
A16: Operating Income | B16: ='Historical Trends'!D11 -> 1017080.7 | C16: =C12+C14 -> 1126195.8 | D16: =D12+D14 -> 1245362.2 | E16: =E12+E14 -> 1375445.1
A17: Operating Margin | B17: ='Historical Trends'!D12 -> 0.20910092 | C17: =IFERROR(C16/C10,0) -> 0.21460745 | D17: =IFERROR(D16/D10,0) -> 0.21996671 | E17: =IFERROR(E16/E10,0) -> 0.22518265
A18: Net Income | B18: ='Historical Trends'!D13 -> 875531.89 | C18: =H272 -> 969654.55 | D18: =D16*(1-Assumptions!$C$51) -> 1072256.9 | E18: =E16*(1-Assumptions!$D$51) -> 1184258.3
A19: Net Profit Margin | B19: =IFERROR(B18/B10,0) -> 0.18 | C19: =IFERROR(C18/C10,0) -> 0.18477702 | D19: =IFERROR(D18/D10,0) -> 0.18939134 | E19: =IFERROR(E18/E10,0) -> 0.19388226
A21: Scenario Comparison
A22: Metric | B22: Base Case | C22: Best Case | D22: Worst Case
A23: Revenue Growth | B23: =Assumptions!C7 -> 0.078871266 | C23: =Assumptions!D7 -> 0.10887127 | D23: =Assumptions!E7 -> 0.048871266
A24: Gross Margin | B24: =Assumptions!C10 -> 0.415 | C24: =Assumptions!D10 -> 0.425 | D24: =Assumptions!E10 -> 0.405
A25: Operating Expense Growth | B25: =Assumptions!C13 -> 0.050018118 | C25: =Assumptions!D13 -> 0.030018118 | D25: =Assumptions!E13 -> 0.070018118
A26: Operating Margin | B26: =Assumptions!C16 -> 0.20910092 | C26: =Assumptions!D16 -> 0.22410092 | D26: =Assumptions!E16 -> 0.19410092
A28: Three-Year Forecast Summary
A30: Metric | B30: 2026 | C30: 2027 | D30: 2028
A31: Revenue | B31: =C10 -> 5247701.1 | C31: =D10 -> 5661594 | D31: =E10 -> 6108131.1
A32: Gross Profit | B32: =C12 -> 2177796 | C32: =D12 -> 2349561.5 | D32: =E12 -> 2534874.4
A33: Operating Expenses | B33: =C14 -> -1051600.2 | C33: =D14 -> -1104199.3 | D33: =E14 -> -1159429.2
A34: Operating Income | B34: =C16 -> 1126195.8 | C34: =D16 -> 1245362.2 | D34: =E16 -> 1375445.1
A35: Net Income | B35: =C18 -> 969654.55 | C35: =D18 -> 1072256.9 | D35: =E18 -> 1184258.3
A36: Operating Margin | B36: =C17 -> 0.21460745 | C36: =D17 -> 0.21996671 | D36: =E17 -> 0.22518265
A37: Net Profit Margin | B37: =C19 -> 0.18477702 | C37: =D19 -> 0.18939134 | D37: =E19 -> 0.19388226
A39: Three-Year Forecast Validation
A41: 2026 Revenue | B41: =B31-C10 -> 0
A42: 2027 Revenue | B42: =C31-D10 -> 0
A43: 2028 Revenue | B43: =D31-E10 -> 0
A45: Monthly Revenue Forecast
A47: Month | B47: 2025 Actual | C47: 2026 Forecast | D47: Revenue Growth | E47: Seasonality
A48: January | B48: ='Monthly Analysis'!D5 -> 353732.04 | C48: =$C$10*E48 -> 382363.44 | D48: =Assumptions!$C$7 -> 0.078871266 | E48: =Assumptions!E26 -> 0.072863037
A49: February | B49: ='Monthly Analysis'!D6 -> 339053.14 | C49: =$C$10*E49 -> 366000.46 | D49: =Assumptions!$C$7 -> 0.078871266 | E49: =Assumptions!E27 -> 0.069744913
A50: March | B50: ='Monthly Analysis'!D7 -> 373615.06 | C50: =$C$10*E50 -> 401586.67 | D50: =Assumptions!$C$7 -> 0.078871266 | E50: =Assumptions!E28 -> 0.076526208
A51: April | B51: ='Monthly Analysis'!D8 -> 398451.02 | C51: =$C$10*E51 -> 431347.47 | D51: =Assumptions!$C$7 -> 0.078871266 | E51: =Assumptions!E29 -> 0.082197415
A52: May | B52: ='Monthly Analysis'!D9 -> 419822.65 | C52: =$C$10*E52 -> 451288.64 | D52: =Assumptions!$C$7 -> 0.078871266 | E52: =Assumptions!E30 -> 0.085997397
A53: June | B53: ='Monthly Analysis'!D10 -> 426140.54 | C53: =$C$10*E53 -> 464201.57 | D53: =Assumptions!$C$7 -> 0.078871266 | E53: =Assumptions!E31 -> 0.08845808
A54: July | B54: ='Monthly Analysis'!D11 -> 441078.15 | C54: =$C$10*E54 -> 470303.82 | D54: =Assumptions!$C$7 -> 0.078871266 | E54: =Assumptions!E32 -> 0.089620922
A55: August | B55: ='Monthly Analysis'!D12 -> 423481.68 | C55: =$C$10*E55 -> 458193.86 | D55: =Assumptions!$C$7 -> 0.078871266 | E55: =Assumptions!E33 -> 0.087313253
A56: September | B56: ='Monthly Analysis'!D13 -> 393858.51 | C56: =$C$10*E56 -> 421959.91 | D56: =Assumptions!$C$7 -> 0.078871266 | E56: =Assumptions!E34 -> 0.080408525
A57: October | B57: ='Monthly Analysis'!D14 -> 397717.38 | C57: =$C$10*E57 -> 432168.42 | D57: =Assumptions!$C$7 -> 0.078871266 | E57: =Assumptions!E35 -> 0.082353856
A58: November | B58: ='Monthly Analysis'!D15 -> 428684 | C58: =$C$10*E58 -> 463505.67 | D58: =Assumptions!$C$7 -> 0.078871266 | E58: =Assumptions!E36 -> 0.088325471
A59: December | B59: ='Monthly Analysis'!D16 -> 468431.92 | C59: =$C$10*E59 -> 504781.21 | D59: =Assumptions!$C$7 -> 0.078871266 | E59: =Assumptions!E37 -> 0.096190922
A60: Total | B60: =SUM(B48:B59) -> 4864066.1 | C60: =SUM(C48:C59) -> 5247701.1 | D60: =AVERAGE(D48:D59) -> 0.078871266 | E60: =SUM(E48:E59) -> 1
A62: 2026 Revenue Reconciliation Check | B62: =C60-C10 -> 0
A65: Three-Year Monthly Revenue Forecast
A67: Month | B67: 2026 Forecast | C67: 2027 Forecast | D67: 2028 Forecast | E67: Seasonality
A68: January | B68: =C48 -> 382363.44 | C68: =$D$10*E68 -> 412520.93 | D68: =$E$10*E68 -> 445056.98 | E68: =Assumptions!$E$26 -> 0.072863037
A69: February | B69: =C49 -> 366000.46 | C69: =$D$10*E69 -> 394867.38 | D69: =$E$10*E69 -> 426011.07 | E69: =Assumptions!$E$27 -> 0.069744913
A70: March | B70: =C50 -> 401586.67 | C70: =$D$10*E70 -> 433260.32 | D70: =$E$10*E70 -> 467432.11 | E70: =Assumptions!$E$28 -> 0.076526208
A71: April | B71: =C51 -> 431347.47 | C71: =$D$10*E71 -> 465368.39 | D71: =$E$10*E71 -> 502072.59 | E71: =Assumptions!$E$29 -> 0.082197415
A72: May | B72: =C52 -> 451288.64 | C72: =$D$10*E72 -> 486882.34 | D72: =$E$10*E72 -> 525283.37 | E72: =Assumptions!$E$30 -> 0.085997397
A73: June | B73: =C53 -> 464201.57 | C73: =$D$10*E73 -> 500813.74 | D73: =$E$10*E73 -> 540313.55 | E73: =Assumptions!$E$31 -> 0.08845808
A74: July | B74: =C54 -> 470303.82 | C74: =$D$10*E74 -> 507397.27 | D74: =$E$10*E74 -> 547416.34 | E74: =Assumptions!$E$32 -> 0.089620922
A75: August | B75: =C55 -> 458193.86 | C75: =$D$10*E75 -> 494332.19 | D75: =$E$10*E75 -> 533320.79 | E75: =Assumptions!$E$33 -> 0.087313253
A76: September | B76: =C56 -> 421959.91 | C76: =$D$10*E76 -> 455240.42 | D76: =$E$10*E76 -> 491145.81 | E76: =Assumptions!$E$34 -> 0.080408525
A77: October | B77: =C57 -> 432168.42 | C77: =$D$10*E77 -> 466254.09 | D77: =$E$10*E77 -> 503028.15 | E77: =Assumptions!$E$35 -> 0.082353856
A78: November | B78: =C58 -> 463505.67 | C78: =$D$10*E78 -> 500062.95 | D78: =$E$10*E78 -> 539503.55 | E78: =Assumptions!$E$36 -> 0.088325471
A79: December | B79: =C59 -> 504781.21 | C79: =$D$10*E79 -> 544593.94 | D79: =$E$10*E79 -> 587546.76 | E79: =Assumptions!$E$37 -> 0.096190922
A80: Total | B80: =SUM(B68:B79) -> 5247701.1 | C80: =SUM(C68:C79) -> 5661594 | D80: =SUM(D68:D79) -> 6108131.1 | E80: =SUM(E68:E79) -> 1
A82: 2027 Revenue Reconciliation | B82: =C80-D10 -> 0
A83: 2028 Revenue Reconciliation | B83: =D80-E10 -> 0
A86: Three-Year Monthly Profitability Forecast
A88: Month | B88: Year | C88: Revenue | D88: Gross Margin | E88: Gross Profit | F88: Cost of Sales | G88: Operating Expenses | H88: Operating Income | I88: Tax Expense | J88: Net Income | K88: Net Margin
A89: January | B89: 2026 | C89: =B68 -> 382363.44 | D89: =Assumptions!$C$10 -> 0.415 | E89: =C89*D89 -> 158680.83 | F89: =-(C89-E89) -> -223682.62 | G89: =$C$14*E68 -> -76622.784 | H89: =E89+G89 -> 82058.044 | I89: =-H89*Assumptions!$C$51 -> -11406.068 | J89: =H89+I89 -> 70651.976 | K89: =IFERROR(J89/C89,0) -> 0.18477702
A90: February | B90: 2026 | C90: =B69 -> 366000.46 | D90: =Assumptions!$C$10 -> 0.415 | E90: =C90*D90 -> 151890.19 | F90: =-(C90-E90) -> -214110.27 | G90: =$C$14*E69 -> -73343.764 | H90: =E90+G90 -> 78546.426 | I90: =-H90*Assumptions!$C$51 -> -10917.953 | J90: =H90+I90 -> 67628.473 | K90: =IFERROR(J90/C90,0) -> 0.18477702
A91: March | B91: 2026 | C91: =B70 -> 401586.67 | D91: =Assumptions!$C$10 -> 0.415 | E91: =C91*D91 -> 166658.47 | F91: =-(C91-E91) -> -234928.2 | G91: =$C$14*E70 -> -80474.975 | H91: =E91+G91 -> 86183.491 | I91: =-H91*Assumptions!$C$51 -> -11979.505 | J91: =H91+I91 -> 74203.986 | K91: =IFERROR(J91/C91,0) -> 0.18477702
A92: April | B92: 2026 | C92: =B71 -> 431347.47 | D92: =Assumptions!$C$10 -> 0.415 | E92: =C92*D92 -> 179009.2 | F92: =-(C92-E92) -> -252338.27 | G92: =$C$14*E71 -> -86438.818 | H92: =E92+G92 -> 92570.381 | I92: =-H92*Assumptions!$C$51 -> -12867.283 | J92: =H92+I92 -> 79703.098 | K92: =IFERROR(J92/C92,0) -> 0.18477702
A93: May | B93: 2026 | C93: =B72 -> 451288.64 | D93: =Assumptions!$C$10 -> 0.415 | E93: =C93*D93 -> 187284.78 | F93: =-(C93-E93) -> -264003.85 | G93: =$C$14*E72 -> -90434.879 | H93: =E93+G93 -> 96849.904 | I93: =-H93*Assumptions!$C$51 -> -13462.137 | J93: =H93+I93 -> 83387.767 | K93: =IFERROR(J93/C93,0) -> 0.18477702
A94: June | B94: 2026 | C94: =B73 -> 464201.57 | D94: =Assumptions!$C$10 -> 0.415 | E94: =C94*D94 -> 192643.65 | F94: =-(C94-E94) -> -271557.92 | G94: =$C$14*E73 -> -93022.534 | H94: =E94+G94 -> 99621.116 | I94: =-H94*Assumptions!$C$51 -> -13847.335 | J94: =H94+I94 -> 85773.78 | K94: =IFERROR(J94/C94,0) -> 0.18477702
A95: July | B95: 2026 | C95: =B74 -> 470303.82 | D95: =Assumptions!$C$10 -> 0.415 | E95: =C95*D95 -> 195176.08 | F95: =-(C95-E95) -> -275127.73 | G95: =$C$14*E74 -> -94245.379 | H95: =E95+G95 -> 100930.7 | I95: =-H95*Assumptions!$C$51 -> -14029.368 | J95: =H95+I95 -> 86901.335 | K95: =IFERROR(J95/C95,0) -> 0.18477702
A96: August | B96: 2026 | C96: =B75 -> 458193.86 | D96: =Assumptions!$C$10 -> 0.415 | E96: =C96*D96 -> 190150.45 | F96: =-(C96-E96) -> -268043.41 | G96: =$C$14*E75 -> -91818.633 | H96: =E96+G96 -> 98331.815 | I96: =-H96*Assumptions!$C$51 -> -13668.122 | J96: =H96+I96 -> 84663.693 | K96: =IFERROR(J96/C96,0) -> 0.18477702
A97: September | B97: 2026 | C97: =B76 -> 421959.91 | D97: =Assumptions!$C$10 -> 0.415 | E97: =C97*D97 -> 175113.36 | F97: =-(C97-E97) -> -246846.55 | G97: =$C$14*E76 -> -84557.62 | H97: =E97+G97 -> 90555.74 | I97: =-H97*Assumptions!$C$51 -> -12587.248 | J97: =H97+I97 -> 77968.492 | K97: =IFERROR(J97/C97,0) -> 0.18477702
A98: October | B98: 2026 | C98: =B77 -> 432168.42 | D98: =Assumptions!$C$10 -> 0.415 | E98: =C98*D98 -> 179349.89 | F98: =-(C98-E98) -> -252818.53 | G98: =$C$14*E77 -> -86603.331 | H98: =E98+G98 -> 92746.564 | I98: =-H98*Assumptions!$C$51 -> -12891.772 | J98: =H98+I98 -> 79854.791 | K98: =IFERROR(J98/C98,0) -> 0.18477702
A99: November | B99: 2026 | C99: =B78 -> 463505.67 | D99: =Assumptions!$C$10 -> 0.415 | E99: =C99*D99 -> 192354.85 | F99: =-(C99-E99) -> -271150.82 | G99: =$C$14*E78 -> -92883.082 | H99: =E99+G99 -> 99471.771 | I99: =-H99*Assumptions!$C$51 -> -13826.576 | J99: =H99+I99 -> 85645.195 | K99: =IFERROR(J99/C99,0) -> 0.18477702
A100: December | B100: 2026 | C100: =B79 -> 504781.21 | D100: =Assumptions!$C$10 -> 0.415 | E100: =C100*D100 -> 209484.2 | F100: =-(C100-E100) -> -295297.01 | G100: =$C$14*E79 -> -101154.39 | H100: =E100+G100 -> 108329.81 | I100: =-H100*Assumptions!$C$51 -> -15057.843 | J100: =H100+I100 -> 93271.965 | K100: =IFERROR(J100/C100,0) -> 0.18477702
A101: January | B101: 2027 | C101: =C68 -> 412520.93 | D101: =Assumptions!$C$10 -> 0.415 | E101: =C101*D101 -> 171196.19 | F101: =-(C101-E101) -> -241324.75 | G101: =$D$14*E68 -> -80455.311 | H101: =E101+G101 -> 90740.874 | I101: =-H101*Assumptions!$C$51 -> -12612.982 | J101: =H101+I101 -> 78127.893 | K101: =IFERROR(J101/C101,0) -> 0.18939134
A102: February | B102: 2027 | C102: =C69 -> 394867.38 | D102: =Assumptions!$C$10 -> 0.415 | E102: =C102*D102 -> 163869.96 | F102: =-(C102-E102) -> -230997.42 | G102: =$D$14*E69 -> -77012.281 | H102: =E102+G102 -> 86857.68 | I102: =-H102*Assumptions!$C$51 -> -12073.218 | J102: =H102+I102 -> 74784.463 | K102: =IFERROR(J102/C102,0) -> 0.18939134
A103: March | B103: 2027 | C103: =C70 -> 433260.32 | D103: =Assumptions!$C$10 -> 0.415 | E103: =C103*D103 -> 179803.03 | F103: =-(C103-E103) -> -253457.29 | G103: =$D$14*E70 -> -84500.182 | H103: =E103+G103 -> 95302.849 | I103: =-H103*Assumptions!$C$51 -> -13247.096 | J103: =H103+I103 -> 82055.753 | K103: =IFERROR(J103/C103,0) -> 0.18939134
A104: April | B104: 2027 | C104: =C71 -> 465368.39 | D104: =Assumptions!$C$10 -> 0.415 | E104: =C104*D104 -> 193127.88 | F104: =-(C104-E104) -> -272240.51 | G104: =$D$14*E71 -> -90762.325 | H104: =E104+G104 -> 102365.56 | I104: =-H104*Assumptions!$C$51 -> -14228.812 | J104: =H104+I104 -> 88136.744 | K104: =IFERROR(J104/C104,0) -> 0.18939134
A105: May | B105: 2027 | C105: =C72 -> 486882.34 | D105: =Assumptions!$C$10 -> 0.415 | E105: =C105*D105 -> 202056.17 | F105: =-(C105-E105) -> -284826.17 | G105: =$D$14*E72 -> -94958.261 | H105: =E105+G105 -> 107097.91 | I105: =-H105*Assumptions!$C$51 -> -14886.609 | J105: =H105+I105 -> 92211.3 | K105: =IFERROR(J105/C105,0) -> 0.18939134
A106: June | B106: 2027 | C106: =C73 -> 500813.74 | D106: =Assumptions!$C$10 -> 0.415 | E106: =C106*D106 -> 207837.7 | F106: =-(C106-E106) -> -292976.04 | G106: =$D$14*E73 -> -97675.346 | H106: =E106+G106 -> 110162.35 | I106: =-H106*Assumptions!$C$51 -> -15312.567 | J106: =H106+I106 -> 94849.785 | K106: =IFERROR(J106/C106,0) -> 0.18939134
A107: July | B107: 2027 | C107: =C74 -> 507397.27 | D107: =Assumptions!$C$10 -> 0.415 | E107: =C107*D107 -> 210569.87 | F107: =-(C107-E107) -> -296827.41 | G107: =$D$14*E74 -> -98959.356 | H107: =E107+G107 -> 111610.51 | I107: =-H107*Assumptions!$C$51 -> -15513.861 | J107: =H107+I107 -> 96096.65 | K107: =IFERROR(J107/C107,0) -> 0.18939134
A108: August | B108: 2027 | C108: =C75 -> 494332.19 | D108: =Assumptions!$C$10 -> 0.415 | E108: =C108*D108 -> 205147.86 | F108: =-(C108-E108) -> -289184.33 | G108: =$D$14*E75 -> -96411.229 | H108: =E108+G108 -> 108736.63 | I108: =-H108*Assumptions!$C$51 -> -15114.391 | J108: =H108+I108 -> 93622.236 | K108: =IFERROR(J108/C108,0) -> 0.18939134
A109: September | B109: 2027 | C109: =C76 -> 455240.42 | D109: =Assumptions!$C$10 -> 0.415 | E109: =C109*D109 -> 188924.77 | F109: =-(C109-E109) -> -266315.65 | G109: =$D$14*E76 -> -88787.033 | H109: =E109+G109 -> 100137.74 | I109: =-H109*Assumptions!$C$51 -> -13919.146 | J109: =H109+I109 -> 86218.594 | K109: =IFERROR(J109/C109,0) -> 0.18939134
A110: October | B110: 2027 | C110: =C77 -> 466254.09 | D110: =Assumptions!$C$10 -> 0.415 | E110: =C110*D110 -> 193495.45 | F110: =-(C110-E110) -> -272758.65 | G110: =$D$14*E77 -> -90935.066 | H110: =E110+G110 -> 102560.38 | I110: =-H110*Assumptions!$C$51 -> -14255.893 | J110: =H110+I110 -> 88304.488 | K110: =IFERROR(J110/C110,0) -> 0.18939134
A111: November | B111: 2027 | C111: =C78 -> 500062.95 | D111: =Assumptions!$C$10 -> 0.415 | E111: =C111*D111 -> 207526.12 | F111: =-(C111-E111) -> -292536.83 | G111: =$D$14*E78 -> -97528.919 | H111: =E111+G111 -> 109997.2 | I111: =-H111*Assumptions!$C$51 -> -15289.611 | J111: =H111+I111 -> 94707.593 | K111: =IFERROR(J111/C111,0) -> 0.18939134
A112: December | B112: 2027 | C112: =C79 -> 544593.94 | D112: =Assumptions!$C$10 -> 0.415 | E112: =C112*D112 -> 226006.48 | F112: =-(C112-E112) -> -318587.46 | G112: =$D$14*E79 -> -106213.94 | H112: =E112+G112 -> 119792.54 | I112: =-H112*Assumptions!$C$51 -> -16651.163 | J112: =H112+I112 -> 103141.38 | K112: =IFERROR(J112/C112,0) -> 0.18939134
A113: January | B113: 2028 | C113: =D68 -> 445056.98 | D113: =Assumptions!$C$10 -> 0.415 | E113: =C113*D113 -> 184698.65 | F113: =-(C113-E113) -> -260358.34 | G113: =$E$14*E68 -> -84479.535 | H113: =E113+G113 -> 100219.11 | I113: =-H113*Assumptions!$C$51 -> -13930.456 | J113: =H113+I113 -> 86288.654 | K113: =IFERROR(J113/C113,0) -> 0.19388226
A114: February | B114: 2028 | C114: =D69 -> 426011.07 | D114: =Assumptions!$C$10 -> 0.415 | E114: =C114*D114 -> 176794.59 | F114: =-(C114-E114) -> -249216.48 | G114: =$E$14*E69 -> -80864.291 | H114: =E114+G114 -> 95930.302 | I114: =-H114*Assumptions!$C$51 -> -13334.312 | J114: =H114+I114 -> 82595.99 | K114: =IFERROR(J114/C114,0) -> 0.19388226
A115: March | B115: 2028 | C115: =D70 -> 467432.11 | D115: =Assumptions!$C$10 -> 0.415 | E115: =C115*D115 -> 193984.32 | F115: =-(C115-E115) -> -273447.79 | G115: =$E$14*E70 -> -88726.722 | H115: =E115+G115 -> 105257.6 | I115: =-H115*Assumptions!$C$51 -> -14630.807 | J115: =H115+I115 -> 90626.795 | K115: =IFERROR(J115/C115,0) -> 0.19388226
A116: April | B116: 2028 | C116: =D71 -> 502072.59 | D116: =Assumptions!$C$10 -> 0.415 | E116: =C116*D116 -> 208360.12 | F116: =-(C116-E116) -> -293712.46 | G116: =$E$14*E71 -> -95302.085 | H116: =E116+G116 -> 113058.04 | I116: =-H116*Assumptions!$C$51 -> -15715.067 | J116: =H116+I116 -> 97342.969 | K116: =IFERROR(J116/C116,0) -> 0.19388226
A117: May | B117: 2028 | C117: =D72 -> 525283.37 | D117: =Assumptions!$C$10 -> 0.415 | E117: =C117*D117 -> 217992.6 | F117: =-(C117-E117) -> -307290.77 | G117: =$E$14*E72 -> -99707.895 | H117: =E117+G117 -> 118284.7 | I117: =-H117*Assumptions!$C$51 -> -16441.574 | J117: =H117+I117 -> 101843.13 | K117: =IFERROR(J117/C117,0) -> 0.19388226
A118: June | B118: 2028 | C118: =D73 -> 540313.55 | D118: =Assumptions!$C$10 -> 0.415 | E118: =C118*D118 -> 224230.12 | F118: =-(C118-E118) -> -316083.43 | G118: =$E$14*E73 -> -102560.88 | H118: =E118+G118 -> 121669.24 | I118: =-H118*Assumptions!$C$51 -> -16912.024 | J118: =H118+I118 -> 104757.21 | K118: =IFERROR(J118/C118,0) -> 0.19388226
A119: July | B119: 2028 | C119: =D74 -> 547416.34 | D119: =Assumptions!$C$10 -> 0.415 | E119: =C119*D119 -> 227177.78 | F119: =-(C119-E119) -> -320238.56 | G119: =$E$14*E74 -> -103909.12 | H119: =E119+G119 -> 123268.66 | I119: =-H119*Assumptions!$C$51 -> -17134.344 | J119: =H119+I119 -> 106134.32 | K119: =IFERROR(J119/C119,0) -> 0.19388226
...

Sheet Headcount Plan
A1: CASCADE OUTDOOR MANUFACTURING
A2: Corporate FP&A — Headcount Planning Model
A3: 2025 Actual | 2026–2028 Forecast
A5: Headcount Planning Summary | H5: Headcount Planning Assumptions
A7: Business Unit | B7: 2025 Actual | C7: 2026 Forecast | D7: 2027 Forecast | E7: 2028 Forecast | F7: CAGR | H7: Assumption | I7: Rate
A8: Manufacturing | B8: 38 | C8: =ROUND(B8*(1+$I$8),0) -> 40 | D8: =ROUND(C8*(1+$I$8),0) -> 42 | E8: =ROUND(D8*(1+$I$8),0) -> 44 | F8: =IFERROR((E8/B8)^(1/3)-1,0) -> 0.050081547 | H8: Annual Headcount Growth | I8: 0.05
A9: Wholesale | B9: 16 | C9: =ROUND(B9*(1+$I$8),0) -> 17 | D9: =ROUND(C9*(1+$I$8),0) -> 18 | E9: =ROUND(D9*(1+$I$8),0) -> 19 | F9: =IFERROR((E9/B9)^(1/3)-1,0) -> 0.058955896 | H9: Annual Turnover Rate | I9: 0.08
A10: Retail | B10: 24 | C10: =ROUND(B10*(1+$I$8),0) -> 25 | D10: =ROUND(C10*(1+$I$8),0) -> 26 | E10: =ROUND(D10*(1+$I$8),0) -> 27 | F10: =IFERROR((E10/B10)^(1/3)-1,0) -> 0.040041912 | H10: Annual Salary Growth | I10: 0.035
A11: E-Commerce | B11: 14 | C11: =ROUND(B11*(1+$I$8),0) -> 15 | D11: =ROUND(C11*(1+$I$8),0) -> 16 | E11: =ROUND(D11*(1+$I$8),0) -> 17 | F11: =IFERROR((E11/B11)^(1/3)-1,0) -> 0.066858844 | H11: Employer Payroll Burden | I11: 0.12
A12: Total Headcount | B12: =SUM(B8:B11) -> 92 | C12: =SUM(C8:C11) -> 97 | D12: =SUM(D8:D11) -> 102 | E12: =SUM(E8:E11) -> 107 | F12: =IFERROR((E12/B12)^(1/3)-1,0) -> 0.05163569
A15: Headcount Movement
A17: Metric | B17: 2025 Actual | C17: 2026 Forecast | D17: 2027 Forecast | E17: 2028 Forecast | F17: Notes
A18: Average Headcount | B18: =B12 -> 92 | C18: =AVERAGE(B12,C12) -> 94.5 | D18: =AVERAGE(C12,D12) -> 99.5 | E18: =AVERAGE(D12,E12) -> 104.5
A19: New Hires | B19: 0 | C19: =MAX(C12-B12,0) -> 5 | D19: =MAX(D12-C12,0) -> 5 | E19: =MAX(E12-D12,0) -> 5
A20: Employee Departures | B20: 0 | C20: =ROUND(B18*$I$9,0) -> 7 | D20: =ROUND(C18*$I$9,0) -> 8 | E20: =ROUND(D18*$I$9,0) -> 8
A21: Net Headcount Change | B21: 0 | C21: =C12-B12 -> 5 | D21: =D12-C12 -> 5 | E21: =E12-D12 -> 5
A24: Compensation Planning
A26: Business Unit | B26: 2025 Avg Salary | C26: 2026 Avg Salary | D26: 2027 Avg Salary | E26: 2028 Avg Salary | F26: Salary CAGR
A27: Manufacturing | B27: 58000 | C27: =B27*(1+$I$10) -> 60030 | D27: =C27*(1+$I$10) -> 62131.05 | E27: =D27*(1+$I$10) -> 64305.637 | F27: =IFERROR((E27/B27)^(1/3)-1,0) -> 0.035
A28: Wholesale | B28: 62000 | C28: =B28*(1+$I$10) -> 64170 | D28: =C28*(1+$I$10) -> 66415.95 | E28: =D28*(1+$I$10) -> 68740.508 | F28: =IFERROR((E28/B28)^(1/3)-1,0) -> 0.035
A29: Retail | B29: 45000 | C29: =B29*(1+$I$10) -> 46575 | D29: =C29*(1+$I$10) -> 48205.125 | E29: =D29*(1+$I$10) -> 49892.304 | F29: =IFERROR((E29/B29)^(1/3)-1,0) -> 0.035
A30: E-Commerce | B30: 55000 | C30: =B30*(1+$I$10) -> 56925 | D30: =C30*(1+$I$10) -> 58917.375 | E30: =D30*(1+$I$10) -> 60979.483 | F30: =IFERROR((E30/B30)^(1/3)-1,0) -> 0.035
A31: Weighted Average | B31: =SUMPRODUCT(B27:B30,B8:B11)/B12 -> 54847.826 | C31: =SUMPRODUCT(C27:C30,C8:C11)/C12 -> 56807.629 | D31: =SUMPRODUCT(D27:D30,D8:D11)/D12 -> 58833.357 | E31: =SUMPRODUCT(E27:E30,E8:E11)/E12 -> 60927.674
A34: Total Compensation Expense
A36: Business Unit | B36: 2025 Actual | C36: 2026 Forecast | D36: 2027 Forecast | E36: 2028 Forecast | F36: Growth
A37: Manufacturing | B37: =B8*B27 -> 2204000 | C37: =C8*C27 -> 2401200 | D37: =D8*D27 -> 2609504.1 | E37: =E8*E27 -> 2829448 | F37: =IFERROR((E37/B37)^(1/3)-1,0) -> 0.086834401
A38: Wholesale | B38: =B9*B28 -> 992000 | C38: =C9*C28 -> 1090890 | D38: =D9*D28 -> 1195487.1 | E38: =E9*E28 -> 1306069.7 | F38: =IFERROR((E38/B38)^(1/3)-1,0) -> 0.096019352
A39: Retail | B39: =B10*B29 -> 1080000 | C39: =C10*C29 -> 1164375 | D39: =D10*D29 -> 1253333.2 | E39: =E10*E29 -> 1347092.2 | F39: =IFERROR((E39/B39)^(1/3)-1,0) -> 0.076443378
A40: E-Commerce | B40: =B11*B30 -> 770000 | C40: =C11*C30 -> 853875 | D40: =D11*D30 -> 942678 | E40: =E11*E30 -> 1036651.2 | F40: =IFERROR((E40/B40)^(1/3)-1,0) -> 0.1041989
A41: Total Compensation | B41: =SUM(B37:B40) -> 5046000 | C41: =SUM(C37:C40) -> 5510340 | D41: =SUM(D37:D40) -> 6001002.4 | E41: =SUM(E37:E40) -> 6519261.1 | F41: =IFERROR((E41/B41)^(1/3)-1,0) -> 0.089140004
A44: Total Employment Cost
A46: Metric | B46: 2025 Actual | C46: 2026 Forecast | D46: 2027 Forecast | E46: 2028 Forecast
A47: Base Compensation | B47: =B41 -> 5046000 | C47: =C41 -> 5510340 | D47: =D41 -> 6001002.4 | E47: =E41 -> 6519261.1
A48: Employer Payroll Burden | B48: =B47*$I$11 -> 605520 | C48: =C47*$I$11 -> 661240.8 | D48: =D47*$I$11 -> 720120.29 | E48: =E47*$I$11 -> 782311.33
A49: Total Employment Cost | B49: =B47+B48 -> 5651520 | C49: =C47+C48 -> 6171580.8 | D49: =D47+D48 -> 6721122.7 | E49: =E47+E48 -> 7301572.4
A52: Headcount Plan Validation
A54: 2025 Headcount | B54: =B12 -> 92
A55: 2026 Headcount | B55: =C12 -> 97
A56: 2027 Headcount | B56: =D12 -> 102
A57: 2028 Headcount | B57: =E12 -> 107
A59: Headcount Growth Validation
A61: 2026 Net Change | B61: =C12-B12 -> 5
A62: 2027 Net Change | B62: =D12-C12 -> 5
A63: 2028 Net Change | B63: =E12-D12 -> 5
A66: Workforce Cost Summary
A68: Metric | B68: 2025 Actual | C68: 2026 Forecast | D68: 2027 Forecast | E68: 2028 Forecast
A69: Base Compensation | B69: =B41 -> 5046000 | C69: =C41 -> 5510340 | D69: =D41 -> 6001002.4 | E69: =E41 -> 6519261.1
A70: Employer Payroll Burden | B70: =B48 -> 605520 | C70: =C48 -> 661240.8 | D70: =D48 -> 720120.29 | E70: =E48 -> 782311.33
A71: Total Employment Cost | B71: =B49 -> 5651520 | C71: =C49 -> 6171580.8 | D71: =D49 -> 6721122.7 | E71: =E49 -> 7301572.4
A72: Employment Cost Growth | C72: =IFERROR(C71/B71-1,0) -> 0.092021403 | D72: =IFERROR(D71/C71-1,0) -> 0.089043952 | E72: =IFERROR(E71/D71-1,0) -> 0.086362014
A74: Employment Cost as % of Revenue | B74: =B71/'Historical Trends'!B5 -> 1.3523997 | C74: =C71/'Forecast Model'!C10 -> 1.1760542 | D74: =D71/'Forecast Model'!D10 -> 1.1871432 | E74: =E71/'Forecast Model'!E10 -> 1.1953857
A76: Revenue per Employee | B76: ='Historical Trends'!D5/B12 -> 52870.284 | C76: ='Forecast Model'!C10/C12 -> 54100.012 | D76: ='Forecast Model'!D10/D12 -> 55505.823 | E76: ='Forecast Model'!E10/E12 -> 57085.337
A77: Revenue per Employee Growth | C77: =IFERROR(C76/B76-1,0) -> 0.023259345 | D77: =IFERROR(D76/C76-1,0) -> 0.02598542 | E77: =IFERROR(E76/D76-1,0) -> 0.028456721
A80: Workforce KPIs
A82: KPI | B82: 2025 | C82: 2028
A83: Total Headcount | B83: =B12 -> 92 | C83: =B12 -> 92
A84: Total Employment Cost | B84: =B71 -> 5651520 | C84: =E71 -> 7301572.4
A85: Employment Cost % of Revenue | B85: =B74 -> 1.3523997 | C85: =E74 -> 1.1953857
A86: Revenue per Employee | B86: =B76 -> 52870.284 | C86: =E76 -> 57085.337

Sheet CapEx Plan
A1: CASCADE OUTDOOR MANUFACTURING
A2: Corporate FP&A — Capital Expenditure Planning Model
A3: 2025 Actual | 2026–2028 Forecast
A5: Capital Expenditure Planning Summary | G5: CapEx Planning Assumptions
A7: Business Unit | B7: 2025 Actual | C7: 2026 Forecast | D7: 2027 Forecast | E7: 2028 Forecast | G7: Assumption | H7: Rate
A8: Manufacturing | B8: 180000 | C8: =B8*(1+$H$8) -> 189000 | D8: =C8*(1+$H$8) -> 198450 | E8: =D8*(1+$H$8) -> 208372.5 | G8: Annual CapEx Growth | H8: 0.05
A9: Wholesale | B9: 65000 | C9: =B9*(1+$H$8) -> 68250 | D9: =C9*(1+$H$8) -> 71662.5 | E9: =D9*(1+$H$8) -> 75245.625 | G9: Useful Life | H9: 5
A10: Retail | B10: 90000 | C10: =B10*(1+$H$8) -> 94500 | D10: =C10*(1+$H$8) -> 99225 | E10: =D10*(1+$H$8) -> 104186.25
A11: E-Commerce | B11: 75000 | C11: =B11*(1+$H$8) -> 78750 | D11: =C11*(1+$H$8) -> 82687.5 | E11: =D11*(1+$H$8) -> 86821.875 | G11: Depreciation Method | H11: Straight-Line
A12: Total CapEx | B12: =SUM(B8:B11) -> 410000 | C12: =SUM(C8:C11) -> 430500 | D12: =SUM(D8:D11) -> 452025 | E12: =SUM(E8:E11) -> 474626.25 | G12: Residual Value | H12: 0
A14: CapEx Growth | C14: =IFERROR(C12/B12-1,0) -> 0.05 | D14: =IFERROR(D12/C12-1,0) -> 0.05 | E14: =IFERROR(E12/D12-1,0) -> 0.05
A16: CapEx as % of Revenue | B16: =B12/'Historical Trends'!D5 -> 0.084291618 | C16: =C12/'Forecast Model'!C10 -> 0.082035922 | D16: =D12/'Forecast Model'!D10 -> 0.079840589 | E16: =E12/'Forecast Model'!E10 -> 0.077704006
A19: Capital Expenditure by Category
A21: Category | B21: 2025 Actual | C21: 2026 Forecast | D21: 2027 Forecast | E21: 2028 Forecast | F21: % of Total
A22: Equipment & Machinery | B22: 205000 | C22: =B22*(1+$H$8) -> 215250 | D22: =C22*(1+$H$8) -> 226012.5 | E22: =D22*(1+$H$8) -> 237313.12 | F22: =IFERROR(B22/B26,0) -> 0.5
A23: Technology & Software | B23: 82000 | C23: =B23*(1+$H$8) -> 86100 | D23: =C23*(1+$H$8) -> 90405 | E23: =D23*(1+$H$8) -> 94925.25 | F23: =IFERROR(B23/B26,0) -> 0.2
A24: Facilities & Improvements | B24: 82000 | C24: =B24*(1+$H$8) -> 86100 | D24: =C24*(1+$H$8) -> 90405 | E24: =D24*(1+$H$8) -> 94925.25 | F24: =IFERROR(B24/B26,0) -> 0.2
A25: Vehicles & Other | B25: 41000 | C25: =B25*(1+$H$8) -> 43050 | D25: =C25*(1+$H$8) -> 45202.5 | E25: =D25*(1+$H$8) -> 47462.625 | F25: =IFERROR(B25/B26,0) -> 0.1
A26: Total CapEx | B26: =SUM(B22:B25) -> 410000 | C26: =SUM(C22:C25) -> 430500 | D26: =SUM(D22:D25) -> 452025 | E26: =SUM(E22:E25) -> 474626.25 | F26: =SUM(F22:F25) -> 1
A29: Depreciation Planning
A31: Metric | B31: 2025 Actual | C31: 2026 Forecast | D31: 2027 Forecast | E31: 2028 Forecast
A32: Depreciation from New CapEx | B32: =B26/$H$9 -> 82000 | C32: =C26/$H$9 -> 86100 | D32: =D26/$H$9 -> 90405 | E32: =E26/$H$9 -> 94925.25
A33: Total Depreciation Expense | B33: 82000 | C33: =B26/$H$9+C26/$H$9 -> 168100 | D33: =B26/$H$9+C26/$H$9+D26/$H$9 -> 258505 | E33: =B26/$H$9+C26/$H$9+D26/$H$9+E26/$H$9 -> 353430.25
A34: Depreciation Growth | B34: =IFERROR(C33/B33-1,0) -> 1.05 | C34: =IFERROR(D33/C33-1,0) -> 0.53780488 | D34: =IFERROR(E33/D33-1,0) -> 0.36720856
A37: Capital Planning KPIs
A39: KPI | B39: 2025 | C39: 2028
A40: Total CapEx | B40: =B12 -> 410000 | C40: =E12 -> 474626.25
A41: CapEx as % of Revenue | B41: =B16 -> 0.084291618 | C41: =E16 -> 0.077704006
A42: Depreciation Expense | B42: =B33 -> 82000 | C42: =E33 -> 353430.25

Sheet Cash Flow Plan
A1: CASCADE OUTDOOR MANUFACTURING
A2: Corporate FP&A — Cash Flow Planning Model
A3: 2025 Actual | 2026–2028 Forecast
A5: 2025 Actual | 2026–2028 Forecast
A7: Metric | B7: 2025 Actual | C7: 2026 Forecast | D7: 2027 Forecast | E7: 2028 Forecast
A8: Revenue | B8: ='Historical Trends'!D5 -> 4864066.1 | C8: ='Forecast Model'!C10 -> 5247701.1 | D8: ='Forecast Model'!D10 -> 5661594 | E8: ='Forecast Model'!E10 -> 6108131.1
A9: Operating Income | B9: ='Historical Trends'!D11 -> 1017080.7 | C9: ='Forecast Model'!C16 -> 1126195.8 | D9: ='Forecast Model'!D16 -> 1245362.2 | E9: ='Forecast Model'!E16 -> 1375445.1
A10: Depreciation Expense | B10: ='CapEx Plan'!B33 -> 82000 | C10: ='CapEx Plan'!C33 -> 168100 | D10: ='CapEx Plan'!D33 -> 258505 | E10: ='CapEx Plan'!E33 -> 353430.25
A11: Operating Cash Flow | B11: =B9+B10 -> 1099080.7 | C11: =C9+C10 -> 1294295.8 | D11: =D9+D10 -> 1503867.2 | E11: =E9+E10 -> 1728875.4
A13: Capital Expenditures | B13: ='CapEx Plan'!B12 -> 410000 | C13: ='CapEx Plan'!C12 -> 430500 | D13: ='CapEx Plan'!D12 -> 452025 | E13: ='CapEx Plan'!E12 -> 474626.25
A14: Free Cash Flow | B14: =B11-B13 -> 689080.7 | C14: =C11-C13 -> 863795.76 | D14: =D11-D13 -> 1051842.2 | E14: =E11-E13 -> 1254249.1 | G14: Starting Cash Balance | H14: 1000000
G15: Source / Rationale | H15: Management planning assumption; replace with actual 2025 year-end cash when available.
A16: Free Cash Flow Margin | B16: =IFERROR(B14/B8,0) -> 0.14166763 | C16: =IFERROR(C14/C8,0) -> 0.1646046 | D16: =IFERROR(D14/D8,0) -> 0.18578553 | E16: =IFERROR(E14/E8,0) -> 0.2053409
A19: Cash Balance Forecast
A21: Metric | B21: 2025 Actual | C21: 2026 Forecast | D21: 2027 Forecast | E21: 2028 Forecast
A22: Beginning Cash | B22: =H14 -> 1000000 | C22: =B24 -> 1689080.7 | D22: =C24 -> 2552876.5 | E22: =D24 -> 3604718.7
A23: Free Cash Flow | B23: =B14 -> 689080.7 | C23: =C14 -> 863795.76 | D23: =D14 -> 1051842.2 | E23: =E14 -> 1254249.1
A24: Ending Cash | B24: =B22+B23 -> 1689080.7 | C24: =C22+C23 -> 2552876.5 | D24: =D22+D23 -> 3604718.7 | E24: =E22+E23 -> 4858967.8
A27: Cash Flow Analysis
A29: Free Cash Flow Growth | C29: =IFERROR(C14/B14-1,0) -> 0.25354804 | D29: =IFERROR(D14/C14-1,0) -> 0.21769783 | E29: =IFERROR(E14/D14-1,0) -> 0.19243088
A30: Operating Cash Flow Margin | B30: =IFERROR(B11/B8,0) -> 0.22595924 | C30: =IFERROR(C11/C8,0) -> 0.24664052 | D30: =IFERROR(D11/D8,0) -> 0.26562612 | E30: =IFERROR(E11/E8,0) -> 0.28304491
A31: CapEx as % of Operating Cash Flow | B31: =IFERROR(B13/B11,0) -> 0.37303903 | C31: =IFERROR(C13/C11,0) -> 0.33261331 | D31: =IFERROR(D13/D11,0) -> 0.30057507 | E31: =IFERROR(E13/E11,0) -> 0.27452889
A34: Cash Flow KPIs
A36: KPI | B36: 2025 | C36: 2028
A37: Operating Cash Flow | B37: =B11 -> 1099080.7 | C37: =E11 -> 1728875.4
A38: Capital Expenditures | B38: =B13 -> 410000 | C38: =E13 -> 474626.25
A39: Free Cash Flow | B39: =B14 -> 689080.7 | C39: =E14 -> 1254249.1
A40: Free Cash Flow Margin | B40: =B16 -> 0.14166763 | C40: =E16 -> 0.2053409
A41: Ending Cash
A44: Working Capital Planning
A46: Metric | B46: 2025 Actual | C46: 2026 Forecast | D46: 2027 Forecast | E46: 2028 Forecast
A47: Accounts Receivable | B47: ='Historical Trends'!D5*8% -> 389125.29 | C47: =C8*8% -> 419816.09 | D47: =D8*8% -> 452927.52 | E47: =E8*8% -> 488650.48
A48: Inventory | B48: =B8*6% -> 291843.97 | C48: =C8*6% -> 314862.07 | D48: =D8*6% -> 339695.64 | E48: =E8*6% -> 366487.86
A49: Accounts Payable | B49: =B8*5% -> 243203.3 | C49: =C8*5% -> 262385.06 | D49: =D8*5% -> 283079.7 | E49: =E8*5% -> 305406.55
A50: Accrued Expenses | B50: =B8*3% -> 145921.98 | C50: =C8*3% -> 157431.03 | D50: =D8*3% -> 169847.82 | E50: =E8*3% -> 183243.93
A52: Net Working Capital | B52: =B47+B48-B49-B50 -> 291843.97 | C52: =C47+C48-C49-C50 -> 314862.07 | D52: =D47+D48-D49-D50 -> 339695.64 | E52: =E47+E48-E49-E50 -> 366487.86
A53: Change in Working Capital | C53: =C52-B52 -> 23018.103 | D53: =D52-C52 -> 24833.57 | E53: =E52-D52 -> 26792.225
A54: Working Capital as % of Revenue | B54: =IFERROR(B52/B8,0) -> 0.06 | C54: =IFERROR(C52/C8,0) -> 0.06 | D54: =IFERROR(D52/D8,0) -> 0.06 | E54: =IFERROR(E52/E8,0) -> 0.06
A57: Adjusted Free Cash Flow
A59: Operating Cash Flow | B59: =B11 -> 1099080.7 | C59: =C11 -> 1294295.8 | D59: =D11 -> 1503867.2 | E59: =E11 -> 1728875.4
A60: Change in Working Capital | B60: 0 | C60: =C53 -> 23018.103 | D60: =D53 -> 24833.57 | E60: =E53 -> 26792.225
A61: Capital Expenditures | B61: =B13 -> 410000 | C61: =C13 -> 430500 | D61: =D13 -> 452025 | E61: =E13 -> 474626.25
A62: Adjusted Free Cash Flow | B62: =B59-B60-B61 -> 689080.7 | C62: =C59-C60-C61 -> 840777.66 | D62: =D59-D60-D61 -> 1027008.7 | E62: =E59-E60-E61 -> 1227456.9
A65: Working Capital Cash Flow Impact
A67: 2026 | B67: =-C53 -> -23018.103
A68: 2027 | B68: =-D53 -> -24833.57
A69: 2028 | B69: =-E53 -> -26792.225
A72: Liquidity Planning KPIs
A74: KPI | B74: 2026 | C74: 2028
A75: Ending Cash | B75: =C24 -> 2552876.5 | C75: =E24 -> 4858967.8
A76: Adjusted Free Cash Flow | B76: =C62 -> 840777.66 | C76: =E62 -> 1227456.9
A77: Working Capital as % of Revenue | B77: =C54 -> 0.06 | C77: =E54 -> 0.06
A79: Liquidity Risk Indicator | B79: 2026 | C79: 2028
B80: =IF(C24<0,"HIGH RISK",IF(C24<'Cash Flow Plan'!$H$14,"MONITOR","LOW RISK")) -> LOW RISK | C80: =IF(E24<0,"HIGH RISK",IF(E24<'Cash Flow Plan'!$H$14,"MONITOR","LOW RISK")) -> LOW RISK
A82: Cash Flow Validation Checks
A84: 2026 Ending Cash | B84: =C22+C23 -> 2552876.5 | C84: =C24 -> 2552876.5 | D84: =IF(ABS(B84-C84)<1,"PASS","CHECK") -> PASS
A85: 2027 Ending Cash | B85: =D22+D23 -> 3604718.7 | C85: =D24 -> 3604718.7 | D85: =IF(ABS(B85-C85)<1,"PASS","CHECK") -> PASS
A86: 2028 Ending Cash | B86: =E22+E23 -> 4858967.8 | C86: =E24 -> 4858967.8 | D86: =IF(ABS(B86-C86)<1,"PASS","CHECK") -> PASS

Sheet Scenario Analysis
A1: CASCADE OUTDOOR MANUFACTURING
A2: Corporate FP&A — Scenario Analysis
A3: Base Case | Best Case | Worst Case
A5: Scenario Financial Summary
A7: Metric | B7: Base Case | C7: Best Case | D7: Worst Case | E7: Variance vs Base
A8: Revenue Growth Rate | B8: =Assumptions!C7 -> 0.078871266 | C8: =Assumptions!D7 -> 0.10887127 | D8: =Assumptions!E7 -> 0.048871266 | E8: =C8-B8 -> 0.03
A9: Gross Margin % | B9: =Assumptions!C10 -> 0.415 | C9: =Assumptions!D10 -> 0.425 | D9: =Assumptions!E10 -> 0.405 | E9: =C9-B9 -> 0.01
A10: Operating Expense Growth | B10: =Assumptions!C13 -> 0.050018118 | C10: =Assumptions!D13 -> 0.030018118 | D10: =Assumptions!E13 -> 0.070018118 | E10: =C10-B10 -> -0.02
A11: Operating Margin % | B11: =Assumptions!C16 -> 0.20910092 | C11: =Assumptions!D16 -> 0.22410092 | D11: =Assumptions!E16 -> 0.19410092 | E11: =C11-B11 -> 0.015
A14: 2026 Scenario Forecast
A16: Metric | B16: Base Case | C16: Best Case | D16: Worst Case | E16: Best vs Worst
A17: Revenue | B17: ='Historical Trends'!D5*(1+B8) -> 5247701.1 | C17: ='Historical Trends'!D5*(1+C8) -> 5393623.1 | D17: ='Historical Trends'!D5*(1+D8) -> 5101779.2 | E17: =C17-D17 -> 291843.97
A18: Gross Profit | B18: =B17*B9 -> 2177796 | C18: =C17*C9 -> 2292289.8 | D18: =D17*D9 -> 2066220.5 | E18: =C18-D18 -> 226069.27
A19: Operating Expenses | B19: ='Historical Trends'!D10*(1+B10) -> 0.038348535 | C19: ='Historical Trends'!D10*(1+C10) -> 0.037618099 | D19: ='Historical Trends'!D10*(1+D10) -> 0.039078971 | E19: =C19-D19 -> -0.0014608714
A20: Operating Income | B20: =B18+B19 -> 2177796 | C20: =C18+C19 -> 2292289.8 | D20: =D18+D19 -> 2066220.6 | E20: =C20-D20 -> 226069.27
A21: Operating Margin | B21: =IFERROR(B20/B17,0) -> 0.415 | C21: =IFERROR(C20/C17,0) -> 0.425 | D21: =IFERROR(D20/D17,0) -> 0.405 | E21: =C21-D21 -> 0.019999999
A22: Capital Expenditures | B22: ='CapEx Plan'!C12 -> 430500 | C22: ='CapEx Plan'!C12 -> 430500 | D22: ='CapEx Plan'!C12 -> 430500 | E22: =0 -> 0
A23: Depreciation Expense | B23: ='CapEx Plan'!C33 -> 168100 | C23: ='CapEx Plan'!C33 -> 168100 | D23: ='CapEx Plan'!C33 -> 168100 | E23: 0
A24: Operating Cash Flow | B24: =B20+B23 -> 2345896 | C24: =C20+C23 -> 2460389.8 | D24: =D20+D23 -> 2234320.6 | E24: =C24-D24 -> 226069.27
A25: Free Cash Flow | B25: =B24-B22 -> 1915396 | C25: =C24-C22 -> 2029889.8 | D25: =D24-D22 -> 1803820.6 | E25: =C25-D25 -> 226069.27
A28: 2027 Scenario Forecast
A30: Metric | B30: Base Case | C30: Best Case | D30: Worst Case | E30: Best vs Worst
A31: Revenue | B31: =B17*(1+B8) -> 5661594 | C31: =C17*(1+C8) -> 5980833.7 | D31: =D17*(1+D8) -> 5351109.6 | E31: =C31-D31 -> 629724.14
A32: Gross Profit | B32: =B31*B9 -> 2349561.5 | C32: =C31*C9 -> 2541854.3 | D32: =D31*D9 -> 2167199.4 | E32: =C32-D32 -> 374654.95
A33: Operating Expenses | B33: =B19*(1+B10) -> 0.040266657 | C33: =C19*(1+C10) -> 0.038747324 | D33: =D19*(1+D10) -> 0.041815207 | E33: =C33-D33 -> -0.0030678828
A34: Operating Income | B34: =B32+B33 -> 2349561.5 | C34: =C32+C33 -> 2541854.3 | D34: =D32+D33 -> 2167199.4 | E34: =C34-D34 -> 374654.94
A35: Operating Margin | B35: =IFERROR(B34/B31,0) -> 0.415 | C35: =IFERROR(C34/C31,0) -> 0.425 | D35: =IFERROR(D34/D31,0) -> 0.405 | E35: =C35-D35 -> 0.019999999
A36: Capital Expenditures | B36: ='CapEx Plan'!D12 -> 452025 | C36: ='CapEx Plan'!D12 -> 452025 | D36: ='CapEx Plan'!D12 -> 452025 | E36: =0 -> 0
A37: Depreciation Expense | B37: ='CapEx Plan'!D33 -> 258505 | C37: ='CapEx Plan'!D33 -> 258505 | D37: ='CapEx Plan'!D33 -> 258505 | E37: =0 -> 0
A38: Operating Cash Flow | B38: =B34+B37 -> 2608066.5 | C38: =C34+C37 -> 2800359.3 | D38: =D34+D37 -> 2425704.4 | E38: =C38-D38 -> 374654.94
A39: Free Cash Flow | B39: =B38-B36 -> 2156041.5 | C39: =C38-C36 -> 2348334.3 | D39: =D38-D36 -> 1973679.4 | E39: =C39-D39 -> 374654.94
A42: 2028 Scenario Forecast
A44: Metric | B44: Base Case | C44: Best Case | D44: Worst Case | E44: Best vs Worst
A45: Revenue | B45: =B31*(1+B8) -> 6108131.1 | C45: =C31*(1+C8) -> 6631974.6 | D45: =D31*(1+D8) -> 5612625.1 | E45: =C45-D45 -> 1019349.6
A46: Gross Profit | B46: =B45*B9 -> 2534874.4 | C46: =C45*C9 -> 2818589.2 | D46: =D45*D9 -> 2273113.1 | E46: =C46-D46 -> 545476.07
A47: Operating Expenses | B47: =B33*(1+B10) -> 0.042280719 | C47: =C33*(1+C10) -> 0.039910446 | D47: =D33*(1+D10) -> 0.044743029 | E47: =C47-D47 -> -0.0048325831
A48: Operating Income | B48: =B46+B47 -> 2534874.4 | C48: =C46+C47 -> 2818589.2 | D48: =D46+D47 -> 2273113.2 | E48: =C48-D48 -> 545476.06
A49: Operating Margin | B49: =IFERROR(B48/B45,0) -> 0.415 | C49: =IFERROR(C48/C45,0) -> 0.425 | D49: =IFERROR(D48/D45,0) -> 0.405 | E49: =C49-D49 -> 0.019999998
A50: Capital Expenditures | B50: ='CapEx Plan'!E12 -> 474626.25 | C50: ='CapEx Plan'!E12 -> 474626.25 | D50: ='CapEx Plan'!E12 -> 474626.25 | E50: =0 -> 0
A51: Depreciation Expense | B51: ='CapEx Plan'!E33 -> 353430.25 | C51: ='CapEx Plan'!E33 -> 353430.25 | D51: ='CapEx Plan'!E33 -> 353430.25 | E51: =0 -> 0
A52: Operating Cash Flow | B52: =B48+B51 -> 2888304.7 | C52: =C48+C51 -> 3172019.5 | D52: =D48+D51 -> 2626543.4 | E52: =C52-D52 -> 545476.06
A53: Free Cash Flow | B53: =B52-B50 -> 2413678.4 | C53: =C52-C50 -> 2697393.2 | D53: =D52-D50 -> 2151917.2 | E53: =C53-D53 -> 545476.06
A56: Three-Year Scenario Summary
A58: Metric | B58: Base Case | C58: Best Case | D58: Worst Case | E58: Best vs Worst | F58: Range vs Base
A59: 2028 Revenue | B59: =B45 -> 6108131.1 | C59: =C45 -> 6631974.6 | D59: =D45 -> 5612625.1 | E59: =C59-D59 -> 1019349.6 | F59: =(C59-D59)/B59 -> 0.16688404
A60: 2028 Operating Income | B60: =B48 -> 2534874.4 | C60: =C48 -> 2818589.2 | D60: =D48 -> 2273113.2 | E60: =C60-D60 -> 545476.06 | F60: =(C60-D60)/B60 -> 0.21518859
A61: 2028 Operating Margin | B61: =B49 -> 0.415 | C61: =C49 -> 0.425 | D61: =D49 -> 0.405 | E61: =C61-D61 -> 0.019999998 | F61: =(C61-D61)/B61 -> 0.048192766
A62: 2028 Free Cash Flow | B62: =B53 -> 2413678.4 | C62: =C53 -> 2697393.2 | D62: =D53 -> 2151917.2 | E62: =C62-D62 -> 545476.06 | F62: =(C62-D62)/B62 -> 0.22599368
A63: 2028 Net Income | B63: =B48*(1-Assumptions!$C$51) -> 2182526.9 | C63: =C48*(1-Assumptions!$C$51) -> 2426805.3 | D63: =D48*(1-Assumptions!$C$51) -> 1957150.4 | E63: =C63-D63 -> 469654.89 | F63: =(C63-D63)/B63 -> 0.21518859
A64: 2028 Revenue Variance | B64: =C59-D59 -> 1019349.6
A65: 2028 Operating Income Variance | B65: =C60-D60 -> 545476.06
A67: Scenario Validation Checks
A68: 2026 Best Case Revenue > Base Case | B68: =IF(C17>B17,"PASS","CHECK") -> PASS
A69: 2026 Base Case Revenue > Worst Case | B69: =IF(B17>D17,"PASS","CHECK") -> PASS
A70: 2028 Best Case Revenue > Base Case | B70: =IF(C45>B45,"PASS","CHECK") -> PASS
A71: 2028 Base Case Revenue > Worst Case | B71: =IF(B45>D45,"PASS","CHECK") -> PASS
A72: 2028 Best Case Operating Margin > Worst Case | B72: =IF(C49>D49,"PASS","CHECK") -> PASS
A74: Management Scenario Interpretation | B74: 2028 Revenue | C74: 2028 Operating Income | D74: 2028 Free Cash Flow
A75: Base Case | B75: =B59 -> 6108131.1 | C75: =B60 -> 2534874.4 | D75: =B62 -> 2413678.4
A76: Best Case | B76: =C59 -> 6631974.6 | C76: =C60 -> 2818589.2 | D76: =C62 -> 2697393.2
A77: Worst Case | B77: =D59 -> 5612625.1 | C77: =D60 -> 2273113.2 | D77: =D62 -> 2151917.2
A79: Management Sensitivity Check | B79: =IF(AND(B75>C75,C75>D75,B76>C76,C76>D76,B77>C77,C77>D77),"PASS","CHECK") -> PASS

Sheet Model QA
A1: CASCADE OUTDOOR MANUFACTURING
A2: FP&A Forecasting Model — Quality Assurance
A4: Control Check | B4: Expected | C4: Actual | D4: Status
A5: 2025 Historical Revenue | B5: 4864066 | C5: ='Historical Trends'!D5 -> 4864066.1 | D5: =IF(ABS(B5-C5)<1,"PASS","CHECK") -> PASS
A6: 2025 Historical Gross Profit | B6: 2018587 | C6: ='Historical Trends'!D7 -> 2018587.4 | D6: =IF(ABS(B6-C6)<1,"PASS","CHECK") -> PASS
A7: 2025 Historical Operating Expenses | B7: -1001507 | C7: ='Historical Trends'!D9 -> -1001506.7 | D7: =IF(ABS(B7-C7)<1,"PASS","CHECK") -> PASS
A8: 2025 Historical Operating Income | B8: 1017081 | C8: ='Historical Trends'!D11 -> 1017080.7 | D8: =IF(ABS(B8-C8)<1,"PASS","CHECK") -> PASS
A9: Base Case Revenue Growth | B9: 0.079 | C9: ='Scenario Analysis'!B8 -> 0.078871266 | D9: =IF(ABS(B9-C9)<0.0002,"PASS","CHECK") -> PASS
A10: Best Case Revenue Growth | B10: 0.109 | C10: ='Scenario Analysis'!C8 -> 0.10887127 | D10: =IF(ABS(B10-C10)<0.0002,"PASS","CHECK") -> PASS
A11: Worst Case Revenue Growth | B11: 0.049 | C11: ='Scenario Analysis'!D8 -> 0.048871266 | D11: =IF(ABS(B11-C11)<0.0002,"PASS","CHECK") -> PASS
A12: Base Case Gross Margin | B12: 0.415 | C12: ='Scenario Analysis'!B9 -> 0.415 | D12: =IF(ABS(B12-C12)<0.0001,"PASS","CHECK") -> PASS
A13: Base Case Operating Expense Growth | B13: 0.05 | C13: ='Scenario Analysis'!B10 -> 0.050018118 | D13: =IF(ABS(B13-C13)<0.0001,"PASS","CHECK") -> PASS
A14: Base Case Operating Margin Assumption | B14: 0.209 | C14: ='Scenario Analysis'!B11 -> 0.20910092 | D14: =IF(ABS(B14-C14)<0.0002,"PASS","CHECK") -> PASS
A15: 2026 Base Case Revenue | B15: ='Historical Trends'!D5*(1+'Scenario Analysis'!B8) -> 5247701.1 | C15: ='Scenario Analysis'!B17 -> 5247701.1 | D15: =IF(ABS(B15-C15)<1,"PASS","CHECK") -> PASS
A16: 2026 Best Case Revenue > Base Case | B16: ='Scenario Analysis'!C17 -> 5393623.1 | C16: ='Scenario Analysis'!B17 -> 5247701.1 | D16: =IF(B16>C16,"PASS","CHECK") -> PASS
A17: 2026 Base Case Revenue > Worst Case | B17: ='Scenario Analysis'!B17 -> 5247701.1 | C17: ='Scenario Analysis'!D17 -> 5101779.2 | D17: =IF(B17>C17,"PASS","CHECK") -> PASS
A18: 2028 Best Case Revenue > Base Case | B18: ='Scenario Analysis'!C45 -> 6631974.6 | C18: ='Scenario Analysis'!B45 -> 6108131.1 | D18: =IF(B18>C18,"PASS","CHECK") -> PASS
A19: 2028 Base Case Revenue > Worst Case | B19: ='Scenario Analysis'!B45 -> 6108131.1 | C19: ='Scenario Analysis'!D45 -> 5612625.1 | D19: =IF(B19>C19,"PASS","CHECK") -> PASS
A20: 2026 Monthly Revenue Forecast Reconciliation | B20: Expected | C20: Actual | D20: Variance
B21: ='Scenario Analysis'!B17 -> 5247701.1 | C21: ='Forecast Model'!B230 -> 5247701.1 | D21: =C21-B21 -> 0
A23: Overall Model QA Result | D23: =IF(COUNTIF(D5:D21,"CHECK")=0,"PASS","CHECK MODEL") -> PASS
A24: 2026 Ending Cash Reconciliation | B24: ='Cash Flow Plan'!C24 -> 2552876.5 | C24: ='Forecast Model'!C169 -> 2552876.5 | D24: =IF(ABS(B24-C24)<1,"PASS","CHECK") -> PASS
A25: 2027 Ending Cash Reconciliation | B25: ='Cash Flow Plan'!D24 -> 3604718.7 | C25: ='Forecast Model'!D169 -> 3604718.7 | D25: =IF(ABS(B25-C25)<1,"PASS","CHECK") -> PASS
A26: 2028 Ending Cash Reconciliation | B26: ='Cash Flow Plan'!E24 -> 4858967.8 | C26: ='Forecast Model'!E169 -> 4858967.8 | D26: =IF(ABS(B26-C26)<1,"PASS","CHECK") -> PASS
A27: 2026 CapEx Reconciliation | B27: ='CapEx Plan'!C12 -> 430500 | C27: ='Forecast Model'!C158 -> 430500 | D27: =IF(ABS(B27-C27)<1,"PASS","CHECK") -> PASS
A28: 2027 CapEx Reconciliation | B28: ='CapEx Plan'!D12 -> 452025 | C28: ='Forecast Model'!D158 -> 452025 | D28: =IF(ABS(B28-C28)<1,"PASS","CHECK") -> PASS
A29: 2028 CapEx Reconciliation | B29: ='CapEx Plan'!E12 -> 474626.25 | C29: ='Forecast Model'!E158 -> 474626.25 | D29: =IF(ABS(B29-C29)<1,"PASS","CHECK") -> PASS
A30: 2026 Employment Cost Reconciliation | B30: ='Headcount Plan'!C71 -> 6171580.8 | C30: ='Forecast Model'!C149 -> 6171580.8 | D30: =IF(ABS(B30-C30)<1,"PASS","CHECK") -> PASS
A31: 2027 Employment Cost Reconciliation | B31: ='Headcount Plan'!D71 -> 6721122.7 | C31: ='Forecast Model'!D149 -> 6721122.7 | D31: =IF(ABS(B31-C31)<1,"PASS","CHECK") -> PASS
A32: 2028 Employment Cost Reconciliation | B32: ='Headcount Plan'!E71 -> 7301572.4 | C32: ='Forecast Model'!E149 -> 7301572.4 | D32: =IF(ABS(B32-C32)<1,"PASS","CHECK") -> PASS
A34: QA Notes
A35: Historical financials reconcile to the established 2023–2025 actual results.
A36: Forecast assumptions are linked to the Assumptions sheet.
A37: Base, Best, and Worst Case scenarios are linked to the established management assumptions.
A38: Scenario forecasts are designed to maintain logical ordering between Best, Base, and Worst Case outcomes.
A39: Monthly forecast totals are reconciled to the annual forecast.
